Workbook

Sheet Main Sheet
B1: ABC & Co. | F1: Annexure - D
B2: (Chartered Accountants)
B4: MATERIALITY CALCULATION
B6: Client: | C6: ABC LIMITED | E6: Prepared by:
B7: Period: | C7: Year ended June 30, 2023 | E7: Reviewed by:
B9: Audit approach for determination of materiality :
B11: Sr. # | C11: Description | D11: Ref | E11: Whether Placed in File | F11: Initial of Reviewer
B13: 1 | C13: Determine the industry as per Materiality Benchmark Table | D13: Annex. D.1.1
B14: 2 | C14: Determine the metrics that influence the economic decisions of users as a group, including the metric that will serve as the benchmark | D14: Annex. D.1.2
B15: 3 | C15: Determine the threshold % for determination of materiality | D15: Annex. D.1.3
B16: 4 | C16: Determine materiality for the financial statements as a whole, considering the metrics and qualitative factors. | D16: Annex. D.1.4
B17: 5 | C17: Analysis of the materiality amount with other metrics in the applicable industry to analyze the appropriateness of the materiality derived. | D17: Annex. D.1.5

Sheet D.1.1
B1: ='Main Sheet'!$B$1 -> ABC & Co. | F1: ='Main Sheet'!D13 -> Annex. D.1.1
B2: ='Main Sheet'!$B$2 -> (Chartered Accountants)
B4: MATERIALITY CALCULATION
B6: ='Main Sheet'!$B$6&" " &'Main Sheet'!$C$6 -> Client: ABC LIMITED | E6: Prepared by: | F6: =IF('Main Sheet'!$F$6>0,'Main Sheet'!$F$6," ")
B7: ='Main Sheet'!$B$7&" " &'Main Sheet'!$C$7 -> Period: Year ended June 30, 2023 | E7: Reviewed by: | F7: =IF('Main Sheet'!$F$7>0,'Main Sheet'!$F$7," ")
B9: ='Main Sheet'!C13 -> Determine the industry as per Materiality Benchmark Table
B11: Industry | C11: Presumed benchmark | D11: Other metrics | E11: Notes
B13: General - Manufacturing and Servicing | C13: Profit Before Tax | D13: Total Revenue | E13: The presumed likely key considerations for the users of the financial statements of profit focused entities are PBT, total revenues and net assets
D14: Net assets
B15: Not for Profit | C15: Donation / Grant income | D15: Total Assets | E15: The presumed likely key considerations for the users of the financial statements of not for profit entities are Donation / Grant income, total assets and net assets
D16: Net assets
B19: Selection of applicable industry for the engagement:
B20: The engagement team has determined "General" as relevant industry according to the Materiality Benchmark Table considering the following aspects:
B21: ABC Limited is a public unlisted company, engaged in the purchase (Local and Import), manufacturing and sale (Local and Export) of _________________________________ items. Considering the business of the company, "General" is the most appropriate industry as per Materiality Benchmark Table.
B24: Company was incorporated in __________, so the company is not in startup phase and is a profit oriented business with stable profits.

Sheet D.1.2
B1: ='Main Sheet'!$B$1 -> ABC & Co. | J1: ='Main Sheet'!D14 -> Annex. D.1.2
B2: ='Main Sheet'!$B$2 -> (Chartered Accountants)
B4: MATERIALITY CALCULATION
B6: ='Main Sheet'!$B$6&" " &'Main Sheet'!$C$6 -> Client: ABC LIMITED | I6: Prepared by: | J6: =IF('Main Sheet'!$F$6>0,'Main Sheet'!$F$6," ")
B7: ='Main Sheet'!$B$7&" " &'Main Sheet'!$C$7 -> Period: Year ended June 30, 2023 | I7: Reviewed by: | J7: =IF('Main Sheet'!$F$7>0,'Main Sheet'!$F$7," ")
B9: ='Main Sheet'!C14 -> Determine the metrics that influence the economic decisions of users as a group, including the metric that will serve as the benchmark
B11: Following matrices have been selected for the determination of materiality since the same will influence the economic decisions of users as a group, including the metric that will serve as the benchmark.
D14: Amount in Rupees | H14: Variance %
D15: =2023 -> 2023 | E15: =D15-1 -> 2022 | F15: =E15-1 -> 2021 | G15: =F15-1 -> 2020 | H15: 2022-23 | I15: 2021-22 | J15: 2020-21
B17: Total Revenue | H17: =IFERROR((D17-E17)/E17,0) -> 0 | I17: =IFERROR((E17-F17)/F17,0) -> 0 | J17: =IFERROR((F17-G17)/G17,0) -> 0
B19: Profit Before Tax | H19: =IFERROR((D19-E19)/E19,0) -> 0 | I19: =IFERROR((E19-F19)/F19,0) -> 0 | J19: =IFERROR((F19-G19)/G19,0) -> 0
B21: Total Assets | H21: =IFERROR((D21-E21)/E21,0) -> 0 | I21: =IFERROR((E21-F21)/F21,0) -> 0 | J21: =IFERROR((F21-G21)/G21,0) -> 0
B23: As per trend analysis above, we have concluded that:
B24: We have selected "____________________" as an appropriate bench mark for determination of materiality. This bench mark has been selected by us after considering the following factors: - The profit before tax is more volatile - Stakeholders are more focused on increasing revenue given its size and importance to maximize the the company's profits

Sheet D.1.3
B1: ='Main Sheet'!$B$1 -> ABC & Co. | I1: ='Main Sheet'!D15 -> Annex. D.1.3
B2: ='Main Sheet'!$B$2 -> (Chartered Accountants)
B4: MATERIALITY CALCULATION
B6: ='Main Sheet'!$B$6&" " &'Main Sheet'!$C$6 -> Client: ABC LIMITED | H6: Prepared by: | I6: =IF('Main Sheet'!$F$6>0,'Main Sheet'!$F$6," ")
B7: ='Main Sheet'!$B$7&" " &'Main Sheet'!$C$7 -> Period: Year ended June 30, 2023 | H7: Reviewed by: | I7: =IF('Main Sheet'!$F$7>0,'Main Sheet'!$F$7," ")
B9: ='Main Sheet'!C15 -> Determine the threshold % for determination of materiality
B11: Following matrices have been selected for the determination of materiality since the same will influence the economic decisions of users as a group, including the metric that will serve as the benchmark.
B14: Sr. # | C14: Factor | D14: Higher end | E14: Lower end | F14: Percentage criteria applied by ET | G14: Justification for application | H14: % for gross measure (Revenue) | I14: % for net measure (PBT)
C16: Concentration of ownership and/or management | D16: Concentration of ownership in a small number of well-informed individuals | E16: Listed or public interest entity | F16: Lower | G16: The Company is an unlisted public company hence lower percentile is chosen. | H16: 0.005 | I16: 0.05
C18: Debt arrangements | D18: Limited debt | E18: Publicly traded debt | F18: Lower | G18: The Company has no extensive debt arrangements. | H18: 0.005 | I18: 0.05
C20: Business environment | D20: The entity operates in a stable business environment | E20: The entity operates in a volatile business environment | F20: Lower | G20: The entity operates in a volatile business environment. | H20: 0.005 | I20: 0.05
D21: The operations of the entity are relatively less complex and few core business processes in which the entity is involved | E21: The entity has complex operations and/or diverse business processes. | F21: Lower | G21: The entity has less complex operations. | H21: 0.005 | I21: 0.05
C23: Other sensitivities | D23: Few changes in stakeholders have occurred or are expected | E23: Intention to list or register securities | F23: Lower | G23: There is no significant change in share holding during the year. | H23: 0.005 | I23: 0.05
C25: Applicable materiality % | H25: =AVERAGE(H16:H23) -> 0.005 | I25: =AVERAGE(I16:I23) -> 0.05
B27: Being prudent we choose __________% for materiality as a percentage of the benchmark.

Sheet D.1.4
B1: ='Main Sheet'!$B$1 -> ABC & Co. | F1: ='Main Sheet'!D16 -> Annex. D.1.4
B2: ='Main Sheet'!$B$2 -> (Chartered Accountants)
B4: MATERIALITY CALCULATION
B6: ='Main Sheet'!$B$6&" " &'Main Sheet'!$C$6 -> Client: ABC LIMITED | E6: Prepared by: | F6: =IF('Main Sheet'!$F$6>0,'Main Sheet'!$F$6," ")
B7: ='Main Sheet'!$B$7&" " &'Main Sheet'!$C$7 -> Period: Year ended June 30, 2023 | E7: Reviewed by: | F7: =IF('Main Sheet'!$F$7>0,'Main Sheet'!$F$7," ")
B9: ='Main Sheet'!C16 -> Determine materiality for the financial statements as a whole, considering the metrics and qualitative factors.
B11: Particulars | D11: Ref. | E11: Formulae | F11: Amount (PKR)
B13: Benchmark selected | C13: Total Revenue
B15: ="Amount of "&C13 -> Amount of Total Revenue | D15: ='D.1.2'!J1 -> Annex. D.1.2 | E15: A | F15: =VLOOKUP(C13,'D.1.2'!B17:D21,3,FALSE) -> 0
B17: Percentage for materiality as per KAM (Refer Annexure-III) | D17: ='D.1.3'!I1 -> Annex. D.1.3 | E17: B | F17: ='D.1.3'!H25 -> 0.005
B19: Materiality amount | E19: C = A x B | F19: =F15*F17 -> 0
B21: Performance materiality (PM) | E21: D = C x 70% | F21: =F19*70% -> 0
B23: Audit Misstatement Posting Threshold (AMPT) | E23: E = D x 5% | F23: =F21*5% -> 0
B25: =""
B26: ="As computed above, the Materiality, Performance materiality (PM) and Audit Misstatement Posting Threshold (AMPT) are determined as Rs. "&TEXT(F19,"##,###")&", Rs. "&TEXT(F21,"##,###")&" and Rs. "&TEXT(F23,"##,###")&" respectively." -> As computed above, the Materiality, Performance materiality (PM) and Audit Misstatement Posting Threshold (AMPT) are determined as Rs. , Rs. and Rs. respectively.

Sheet D.1.5
B1: ='Main Sheet'!$B$1 -> ABC & Co. | G1: ='Main Sheet'!D17 -> Annex. D.1.5
B2: ='Main Sheet'!$B$2 -> (Chartered Accountants)
B4: MATERIALITY CALCULATION
B6: ='Main Sheet'!$B$6&" " &'Main Sheet'!$C$6 -> Client: ABC LIMITED | F6: Prepared by: | G6: =IF('Main Sheet'!$F$6>0,'Main Sheet'!$F$6," ")
B7: ='Main Sheet'!$B$7&" " &'Main Sheet'!$C$7 -> Period: Year ended June 30, 2023 | F7: Reviewed by: | G7: =IF('Main Sheet'!$F$7>0,'Main Sheet'!$F$7," ")
B9: ='Main Sheet'!C17 -> Analysis of the materiality amount with other metrics in the applicable industry to analyze the appropriateness of the materiality derived.
B11: Presumed benchmark and other metrices as per Materiality benchmark table (MBT)-
B13: Particulars | D13: Ref. | E13: Presumed and other benchmarks
E15: ='D.1.2'!B17 -> Total Revenue | F15: ='D.1.2'!B19 -> Profit Before Tax | G15: ='D.1.2'!B21 -> Total Assets
B17: Amount in Rupees | D17: ='D.1.2'!J1 -> Annex. D.1.2 | E17: ='D.1.2'!D17 -> 0 | F17: ='D.1.2'!D19 -> 0 | G17: ='D.1.2'!D21 -> 0
B19: Materiality computed by engagement team | D19: ='D.1.4'!F1 -> Annex. D.1.4 | E19: ='D.1.4'!$F$19 -> 0 | F19: ='D.1.4'!$F$19 -> 0 | G19: ='D.1.4'!$F$19 -> 0
B21: Materiality as a % of other metrices | E21: =IFERROR(E19/E17,0) -> 0 | F21: =IFERROR(F19/F17,0) -> 0 | G21: =IFERROR(G19/G17,0) -> 0
B23: Range for determination of materility for metrices | E23: 0.5%-3% | F23: 3%-10% | G23: 3%-10%
B25: Conclusion
B27: The benchmark adopted by the engagament team is justified considering professional judgement and other parameters mentioned above.
B29: After establishing the upper and lower limit of materiality based of expceted full year materiality we chose the ________ limit for the determination of materiality.
