Workbook

Sheet Cover
B1: Name of Company | C1: ABC LIMITED
B2: Reporting Date | C2: =UPPER("as at "&G6) -> AS AT JUNE 30, 2023
B3: Period under Audit | C3: =UPPER("for the year ended "&G6) -> FOR THE YEAR ENDED JUNE 30, 2023
B5: Basic Information | I5: Date Value
B6: Current year presented for year from and to? | E6: July 01, 2022 | G6: June 30, 2023 | H6: 2023 | I6: 44743 | J6: 45107
B7: Comparative information presented for year from and to? | E7: July 01, 2021 | G7: June 30, 2022 | H7: 2022 | I7: 44378 | J7: 44742
B8: Total notes provided in the financial statements from and to? | E8: =Policies!A5 -> 1 | G8: =Notes!A753 -> 38
B9: Signatories | E9: Chief Executive | G9: Director
B10: Authorized share capital Number of shares and value per share. | G10: 10
B11: Functional and Presentation Currency | E11: Rupees
B12: Applicable Financial Reporting Framework | E12: Revised AFRS for SSEs
B13: Measurement method? (Cost / Revaluation) | E13: Cost | I13: Cost | J13: Revaluation
I14: IFRSs | J14: International Financial Reporting Standards issued by the International Accounting Standards Board (IASB) as notified under the Companies Act, 2017; and
I15: IFRS for SMEs | J15: International Financial Reporting Standards for Small and Medium Sized Entities (IFRS for SMEs) issued by the International Accounting Standards Board (IASB) as notified under the Companies Act, 2017; and
I16: Revised AFRS for SSEs | J16: Revised Accounting and Financial Reporting Standards for Small Sized Entities (Revised AFRS for SSEs) issued by the Institute of Chartered Accountants of Pakistan (ICAP) as notified under the Companies Act, 2017; and
I17: AFRS for NPOs | J17: Accounting and Financial Reporting Standards for Non Government Organizations and Not for Profit Organization (AFRS for NPOs) issued by the Institute of Chartered Accountants of Pakistan (ICAP); and

Sheet SOFP
B1: =Cover!C1 -> ABC LIMITED
B2: STATEMENT OF FINANCIAL POSITION
B3: =Cover!C2 -> AS AT JUNE 30, 2023
J5: Note | L5: =Cover!H6 -> 2023 | N5: =Cover!H7 -> 2022
L6: ------------- Rupees -------------
B8: ASSETS
B9: Non-current assets
B10: Property, plant and equipment | J10: =Policies!A73+1 -> 5 | L10: =FAS!L11 -> 0 | N10: =FAS!N11 -> 0
B11: Investment properties | J11: =J10+1 -> 6 | L11: =Notes!L71 -> 0 | N11: =Notes!N71 -> 0
B12: Intangible assets | J12: =J11+1 -> 7 | L12: =Notes!L91 -> 0 | N12: =Notes!N91 -> 0
B13: Long-term loans and advances | J13: =J12+1 -> 8 | L13: =Notes!L105 -> 0 | N13: =Notes!N105 -> 0
B14: Deferred tax assets | J14: =J13+1 -> 9 | L14: =Notes!L143 -> 0 | N14: =Notes!N143 -> 0
L16: =SUM(L10:L15) -> 0 | N16: =SUM(N10:N15) -> 0
B18: Current assets
B19: Stores, spares and loose tools | J19: =J14+1 -> 10 | L19: 0 | N19: 0
B20: Inventories | J20: =J19+1 -> 11 | L20: =Notes!L178 -> 0 | N20: =Notes!N178 -> 0
B21: Trade receivables - net | J21: =J20+1 -> 12 | L21: =Notes!L184 -> 0 | N21: =Notes!N184 -> 0
B22: Advances, deposits and prepayments | J22: =J21+1 -> 13 | L22: =Notes!L197 -> 0 | N22: =Notes!N197 -> 0
B23: Tax refunds due from government | L23: 0 | N23: 0
B24: Cash and cash equivalents (excluding bank overdrafts) | J24: =J22+1 -> 14 | L24: =Notes!L208 -> 0 | N24: =Notes!N208 -> 0
L26: =SUM(L20:L25) -> 0 | N26: =SUM(N20:N25) -> 0
B28: Total assets | L28: =L16+L26 -> 0 | N28: =N16+N26 -> 0
B30: EQUITY AND LIABILITIES
B31: Share capital and reserves
B32: Authorized share capital | L32: =IFERROR(Cover!E10*Cover!G10,0) -> 0 | N32: =IFERROR(Cover!E10*Cover!G10,0) -> 0
B33: =TEXT(Cover!E10,"##,###")&" Ordinary shares of Rs. "&Cover!G10 &" each." -> Ordinary shares of Rs. 10 each.
B35: Issued, subscribed and paid up share capital | J35: =J24+1 -> 15 | L35: =Notes!L230 -> 0 | N35: =Notes!N230 -> 0
B36: Share deposit money | J36: =J35+1 -> 16 | L36: =Notes!L248 -> 0 | N36: =Notes!N248 -> 0
B37: Other reserves | J37: =J36+1 -> 17 | L37: =Notes!L262 -> 0 | N37: =Notes!N262 -> 0
B38: Retained earnings | L38: =SOCIE!N22 -> 0 | N38: =SOCIE!N14 -> 0
L40: =SUM(L35:L39) -> 0 | N40: =SUM(N35:N39) -> 0
B42: Non-current liabilities
B43: Borrowings | J43: =J37+1 -> 18 | L43: =Notes!L291 -> 0 | N43: =Notes!N291 -> 0
B44: Deferred tax liabilities | J44: =J14 -> 9 | L44: 0 | N44: 0
L46: =SUM(L43:L45) -> 0 | N46: =SUM(N43:N45) -> 0
B48: Current liabilities
B49: Trade and other payables | J49: =J43+1 -> 19 | L49: =Notes!L329 -> 0 | N49: =Notes!N329 -> 0
B50: ="Current portion of "&LOWER(B43) -> Current portion of borrowings | J50: =J43 -> 18 | L50: =Notes!L290 -> 0 | N50: =Notes!N290 -> 0
B51: Payable to related parties | J51: =J49+1 -> 20 | L51: =Notes!L335 -> 0 | N51: =Notes!N335 -> 0
B52: Deferred revenue | J52: =J51+1 -> 21
B53: Provision for taxation
L55: =SUM(L49:L54) -> 0 | N55: =SUM(N49:N54) -> 0
B57: Contingencies and commitments | J57: =J52+1 -> 22 | L57: 0 | N57: 0
B59: Total liabilities | L59: =L46+L55 -> 0 | N59: =N46+N55 -> 0
B61: Total equity and liabilities | L61: =L40+L59 -> 0 | N61: =N40+N59 -> 0
B63: ="The annexed notes from "&Cover!E8&" to "&Cover!G8&" form an integral part of these financial statements." -> The annexed notes from 1 to 38 form an integral part of these financial statements.
B69: =Cover!E9 -> Chief Executive | L69: =Cover!G9 -> Director
L72: =L28-L61 -> 0 | N72: =N28-N61 -> 0

Sheet SOPL
B1: =Cover!C1 -> ABC LIMITED
B2: STATEMENT OF PROFIT OR LOSS
B3: =Cover!C3 -> FOR THE YEAR ENDED JUNE 30, 2023
J5: =SOFP!J5 -> Note | L5: =SOFP!L5 -> 2023 | N5: =SOFP!N5 -> 2022
L6: =SOFP!L6 -> ------------- Rupees -------------
B8: Revenue - net | J8: =SOFP!J57+1 -> 23 | L8: =Notes!L416 -> 0 | N8: =Notes!N416 -> 0
B10: Cost of revenue | J10: =J8+1 -> 24 | L10: =-Notes!L424 -> 0 | N10: =-Notes!N424 -> 0
B12: =IF(AND(L12>=0,N12>=0),"Gross profit",IF(AND(L12>=0,N12<0),"Gross profit / (loss)",IF(AND(L12<0,N12>=0),"Gross (loss) / profit","Gross loss"))) -> Gross profit | L12: =SUM(L8:L11) -> 0 | N12: =SUM(N8:N11) -> 0
B14: Distribution costs | J14: =J10+1 -> 25 | L14: =-Notes!L516 -> 0 | N14: =-Notes!N516 -> 0
B15: Administrative expenses | J15: =J14+1 -> 26 | L15: =-Notes!L531 -> 0 | N15: =-Notes!N531 -> 0
B16: Other operating income / (expenses) | J16: =J15+1 -> 27 | L16: =-Notes!L564 -> 0 | N16: =-Notes!N564 -> 0
B17: Other gains/(losses) | J17: =J16+1 -> 28 | L17: =-Notes!L599 -> 0 | N17: =-Notes!N599 -> 0
L19: =SUM(L14:L18) -> 0 | N19: =SUM(N14:N18) -> 0
B21: =IF(AND(L21>=0,N21>=0),"Operating profit",IF(AND(L21>=0,N21<0),"Operating profit / (loss)",IF(AND(L21<0,N21>=0),"Operating (loss) / profit","Operating loss"))) -> Operating profit | L21: =L12+L19 -> 0 | N21: =N12+N19 -> 0
B23: Other income | J23: =J17+1 -> 29 | L23: =Notes!L606 -> 0 | N23: =Notes!N606 -> 0
B24: Finance costs | J24: =J23+1 -> 30 | L24: =-Notes!L619 -> 0 | N24: =-Notes!N619 -> 0
L26: =SUM(L23:L24) -> 0 | N26: =SUM(N23:N24) -> 0
B28: =IF(AND(L28>=0,N28>=0),"Profit before tax",IF(AND(L28>=0,N28<0),"Profit / (loss) before tax",IF(AND(L28<0,N28>=0),"(Loss) / profit before tax","Loss before tax"))) -> Profit before tax | L28: =L21+L26 -> 0 | N28: =N21+N26 -> 0
B30: Taxation | J30: =J24+1 -> 31 | L30: =-Notes!L627 -> 0 | N30: =-Notes!N627 -> 0
B32: =IF(AND(L32>=0,N32>=0),"Profit after tax",IF(AND(L32>=0,N32<0),"Profit / (loss) after tax",IF(AND(L32<0,N32>=0),"(Loss) / profit after tax","Loss after tax"))) -> Profit after tax | L32: =SUM(L28:L31) -> 0 | N32: =SUM(N28:N31) -> 0
B34: Earnings per share - basic | J34: =J30+1 -> 32 | L34: =Notes!#REF! -> #REF! | N34: =Notes!#REF! -> #REF!
B36: =SOFP!B63 -> The annexed notes from 1 to 38 form an integral part of these financial statements.
B42: =SOFP!B69 -> Chief Executive | L42: =SOFP!L69 -> Director

Sheet SOCI
B1: =Cover!C1 -> ABC LIMITED
B2: STATEMENT OF COMPREHENSIVE INCOME
B3: =Cover!C3 -> FOR THE YEAR ENDED JUNE 30, 2023
J5: =SOFP!J5 -> Note | L5: =SOFP!L5 -> 2023 | N5: =SOFP!N5 -> 2022
L6: =SOFP!L6 -> ------------- Rupees -------------
B8: =SOPL!B32 -> Profit after tax | L8: =SOPL!L32 -> 0 | N8: =SOPL!N32 -> 0
B10: Other comprehensive income
B12: Items that may be subsequently reclassified to profit or loss
B13: Changes in the fair value of available-for-sale financial assets
B14: Exchange differences on translation of foreign operations
B15: Exchange differences on translation of discontinued operation
B16: Changes in the fair value of cash flow hedges
B17: Net investment hedge
B18: Income tax relating to these items
L19: =SUM(L13:L18) -> 0 | N19: =SUM(N13:N18) -> 0
B20: Items that will not be subsequently reclassified to profit or loss
B21: Gain on revaluation of land and buildings
B22: Remeasurements of retirement benefit obligations
B23: Income tax relating to these items
L24: =SUM(L21:L23) -> 0 | N24: =SUM(N21:N23) -> 0
B26: =IF(AND(L26>=0,N26>=0),"Other comprehensive income",IF(AND(L26>=0,N26<0),"Other comprehensive income / (loss)",IF(AND(L26<0,N26>=0),"Other comprehensive (loss) / income","Other comprehensive loss"))) -> Other comprehensive income | L26: =L19+L24 -> 0 | N26: =N19+N24 -> 0
B28: =IF(AND(L28>=0,N28>=0),"Total comprehensive income for the year",IF(AND(L28>=0,N28<0),"Total comprehensive income / (loss) for the year",IF(AND(L28<0,N28>=0),"Total comprehensive (loss) / income for the year","Total comprehensive loss for the year"))) -> Total comprehensive income for the year | L28: =L8+L26 -> 0 | N28: =N8+N26 -> 0
B30: =SOFP!B63 -> The annexed notes from 1 to 38 form an integral part of these financial statements.
B36: =SOFP!B69 -> Chief Executive | L36: =SOFP!L69 -> Director

Sheet SOCF
B1: =Cover!C1 -> ABC LIMITED
B2: STATEMENT OF CASH FLOWS
B3: =Cover!C3 -> FOR THE YEAR ENDED JUNE 30, 2023
J5: =SOFP!J5 -> Note | L5: =SOFP!L5 -> 2023 | N5: =SOFP!N5 -> 2022
L6: =SOFP!L6 -> ------------- Rupees -------------
B8: Cash flows from operating activities
B9: =SOPL!B28 -> Profit before tax | L9: =SOPL!L28 -> 0 | N9: =SOPL!N28 -> 0
B10: Adjustments for:
L20: =SUM(L11:L19) -> 0 | N20: =SUM(N11:N19) -> 0
B21: =IF(AND(L21>=0,N21>=0),"Operating profit before working capital changes",IF(AND(L21>=0,N21<0),"Operating profit / (loss) before working capital changes",IF(AND(L21<0,N21>=0),"Operating (loss) / profit before working capital changes","Operating loss before working capital changes"))) -> Operating profit before working capital changes | L21: =L9+L20 -> 0 | N21: =N9+N20 -> 0
B23: Effect of working capital changes
B24: (Increase) / decrease in current assets
L29: =SUM(L25:L28) -> 0 | N29: =SUM(N25:N28) -> 0
B30: Increase / (decrease) in current liabilities
L35: =SUM(L31:L34) -> 0 | N35: =SUM(N31:N34) -> 0
B37: =IF(AND(L37>=0,N37>=0),"Cash generated from operations",IF(AND(L37>=0,N37<0),"Cash generated from / (used in) operations",IF(AND(L37<0,N37>=0),"Cash (used in) / generated from operations","Cash used in operations"))) -> Cash generated from operations | L37: =L21+L29+L35 -> 0 | N37: =N21+N29+N35 -> 0
B39: Interest received
B40: Interest paid
B41: Income taxes paid
B42: Lease payments (interest portion)
B43: Short-term lease payments (low values assets and variable lease payments not included in lease liability)
L46: =SUM(L39:L45) -> 0 | N46: =SUM(N39:N45) -> 0
B48: =IF(AND(L48>0,N48>0),"Net cash inflows from operating activities",IF(AND(L48>=0,N48<0),"Net cash inflows / (outflows) from operating activities",IF(AND(L48<0,N48>=0),"Net cash (outflows) / inflows from operating activities",IF(AND(L48=0,N48=0),"Net cash flows from operating activities","Net cash outflows from operating activities")))) -> Net cash flows from operating activities | L48: =L37+L46 -> 0 | N48: =N37+N46 -> 0
B50: Cash flows from investing activities
B51: Payments for property, plant and equipment
B52: Payments for investment property
B53: Payments for available-for-sale financial assets
B54: Payments for held-to-maturity investments
B55: Payments for patents and trademarks
B56: Payment of software development costs
B57: Loans to related parties
B58: Proceeds from sale of property, plant and equipment
B59: Proceeds from sale of available-for-sale financial assets
B60: Repayment of loans by related parties
B61: Dividends received
B62: Interest received on available-for-sale financial assets
B64: =IF(AND(L64>0,N64>0),"Net cash inflows from investing activities",IF(AND(L64>=0,N64<0),"Net cash inflows / (outflows) from investing activities",IF(AND(L64<0,N64>=0),"Net cash (outflows) / inflows from investing activities",IF(AND(L64=0,N64=0),"Net cash flows from investing activities","Net cash outflows from investing activities")))) -> Net cash flows from investing activities | L64: =SUM(L51:L63) -> 0 | N64: =SUM(N51:N63) -> 0
B66: Cash flows from financing activities
B67: Proceeds from issues of shares and other equity securities
B68: Proceeds from borrowings
B69: Repayment of borrowings
B70: Lease payments (principal portion)
B71: Dividends paid to company’s shareholders
B73: =IF(AND(L73>0,N73>0),"Net cash inflows from financing activities",IF(AND(L73>=0,N73<0),"Net cash inflows / (outflows) from financing activities",IF(AND(L73<0,N73>=0),"Net cash (outflows) / inflows from financing activities",IF(AND(L73=0,N73=0),"Net cash flows from investing activities","Net cash outflows from financing activities")))) -> Net cash flows from investing activities | L73: =SUM(L67:L72) -> 0 | N73: =SUM(N67:N72) -> 0
B75: =IF(AND(L75>=0,N75>=0),"Net increase in cash and cash equivalents",IF(AND(L75>=0,N75<0),"Net increase / (decrease) in cash and cash equivalents",IF(AND(L75<0,N75>=0),"Net (decrease) / increase in cash and cash equivalents","Net decrease in cash and cash equivalents"))) -> Net increase in cash and cash equivalents | L75: =L48+L64+L73 -> 0 | N75: =N48+N64+N73 -> 0
B76: Cash and cash equivalents at the beginning of the year | L76: =N77 -> 0
B77: Cash and cash equivalents at end of the year | L77: =SUM(L75:L76) -> 0 | N77: =SUM(N75:N76) -> 0
B79: =SOFP!B63 -> The annexed notes from 1 to 38 form an integral part of these financial statements.
B85: =SOFP!B69 -> Chief Executive | L85: =SOFP!L69 -> Director
L88: =L77-SOFP!L24 -> 0 | N88: =N77-SOFP!N24 -> 0

Sheet SOCIE
B1: =Cover!C1 -> ABC LIMITED
B2: STATEMENT OF CHANGES IN EQUITY
B3: =Cover!C3 -> FOR THE YEAR ENDED JUNE 30, 2023
F5: =SOFP!J5 -> Note | H5: =SOFP!B35 -> Issued, subscribed and paid up share capital | J5: =SOFP!B36 -> Share deposit money | L5: =SOFP!B37 -> Other reserves | N5: =SOFP!B38 -> Retained earnings | P5: Total share capital and reserves
H6: ="------------------------"&SOFP!L6&"------------------------" -> ------------------------------------- Rupees -------------------------------------
B8: =("Balance as at " &Cover!E7) -> Balance as at July 01, 2021 | P8: =SUM(H8:N8) -> 0
B10: =IF(P10>=0,"Profit for the year","Loss for the year") -> Profit for the year | P10: =SUM(H10:N10) -> 0
B12: =IF(P12>=0,"Other comprehensive income for the year","Other comprehensive loss for the year") -> Other comprehensive income for the year | N12: =SOCI!N26 -> 0 | P12: =SUM(H12:N12) -> 0
B14: =("Balance as at " &Cover!G7) -> Balance as at June 30, 2022 | H14: =SUM(H8:H13) -> 0 | J14: =SUM(J8:J13) -> 0 | L14: =SUM(L8:L13) -> 0 | N14: =SUM(N8:N13) -> 0 | P14: =SUM(P8:P13) -> 0
B16: =("Balance as at " &Cover!E6) -> Balance as at July 01, 2022 | H16: =H14 -> 0 | J16: =J14 -> 0 | L16: =L14 -> 0 | N16: =N14 -> 0 | P16: =SUM(H16:N16) -> 0
B18: =IF(P18>=0,"Profit for the year","Loss for the year") -> Profit for the year | N18: =SOPL!L32 -> 0 | P18: =SUM(H18:N18) -> 0
B20: =IF(P20>=0,"Other comprehensive income for the year","Other comprehensive loss for the year") -> Other comprehensive income for the year | N20: =SOCI!L26 -> 0 | P20: =SUM(H20:N20) -> 0
B22: =("Balance as at " &Cover!G6) -> Balance as at June 30, 2023 | H22: =SUM(H16:H21) -> 0 | J22: =SUM(J16:J21) -> 0 | L22: =SUM(L16:L21) -> 0 | N22: =SUM(N16:N21) -> 0 | P22: =SUM(P16:P21) -> 0
B24: =SOFP!B63 -> The annexed notes from 1 to 38 form an integral part of these financial statements.
B30: =SOFP!B69 -> Chief Executive | N30: =SOFP!L69 -> Director

Sheet Policies
A1: =Cover!C1 -> ABC LIMITED
A2: NOTES TO THE FINANCIAL STATEMENTS
A3: =Cover!C3 -> FOR THE YEAR ENDED JUNE 30, 2023
A5: 1 | B5: Status and nature of business
B7: ABC Limited (the Company) was incorporated in Pakistan on _________________ as a Private Limited Company under the repealed Companies Ordinance, 1984. The company is principally engaged in ___________________. The registered office of the company is located at ________________________. (If the Company is a Manufacturer and its registered office is located at a location other than Manufacturing Facility then, The manufacturing facility of the company is located at ___________________________).
A13: =A5+1 -> 2 | B13: Basis of preparation
A15: =A13+0.1 -> 2.1 | B15: Basis of measurement
B17: =IF(Cover!E13="Cost","These financial statements have been prepared under the historical cost convention unless otherwise specifically stated, if any,","These financial statements have been prepared under the historical cost convention unless otherwise specifically stated, except for, "&"certain items of property, plant and equipment, which are stated at revalued amount less accumulated depreciation and impairment losses, if any.") -> These financial statements have been prepared under the historical cost convention unless otherwise specifically stated, if any,
A20: =A15+0.1 -> 2.2 | B20: Statement of compliance
B22: These financial statements have been prepared in accordance with the approved accounting standards as applicable in Pakistan and the requirements of Companies Act, 2017. Approved accounting standards comprise of:
A24: - | B24: =VLOOKUP(Cover!$E$12,Cover!$I$14:$J$17,2,FALSE) -> Revised Accounting and Financial Reporting Standards for Small Sized Entities (Revised AFRS for SSEs) issued by the Institute of Chartered Accountants of Pakistan (ICAP) as notified under the Companies Act, 2017; and
A26: - | B26: Islamic Financial Accounting Standards (IFASs) as issued by the Institute of Chartered Accountants of Pakistan (ICAP); and
A27: - | B27: Provisions of and directives issued under the Companies Act, 2017.
B28: Wherever, the requirements of the Companies Act, 2017 or directives issued by the Securities and Exchange Commission of Pakistan differs with the requirements of these accounting standards, the requirements of the Companies Act, 2017 or the requirements of the said directives shall prevail.
A32: =A20+0.1 -> 2.3 | B32: Functional and presentational currency
B34: These financial statements have been prepared in Pakistani Rupees (PKR), which is the company's functional and presentational currency
A36: =A13+1 -> 3 | B36: Use of judgments, estimates and assumptions
B38: The preparation of financial statements in conformity with the accounting and reporting standards requires the use of certain critical accounting estimates. It also requires management to exercise its judgement in the process of applying the Company’s accounting policies. Estimates and judgements are continually evaluated and are based on historic experience and other factors, including expectation of future events that are believed to be reasonable under the circumstances. In the process of applying the Company’s accounting policies, the management has made the following estimates and judgements which are significant to the financial statements:
A45: - | B45: ="assumptions and estimates used in determining the recoverable amount, residual values and useful lives of "&LOWER(SOFP!B10)&"(Note "&TEXT(SOFP!J10,"##")&");" -> assumptions and estimates used in determining the recoverable amount, residual values and useful lives of property, plant and equipment (Note 5);
A49: - | B49: ="assumptions and estimates used in deriving fair value of "&LOWER(SOFP!B11)&"(Note "&TEXT(SOFP!J11,"##")&");" -> assumptions and estimates used in deriving fair value of investment properties (Note 6);
A51: - | B51: ="assumptions and estimates used in determining the recoverable amount, residual values and useful lives of "&LOWER(SOFP!B12)&"(Note "&TEXT(SOFP!J12,"##")&");" -> assumptions and estimates used in determining the recoverable amount, residual values and useful lives of intangible assets (Note 7);
A54: - | B54: =LOWER(SOFP!B14)&" is recognised only to the extent that it is probable that future taxable profits will be available against which the assets may be utilised"&" (Note "&TEXT(SOFP!J14,"##")&");" -> deferred tax assets is recognised only to the extent that it is probable that future taxable profits will be available against which the assets may be utilised (Note 9);
A57: - | B57: ="assumptions and estimates used in determining the provision for slow moving and obsolete "&LOWER(SOFP!B19)&"(Note "&TEXT(SOFP!J19,"##")&");" -> assumptions and estimates used in determining the provision for slow moving and obsolete stores, spares and loose tools (Note 10);
A60: - | B60: ="assumptions and estimates used in writing down items of "&LOWER(SOFP!B20)&" to their net realisable value "&"(Note "&TEXT(SOFP!J20,"##")&");" -> assumptions and estimates used in writing down items of inventories to their net realisable value (Note 11);
A62: - | B62: ="assumptions and estimates used in calculating the provision for impairment for "&LOWER(SOFP!B21)&"(Note "&TEXT(SOFP!J21,"##")&");" -> assumptions and estimates used in calculating the provision for impairment for trade receivables - net (Note 12);
A64: - | B64: ="assumptions and estimates used in calculating the provision for impairment for "&LOWER(SOFP!B22)&"(Note "&TEXT(SOFP!J22,"##")&");" -> assumptions and estimates used in calculating the provision for impairment for advances, deposits and prepayments (Note 13);
A68: - | B68: ="assumptions and estimates used in disclosure and assessment of provision for "&LOWER(SOFP!B57)&"(Note "&TEXT(SOFP!J57,"##")&");" -> assumptions and estimates used in disclosure and assessment of provision for contingencies and commitments (Note 22);
A70: - | B70: ="assumptions and estimates used in determining current income under relevant tax law and the decisions of appellate authorities on certain cases issued in the past "&"(Note "&TEXT(SOPL!J30,"##")&");" -> assumptions and estimates used in determining current income under relevant tax law and the decisions of appellate authorities on certain cases issued in the past (Note 31);
A73: =A36+1 -> 4 | B73: Summary of significant accounting policies
A75: =A73+0.1 -> 4.1 | B75: =SOFP!B10 -> Property, plant and equipment
B77: =B75&" are stated at cost less accumulated depreciation and impairment losses, if any, Cost includes expenditures directly attributable to the acquisition of an asset." -> Property, plant and equipment are stated at cost less accumulated depreciation and impairment losses, if any, Cost includes expenditures directly attributable to the acquisition of an asset.
B80: Capital work-in-progress is stated at cost accumulated to the date of statement of financial position less impairment losses, if any.
B82: ="Depreciation on "&LOWER(B75)&" is charged on reducing balance method at the rates stated in Note "&FAS!A5&" to these financial statements. Depreciation charge commences from the month in which asset is available for use and continues until the month of disposal." -> Depreciation on property, plant and equipment is charged on reducing balance method at the rates stated in Note 5 to these financial statements. Depreciation charge commences from the month in which asset is available for use and continues until the month of disposal.
B86: Residual values and the useful lives are reviewed at each date of statement of financial position and adjusted if expectations differ significantly from previous estimates.
B89: ="Residual values are determined by the management as the amount it expects it would receive currently for an item of "&LOWER(B75)&" if it was already of the age and in the condition expected at the end of its useful life based on the prevailing market prices of similar assets already at the end of their useful lives." -> Residual values are determined by the management as the amount it expects it would receive currently for an item of property, plant and equipment if it was already of the age and in the condition expected at the end of its useful life based on the prevailing market prices of similar assets already at the end of their useful lives.
B93: Useful lives are determined by the management based on the expected usage of assets, physical wear and tear, technical and commercial obsolescence, legal and similar limits on the use of the assets and other similar factors.
B96: ="The carrying values of "&LOWER(B75)&" are reviewed at each reporting date for indications that an asset may be impaired and carrying values may not be recovered."&" If any such indication exists and where the carrying value exceeds the estimated recoverable amount, the asset or cash generating unit is written down to its recoverable amount. The recoverable amount of "&LOWER(B75)&" is the greater of fair value less cost to sell and value in use." -> The carrying values of property, plant and equipment are reviewed at each reporting date for indications that an asset may be impaired and carrying values may not be recovered. If any such indication exists and where the carrying value exceeds the estimated recoverable amount, the asset or cash generating unit is written down to its recoverable amount. The recoverable amount of property, plant and equipment is the greater of fair value less cost to sell and value in use.
B101: Normal repairs and maintenance are charged to profit or loss as and when incurred. Major renewals and improvements, if any, are capitalised, when it is probable that future economic benefits will flow to the Company.
B104: ="An item of "&LOWER(B75)&" is derecognised upon disposal or when no future economic benefits are expected from its use or disposal. Gains and losses on disposals are determined by comparing proceeds with carrying amount of the relevant assets. These are included in profit or loss." -> An item of property, plant and equipment is derecognised upon disposal or when no future economic benefits are expected from its use or disposal. Gains and losses on disposals are determined by comparing proceeds with carrying amount of the relevant assets. These are included in profit or loss.
A108: =A75+0.1 -> 4.2 | B108: Investment properties
B110: Investment property, which is property held to earn rentals and/or for capital appreciation (including property under construction for such purposes), is measured initially at cost, including transaction costs. Subsequent to initial recognition, investment property is measured at fair value. Gains or losses arising from changes in the fair value of investment property are included in profit or loss in the period in which they arise.
B115: An investment property is derecognised upon disposal or when the investment property is permanently withdrawn from use and no future economic benefits are expected from the disposal. Any gain or loss arising on derecognition of the property (calculated as the difference between the net disposal proceeds and the carrying amount of the asset) is included in profit or loss in the period in which the property is derecognised.
A120: =A108+0.1 -> 4.3 | B120: Intangible assets
B122: ="Intangible assets are measured at cost less accumulated amortization and accumulated impairment losses. "&"Amortization is charged so as to allocate the cost of assets over their estimated useful lives, using the straight-line method at the rates specified in Note "&SOFP!J12&" to these financial statements." -> Intangible assets are measured at cost less accumulated amortization and accumulated impairment losses. Amortization is charged so as to allocate the cost of assets over their estimated useful lives, using the straight-line method at the rates specified in Note 7 to these financial statements.
B126: The useful lives, residual values and amortization method are reviewed on a regular basis. The effect of any changes in estimate accounted for on a prospective basis.
B129: The carrying amount of the intangible is reviewed for impairment whenever events or changes in circumstances indicate that the carrying amount may not be recoverable. An impairment loss is recognised in the profit or loss for the amount by which the asset’s carrying amount exceeds its recoverable amount. Reversal of impairment losses are also recognised in the profit or loss, however, it is restricted to the original cost of the asset.
A134: =A120+0.1 -> 4.4 | B134: Stores and spares
B136: These are valued at lower of cost using Weighted Average Cost method and estimated net realisable value. Provision is made for slow moving and obsolete stores and spares. Items in transit are valued at cost comprising invoice values plus other charges incurred thereon.
B140: Net realisable value specifies the estimated selling price in the ordinary course of business less the estimated cost of completion and cost necessarily to be incurred to make the sale.
A143: =A134+0.1 -> 4.5 | B143: Stock in trade
B145: All stocks are stated at lower of cost and estimated net realizable value. Cost is determined as follows: | Q145: Inventories are stated at the lower of cost and net realisable value. Cost comprises direct materials and, where
Q146: applicable, direct labour costs and those overheads that have been incurred in bringing the inventories to their
B147: Stock Type | E147: Valuation Method | Q147: present location and condition. Cost is calculated using the weighted average cost method. Net realisable value
Q148: represents the estimated selling price less all estimated costs of completion and costs to be incurred in marketing,
B149: Raw material | E149: Weighted average basis | Q149: selling and distribution.
B151: Work in process | E151: Estimated manufacturing cost including appropriate overheads
B153: Finished goods | E153: Average manufacturing cost including appropriate overheads
B155: Waste/Scrap | E155: Net realizable value
B158: Net realisable value is determined on the basis of estimated selling price of the product in the ordinary course of business less estimated costs of completion and the estimated costs necessary to be incurred for its sale.
A161: =A143+0.1 -> 4.6 | B161: Financial instruments
B163: All the financial assets and financial liabilities are recognized at the time when the Company becomes a party to the contractual provisions of the instruments. The Company derecognizes a financial asset or a portion of financial asset when, and only when, the Company loses control of the contractual rights that comprise the financial asset or portion of financial asset. While a financial liability or part of financial liability is derecognized from the balance sheet when, and only when, it is extinguished, i.e. when the obligation specified in the contract is discharged, cancelled or expires.
B169: All financial assets and financial liabilities are initially measured at cost, which is the fair value of the consideration given and received respectively. These financial assets and liabilities are subsequently measured at fair value, amortized cost or cost, as the case may be.
B173: Financial assets are Trade receivebales, cash and bank balances. These are stated at their nominal values as reduced by the appropriate allowances for estimating irrecoverable amount.
B176: Financial liabilities are classified according to the substance of the contractual arrangements entered into. Significant financial liabilities are long term loans, short term running finance utilized under mark-up arrangements, creditors, liabilities, accrued and other liabilities. Mark-up bearing finances are recorded at the gross proceeds received. Other liabilities are stated at their nominal value.
A181: =A161+0.1 -> 4.7 | B181: Offsetting of financial assets and liabilities
B183: Financial assets and liabilities are offset and the net amount is reported in the statement of financial position, if the company has a legally enforceable right to offset the recognized amounts and the company intends to settle either on a net basis or realize the asset and settle the liability simultaneously.
A187: =A181+0.1 -> 4.8 | B187: Impairment of financial assets
B189: The Company assesses at each balance sheet date whether there is any objective evidence that a financial asset or a group of financial assets is impaired. A financial asset or a group of financial assets is deemed to be impaired if, and only if, there is objective evidence of impairment as a result of one or more events that has occurred after the initial recognition of the asset (an incurred ‘loss event’) and that loss event has an impact on the estimated future cash flows of the financial asset or the group of financial assets that can be reliably estimated.
B194: Evidence of the impairment may include indicators that the debtor or a group of debtors is experiencing significant financial difficulty, default or delinquency in interest or principal payments, the probability that they will enter bankruptcy or other financial reorganization and where observable data indicates that there is a measurable decrease in the estimated future cash flows, such as changes in arrears or economic conditions that correlate with defaults.
B199: The amount of loss is measured as the difference between the asset’s carrying amount and the present value of the estimated future cash flows discounted at the financial asset’s original effective interest rate. The carrying amount of the asset is reduced and the amount of the loss is recognized in the profit and loss account. If, in a subsequent period, the amount of the impairment loss decreases and the decrease can be related objectively to an event occurring after the impairment was recognized, the reversal of the previously recognized impairment loss is recognized in profit and loss account.
A205: =A187+0.1 -> 4.9 | B205: Trade debts
B207: Trade debts are carried at invoice amount on transaction date less any estimate for doubtful debts. Known bad debts are written off as and when identified.
A210: 4.10 | B210: Cash and cash equivalents
B212: Cash and cash equivalents are carried in the statement of financial position at cost. For the purposes of the statement of cash flows, cash and cash equivalents comprise cash in hand, cash with banks on current/savings and deposit accounts, that are readily convertible to known amount of cash and which are subject to insignificant risk of change in value.
A216: =A210+0.01 -> 4.11 | B216: Trade and other payables
B218: Liabilities for trade and other payables are carried at cost which is the fair value of the consideration to be paid in future for goods and services.
A221: =A216+0.01 -> 4.12 | B221: Provisions
B223: Provisions are recognized when the company has a present legal or constructive obligation as a result of past events and, it is probable that an outflow of resources embodying economic benefits will be required to settle the obligation and a reliable estimate can be made of the amount of obligation.
A227: =A221+0.01 -> 4.13 | B227: Taxation
B229: Current:
B231: Provision for current taxation is based on taxable income at the current rates of taxation after taking into account applicable tax credits, rebates and exemptions, if any.
B234: Deferred:
B236: Deferred tax is accounted for using the balance sheet liability method in respect of all temporary differences arising from difference between the carrying amount of the assets and liabilities in the financial statements and corresponding tax bases used in the computation of taxable profit. Deferred tax liabilities are recognized for all taxable temporary differences and deferred tax assets are recognized to the extent that it is probable that taxable profit will be available against which the deductible temporary differences, unused tax losses and tax credits can be utilized. Deferred tax is calculated at the rates that are expected to apply to the period when the differences reverse, based on tax rates that have been enacted or substantively enacted by the statement of financial position date. Deferred tax is charged or credited in the income statement, except where deferred tax arises on the items credited or charged to equity in which case it is included in equity.
A246: =A227+0.01 -> 4.14 | B246: Related party transactions and transfer pricing
B248: Parties are said to be related if they are able to influence the operating and financing decisions of the Company and vice versa. All transactions with related parties and associated undertakings are entered into on the basis of mutually agreed terms.
A251: =A246+0.01 -> 4.15 | B251: Leases
B253: At its inception, a lease is classified as either a finance lease or an operating lease. Finance leases transfer substantially all the risks and rewards of ownership. All other leases are classified as operating leases.
B256: Finance leases
B257: Finance leases are capitalized at the lease’s commencement at the lower of the fair value of the leased property and the present value of the minimum lease payments. Each lease payment is apportioned between the liability and finance charges using the effective interest method. Rental obligations, net of finance charges, are included in borrowings in the statement of financial position.
B261: Operating leases
B263: Rentals payable under operating leases are charged to profit or loss on a straight-line basis over the term of the relevant lease. Minimum lease payments receivable under operating leases are recognised as revenue on a straight-line basis over the term of the lease.
A266: =A251+0.01 -> 4.16 | B266: Borrowings and their costs
B268: Borrowings are recorded at the proceeds received. Borrowing costs are recognized as an expense in the period in which these are incurred except to the extent of borrowing costs that are directly attributable to the acquisition, construction or production of a qualifying asset. Such borrowing costs, if any, are capitalized as part of the cost of that asset.
A272: =A266+0.01 -> 4.17 | B272: Deferred income
B274: Grants related to long term financing are accounted for by recognising the grants as deferred income. These grants are recognised as income on a systematic basis over the period for which the company has obtained long term financing. The company adjusts grant income against the associated expense of long term financing.
A278: =A272+0.01 -> 4.18 | B278: Revenue recognition
B280: The company recognizes revenue when the amount of revenue can be reliably measured, it is probable that future economic benefits will flow to the company and specific criteria has been met for each of the company's activities as described below:
A283: - | B283: Revenue from the sale of goods is recognised when the significant risks and rewards of ownership of the goods have been transferred to the buyer. This is usually at the point that the customer has signed for the delivery of the goods.
A286: - | B286: Interest income recognised on a time proportion basis on the principal amount outstanding and at the applicable rate.
A288: =A278+0.01 -> 4.19 | B288: Contingent liabilities
...

Sheet FAS
A1: =Cover!C1 -> ABC LIMITED
A2: =Policies!A2 -> NOTES TO THE FINANCIAL STATEMENTS
A3: =Cover!C3 -> FOR THE YEAR ENDED JUNE 30, 2023
A5: =SOFP!J10 -> 5 | B5: =SOFP!B10 -> Property, plant and equipment | J5: =SOFP!J5 -> Note | L5: =SOFP!L5 -> 2023 | N5: =SOFP!N5 -> 2022
L6: =SOFP!L6 -> ------------- Rupees -------------
B8: Operating fixed assets | J8: =A13 -> 5.1 | L8: =Z66 -> 0 | N8: =Z64 -> 0
B9: Capital work in progress
L11: =SUM(L8:L10) -> 0 | N11: =SUM(N8:N10) -> 0
A13: =A5+0.1 -> 5.1 | B13: =B8 -> Operating fixed assets
H14: Owned assets | Z14: Total assets
H15: Freehold Land | J15: Building on Freehold Land | L15: Plant and Machinery | N15: Generator | P15: Office Equipment | R15: Computers | T15: Electric Equipment & Installations | V15: Furniture and Fixture | X15: Vehicles
H16: =SOCIE!H6 -> ------------------------------------- Rupees -------------------------------------
A18: Cost/Revaluation
B20: =("Balance as at " &Cover!E7 &" - Cost") -> Balance as at July 01, 2021 - Cost | L20: 0 | R20: 0 | V20: 0 | Z20: =SUM(H20:X20) -> 0
B21: =("Balance as at " &Cover!E7 &" - Revaluation") -> Balance as at July 01, 2021 - Revaluation | H21: 0 | Z21: =SUM(H21:X21) -> 0
H22: =SUM(H20:H21) -> 0 | J22: =SUM(J20:J21) -> 0 | L22: =SUM(L20:L21) -> 0 | N22: =SUM(N20:N21) -> 0 | P22: =SUM(P20:P21) -> 0 | R22: =SUM(R20:R21) -> 0 | T22: =SUM(T20:T21) -> 0 | V22: =SUM(V20:V21) -> 0 | X22: =SUM(X20:X21) -> 0 | Z22: =SUM(H22:X22) -> 0
B24: Additions during the year | Z24: =SUM(H24:X24) -> 0
B26: Disposals | Z26: =SUM(H26:X26) -> 0
B28: =("Balance as at " &Cover!G7) -> Balance as at June 30, 2022 | H28: =SUM(H22:H27) -> 0 | J28: =SUM(J22:J27) -> 0 | L28: =SUM(L22:L27) -> 0 | N28: =SUM(N22:N27) -> 0 | P28: =SUM(P22:P27) -> 0 | R28: =SUM(R22:R27) -> 0 | T28: =SUM(T22:T27) -> 0 | V28: =SUM(V22:V27) -> 0 | X28: =SUM(X22:X27) -> 0 | Z28: =SUM(H28:X28) -> 0
B30: =("Balance as at " &Cover!E6 &" - Cost") -> Balance as at July 01, 2022 - Cost | H30: =H28-H31 -> 0 | J30: =J28-J31 -> 0 | L30: =L28-L31 -> 0 | N30: =N28-N31 -> 0 | P30: =P28-P31 -> 0 | R30: =R28-R31 -> 0 | T30: =T28-T31 -> 0 | V30: =V28-V31 -> 0 | X30: =X28-X31 -> 0 | Z30: =SUM(H30:X30) -> 0
B31: =("Balance as at " &Cover!E6 &" - Revaluation") -> Balance as at July 01, 2022 - Revaluation | Z31: =SUM(H31:X31) -> 0
H32: =SUM(H30:H31) -> 0 | J32: =SUM(J30:J31) -> 0 | L32: =SUM(L30:L31) -> 0 | N32: =SUM(N30:N31) -> 0 | P32: =SUM(P30:P31) -> 0 | R32: =SUM(R30:R31) -> 0 | T32: =SUM(T30:T31) -> 0 | V32: =SUM(V30:V31) -> 0 | X32: =SUM(X30:X31) -> 0 | Z32: =SUM(H32:X32) -> 0
B34: Additions during the year | Z34: =SUM(H34:X34) -> 0
B36: Disposals | L36: =-L32*0.1 -> 0 | Z36: =SUM(H36:X36) -> 0
B38: =("Balance as at " &Cover!G6) -> Balance as at June 30, 2023 | H38: =SUM(H32:H37) -> 0 | J38: =SUM(J32:J37) -> 0 | L38: =SUM(L32:L37) -> 0 | N38: =SUM(N32:N37) -> 0 | P38: =SUM(P32:P37) -> 0 | R38: =SUM(R32:R37) -> 0 | T38: =SUM(T32:T37) -> 0 | V38: =SUM(V32:V37) -> 0 | X38: =SUM(X32:X37) -> 0 | Z38: =SUM(H38:X38) -> 0
A40: Depreciation
B42: =B20 -> Balance as at July 01, 2021 - Cost | Z42: =SUM(H42:X42) -> 0
B43: =B21 -> Balance as at July 01, 2021 - Revaluation | Z43: =SUM(H43:X43) -> 0
H44: =SUM(H42:H43) -> 0 | J44: =SUM(J42:J43) -> 0 | L44: =SUM(L42:L43) -> 0 | N44: =SUM(N42:N43) -> 0 | P44: =SUM(P42:P43) -> 0 | R44: =SUM(R42:R43) -> 0 | T44: =SUM(T42:T43) -> 0 | V44: =SUM(V42:V43) -> 0 | X44: =SUM(X42:X43) -> 0 | Z44: =SUM(H44:X44) -> 0
B46: Charge for the year | Z46: =SUM(H46:X46) -> 0
B48: Depreciation on disposals | Z48: =SUM(H48:X48) -> 0
B50: =B28 -> Balance as at June 30, 2022 | H50: =SUM(H44:H49) -> 0 | J50: =SUM(J44:J49) -> 0 | L50: =SUM(L44:L49) -> 0 | N50: =SUM(N44:N49) -> 0 | P50: =SUM(P44:P49) -> 0 | R50: =SUM(R44:R49) -> 0 | T50: =SUM(T44:T49) -> 0 | V50: =SUM(V44:V49) -> 0 | X50: =SUM(X44:X49) -> 0 | Z50: =SUM(H50:X50) -> 0
B52: =B30 -> Balance as at July 01, 2022 - Cost | H52: =H50 -> 0 | J52: =J50 -> 0 | L52: =L50 -> 0 | N52: =N50 -> 0 | P52: =P50 -> 0 | R52: =R50 -> 0 | T52: =T50 -> 0 | V52: =V50 -> 0 | X52: =X50 -> 0 | Z52: =SUM(H52:X52) -> 0
B53: =B31 -> Balance as at July 01, 2022 - Revaluation | Z53: =SUM(H53:X53) -> 0
H54: =SUM(H52:H53) -> 0 | J54: =SUM(J52:J53) -> 0 | L54: =SUM(L52:L53) -> 0 | N54: =SUM(N52:N53) -> 0 | P54: =SUM(P52:P53) -> 0 | R54: =SUM(R52:R53) -> 0 | T54: =SUM(T52:T53) -> 0 | V54: =SUM(V52:V53) -> 0 | X54: =SUM(X52:X53) -> 0 | Z54: =SUM(H54:X54) -> 0
B56: Charge for the year | H56: =-AD!K14 -> 0 | J56: =-AD!K19 -> 0 | L56: =-AD!K24 -> 0 | N56: =-AD!K29 -> 0 | P56: =-AD!K34 -> 0 | R56: =-AD!K39 -> 0 | T56: =-AD!K44 -> 0 | V56: =-AD!K49 -> 0 | X56: =-AD!K54 -> 0 | Z56: =SUM(H56:X56) -> 0
B58: Depreciation on disposals | H58: =-AD!N69 -> 0 | J58: =-AD!N73 -> 0 | L58: =-AD!N77 -> 0 | N58: =-AD!N81 -> 0 | P58: =-AD!N85 -> 0 | R58: =-AD!N89 -> 0 | T58: =-AD!N93 -> 0 | V58: =-AD!N97 -> 0 | X58: =-AD!N101 -> 0 | Z58: =SUM(H58:X58) -> 0
B60: =B38 -> Balance as at June 30, 2023 | H60: =SUM(H54:H59) -> 0 | J60: =SUM(J54:J59) -> 0 | L60: =SUM(L54:L59) -> 0 | N60: =SUM(N54:N59) -> 0 | P60: =SUM(P54:P59) -> 0 | R60: =SUM(R54:R59) -> 0 | T60: =SUM(T54:T59) -> 0 | V60: =SUM(V54:V59) -> 0 | X60: =SUM(X54:X59) -> 0 | Z60: =SUM(H60:X60) -> 0
A62: Rate of depreciation
A64: =("Written down value as at " &Cover!G7) -> Written down value as at June 30, 2022 | H64: =H28-H50 -> 0 | J64: =J28-J50 -> 0 | L64: =L28-L50 -> 0 | N64: =N28-N50 -> 0 | P64: =P28-P50 -> 0 | R64: =R28-R50 -> 0 | T64: =T28-T50 -> 0 | V64: =V28-V50 -> 0 | X64: =X28-X50 -> 0 | Z64: =SUM(H64:X64) -> 0
A66: =("Written down value as at " &Cover!G6) -> Written down value as at June 30, 2023 | H66: =H38-H60 -> 0 | J66: =J38-J60 -> 0 | L66: =L38-L60 -> 0 | N66: =N38-N60 -> 0 | P66: =P38-P60 -> 0 | R66: =R38-R60 -> 0 | T66: =T38-T60 -> 0 | V66: =V38-V60 -> 0 | X66: =X38-X60 -> 0 | Z66: =SUM(H66:X66) -> 0
A68: =A13+0.1 -> 5.2 | B68: ="Disposal of "&B5 -> Disposal of Property, plant and equipment | F68: In case of disposal if aggregate book value of assets exceeds 5 Million Rupees, following particulars of each assets which has book value 500,000 or more shall be disclosed.
B70: Particulars | D70: Classified as | H70: Cost/ revalued amount | J70: Accumulated depreciation | L70: Book value | N70: Sale proceeds | P70: Gain/(Loss) | R70: Mode of disposal | T70: Particulars of buyer | X70: Relationship with company or any of its director
H71: =L6 -> ------------- Rupees -------------
D73: =H15 -> Freehold Land | L73: =H73-J73 -> 0 | P73: =N73-L73 -> 0 | R73: Negotiation
D74: =J15 -> Building on Freehold Land | L74: =H74-J74 -> 0 | P74: =N74-L74 -> 0 | R74: Direct sale
D75: =L15 -> Plant and Machinery | L75: =H75-J75 -> 0 | P75: =N75-L75 -> 0 | R75: Quotation
D76: =N15 -> Generator | L76: =H76-J76 -> 0 | P76: =N76-L76 -> 0 | R76: Selected tender
D77: =P15 -> Office Equipment | L77: =H77-J77 -> 0 | P77: =N77-L77 -> 0 | R77: Open tender
D78: =R15 -> Computers | L78: =H78-J78 -> 0 | P78: =N78-L78 -> 0 | R78: Other means
D79: =T15 -> Electric Equipment & Installations | L79: =H79-J79 -> 0 | P79: =N79-L79 -> 0
D80: =V15 -> Furniture and Fixture | L80: =H80-J80 -> 0 | P80: =N80-L80 -> 0
D81: =X15 -> Vehicles | L81: =H81-J81 -> 0 | P81: =N81-L81 -> 0

Sheet Notes
A1: =Cover!C1 -> ABC LIMITED
A2: =Policies!A2 -> NOTES TO THE FINANCIAL STATEMENTS
A3: =Cover!C3 -> FOR THE YEAR ENDED JUNE 30, 2023
A5: =FAS!A68+0.1 -> 5.3 | B5: Following are the property/assets acquired with the fund of the company, is not held in the name of the company or is not in the possession and control of the company.
Q7: Impairment losses recognised during the year
B8: Particulars of property/assets | F8: Classified as | H8: Particulars of person | L8: =SOFP!$J$5 -> Note | N8: Value of the property/assets | Q8: IAS 36:130(a)-(g)
Q9: IAS 36:131
N10: Rupees | Q10: IAS 36:126(a)
Q11: The discount rate used in measuring value in use was __ per cent per annum. No impairment assessment was
F12: =FAS!H15 -> Freehold Land | L12: =A22 -> 5.3.1 | Q12: performed in 2019 as there was no indication of impairment.
F13: =FAS!J15 -> Building on Freehold Land | Q13: These losses are attributable to greater than anticipated wear and tear. Those assets have been impaired in full and
F14: =FAS!L15 -> Plant and Machinery | Q14: The impairment losses have been included in the profit and loss in the [other expenses/cost of sales] line item.
F15: =FAS!N15 -> Generator | Q15: IAS 16:74(a) Assets pledged as security
F16: =FAS!P15 -> Office Equipment | Q16: Freehold land and buildings with a carrying amount of CU__ million (2019: CU__ million) have been pledged to
F17: =FAS!R15 -> Computers | Q17: secure borrowings of the Group (see note 33). The Group is not allowed to pledge these assets as security for other
F18: =FAS!T15 -> Electric Equipment & Installations | Q18: borrowings or to sell them to another entity.
F19: =FAS!V15 -> Furniture and Fixture
F20: =FAS!X15 -> Vehicles
A22: =A5&".1" -> 5.3.1 | B22: Reason for the property or assets not being in the name of or possession of control of the company
J27: Note | L27: =SOFP!$L$5 -> 2023 | N27: =SOFP!$N$5 -> 2022
L28: =SOFP!$L$6 -> ------------- Rupees -------------
A30: =A5+0.1 -> 5.4 | B30: Depreciation for the year has been allocated as under:
B31: =SOPL!B10 -> Cost of revenue
B32: =SOPL!B14 -> Distribution costs
B33: =SOPL!B15 -> Administrative expenses
L35: =SUM(L31:L34) -> 0 | N35: =SUM(N31:N34) -> 0
A37: =A30+0.1 -> 5.5 | B37: Freehold Land, building, furniture and fixture and plant and machinery were revalued by M/s _________________ as on ___________.
A40: =A37+0.1 -> 5.6 | B40: Forced Sales Value (FSV) of the land, building, furniture and fixture and plant and machinery was Rs. _____ million , _____ million, Rs. ______ thousand and ___________ million respectively as at date of valuation.
A43: =A40+0.1 -> 5.7 | B43: ="Had there been no revaluation, the cost, accumulated depreciation and book value of revalued assets as at "&Cover!G6&" would have been as under:" -> Had there been no revaluation, the cost, accumulated depreciation and book value of revalued assets as at June 30, 2023 would have been as under:
J46: Cost | L46: Accumulated Depreciation | N46: Book Value
J47: =SOFP!$L$6 -> ------------- Rupees -------------
B49: =FAS!H15 -> Freehold Land | J49: =FAS!H30+FAS!H34-FAS!H36 -> 0 | L49: =FAS!H52+FAS!H56 -> 0 | N49: =J49-L49 -> 0
B50: =FAS!J15 -> Building on Freehold Land | J50: =FAS!J30+FAS!J34-FAS!J36 -> 0 | L50: =FAS!J52+FAS!J56-#REF! -> #REF! | N50: =J50-L50 -> #REF!
B51: =FAS!V15 -> Furniture and Fixture | J51: =FAS!V30+FAS!V34-FAS!V36 -> 0 | L51: =FAS!V52+FAS!V56-#REF! -> #REF! | N51: =J51-L51 -> #REF!
B52: =FAS!L15 -> Plant and Machinery | J52: =FAS!L30+FAS!L34-FAS!L36 -> 0 | L52: =FAS!L52+FAS!L56-#REF! -> #REF! | N52: =J52-L52 -> #REF!
B54: =FAS!B60 -> Balance as at June 30, 2023 | J54: =SUM(J49:J53) -> 0 | L54: =SUM(L49:L53) -> #REF! | N54: =SUM(N49:N53) -> #REF!
B56: =FAS!B50 -> Balance as at June 30, 2022 | J56: =FAS!H30+FAS!J30+FAS!V30+FAS!L30 -> 0 | L56: =FAS!H52+FAS!J52+FAS!V52+FAS!L52 -> 0 | N56: =J56-L56 -> 0
J60: Note | L60: =SOFP!$L$5 -> 2023 | N60: =SOFP!$N$5 -> 2022
L61: =SOFP!$L$6 -> ------------- Rupees -------------
A63: =SOFP!J11 -> 6 | B63: =SOFP!B11 -> Investment properties
B64: Opening balance | Q64: This represents freehold land and building adjacent to PVC manufacturing plant owned
B65: Acquisitions made | Q65: by the Group. This property is not occupied by the Group and is held for capital
B66: Capitalised subsequent expenditure | Q66: appreciation and earning rental income. The Group carries this investment property
B67: Classified as held for sale or disposals | Q67: under cost model as its fair value cannot be reliably determined as there is no active
B68: Net gain/(loss) from fair value adjustment | Q68: market for this property and a recent comparable transaction for identical property is
B69: Transfer (to)/from inventories and owner-occupied property | Q69: also not available. Further, the application of valuation techniques is not supposed to
Q70: provide a reliable measure of fair value. The possible range of estimates with in which
L71: =SUM(L64:L70) -> 0 | N71: =SUM(N64:N70) -> 0 | Q71: the fair value is highly likely to lie is Rs. xxx to Rs.xxx.
A73: =A63+0.1 -> 6.1 | B73: Amounts recognised in profit or loss for investment properties
B74: Rental income
B75: Expenses from property that generated rental income
B76: Expenses from property that did not generated rental income
B77: Fair value gain recognised in other income
L79: =SUM(L74:L78) -> 0 | N79: =SUM(N74:N78) -> 0
J82: Note | L82: =SOFP!$L$5 -> 2023 | N82: =SOFP!$N$5 -> 2022
L83: =SOFP!$L$6 -> ------------- Rupees -------------
A85: =SOFP!J12 -> 7 | B85: =SOFP!B12 -> Intangible assets
B86: Financial Software
B87: Net carrying value basis
B88: Opening net book value (NBV)
B89: Amortization charge
B91: Closing net book value (NBV) | L91: =SUM(L88:L90) -> 0 | N91: =SUM(N88:N90) -> 0
B93: Gross carrying value basis
B94: Cost
B95: Accumulated amortization
L97: =SUM(L94:L96) -> 0 | N97: =SUM(N94:N96) -> 0
B99: Amortization Rate
A101: =SOFP!J13 -> 8 | B101: =SOFP!B13 -> Long-term loans and advances
B102: Related parties | J102: =A107 -> 8.1
B103: Employees
L105: =SUM(L102:L103) -> 0 | N105: =SUM(N102:N103) -> 0
A107: =A101+0.1 -> 8.1 | B107: Long-term loans to related parties
B108: Directors | J108: =A115 -> 8.2
B109: Holding company
B110: Associated companies
B111: Less: Due within 12 months, shown under current loans and advances
L113: =SUM(L108:L111) -> 0 | N113: =SUM(N108:N111) -> 0
A115: =A107+0.1 -> 8.2 | B115: Long-term loans to directors
B116: The Company's Board of Directors has adopted a policy that there should be no loans to Directors, except for loans to fund expenditure to defend Directors in legal or regulatory proceedings. The loans provided are unsecured and bear interest at six month KIBOR + 1.5% (20X7: six month KIBOR + 1.5%) per annum. The effective interest rate was 6% (20X7: 6.5%) per annum. All the related requirements of the Companies Act, 2017 have been complied with. The reconciliation of the carrying amount at the beginning and end of the period is as under:
J122: Note | L122: =SOFP!$L$5 -> 2023 | N122: =SOFP!$N$5 -> 2022
L123: =SOFP!$L$6 -> ------------- Rupees -------------
B125: Balance at the beginning of the year
B126: Disbursements
B127: Receipts
B128: Balance at the end of the year
L129: =SUM(L125:L128) -> 0
B130: The maximum amount due as at the end of any month during the year was Rs. xxx (2020: Rs. xxx).
A133: =SOFP!J14 -> 9 | B133: =SOFP!B14 -> Deferred tax assets
B134: Movement of deferred tax
B135: Opening balance
B137: (Charged) / credited
B138: - to profit or loss
B139: - to other comprehensive income
B140: - effect of change of tax rates
L141: =SUM(L138:L140) -> 0 | N141: =SUM(N138:N140) -> 0
L143: =L135+L141 -> 0 | N143: =N135+N141 -> 0
A145: =A133+0.1 -> 9.1 | B145: Deferred tax comprises temporary differences attributable to:
B146: Taxable temporary difference
L151: =SUM(L147:L150) -> 0 | N151: =SUM(N147:N150) -> 0
B153: Deductible temporary difference
...

Sheet CS
B1: =Cover!C1 -> ABC LIMITED
B2: CONTROL SHEET
B3: =Cover!C3 -> FOR THE YEAR ENDED JUNE 30, 2023
E5: =D6-E6 -> 0 | G5: =F6-G6 -> 0 | I5: =H6-I6 -> 0
D6: =D306 -> 0 | E6: =E306 -> 0 | F6: =F306 -> 0 | G6: =G306 -> 0 | H6: =H306 -> 0 | I6: =I306 -> 0
B8: Financial Statements Heads / SubHeads | D8: Opening Balances | F8: Accumulated Activity | H8: Closing Balances
D9: Debit | E9: Credit | F9: Debit | G9: Credit | H9: Debit | I9: Credit
B10: .
B11: ASSETS | D11: =SUMIF(ATB!D:D,CS!B:B,ATB!F:F) -> 0 | E11: =SUMIF(ATB!D:D,CS!B:B,ATB!G:G) -> 0 | F11: =SUMIF(ATB!D:D,CS!B:B,ATB!H:H)+SUMIF(ATB!D:D,CS!B:B,ATB!J:J) -> 0 | G11: =SUMIF(ATB!D:D,CS!B:B,ATB!I:I)+SUMIF(ATB!D:D,CS!B:B,ATB!K:K) -> 0 | H11: =SUMIF(ATB!D:D,CS!B:B,ATB!L:L) -> 0 | I11: =SUMIF(ATB!D:D,CS!B:B,ATB!M:M) -> 0
B12: Non-current assets | D12: =SUMIF(ATB!D:D,CS!B:B,ATB!F:F) -> 0 | E12: =SUMIF(ATB!D:D,CS!B:B,ATB!G:G) -> 0 | F12: =SUMIF(ATB!D:D,CS!B:B,ATB!H:H)+SUMIF(ATB!D:D,CS!B:B,ATB!J:J) -> 0 | G12: =SUMIF(ATB!D:D,CS!B:B,ATB!I:I)+SUMIF(ATB!D:D,CS!B:B,ATB!K:K) -> 0 | H12: =SUMIF(ATB!D:D,CS!B:B,ATB!L:L) -> 0 | I12: =SUMIF(ATB!D:D,CS!B:B,ATB!M:M) -> 0
B13: Property, plant and equipment | D13: =SUMIF(ATB!D:D,CS!B:B,ATB!F:F) -> 0 | E13: =SUMIF(ATB!D:D,CS!B:B,ATB!G:G) -> 0 | F13: =SUMIF(ATB!D:D,CS!B:B,ATB!H:H)+SUMIF(ATB!D:D,CS!B:B,ATB!J:J) -> 0 | G13: =SUMIF(ATB!D:D,CS!B:B,ATB!I:I)+SUMIF(ATB!D:D,CS!B:B,ATB!K:K) -> 0 | H13: =SUMIF(ATB!D:D,CS!B:B,ATB!L:L) -> 0 | I13: =SUMIF(ATB!D:D,CS!B:B,ATB!M:M) -> 0
B14: Freehold Land | D14: =SUMIF(ATB!D:D,CS!B:B,ATB!F:F) -> 0 | E14: =SUMIF(ATB!D:D,CS!B:B,ATB!G:G) -> 0 | F14: =SUMIF(ATB!D:D,CS!B:B,ATB!H:H)+SUMIF(ATB!D:D,CS!B:B,ATB!J:J) -> 0 | G14: =SUMIF(ATB!D:D,CS!B:B,ATB!I:I)+SUMIF(ATB!D:D,CS!B:B,ATB!K:K) -> 0 | H14: =SUMIF(ATB!D:D,CS!B:B,ATB!L:L) -> 0 | I14: =SUMIF(ATB!D:D,CS!B:B,ATB!M:M) -> 0
B15: Building on Freehold Land | D15: =SUMIF(ATB!D:D,CS!B:B,ATB!F:F) -> 0 | E15: =SUMIF(ATB!D:D,CS!B:B,ATB!G:G) -> 0 | F15: =SUMIF(ATB!D:D,CS!B:B,ATB!H:H)+SUMIF(ATB!D:D,CS!B:B,ATB!J:J) -> 0 | G15: =SUMIF(ATB!D:D,CS!B:B,ATB!I:I)+SUMIF(ATB!D:D,CS!B:B,ATB!K:K) -> 0 | H15: =SUMIF(ATB!D:D,CS!B:B,ATB!L:L) -> 0 | I15: =SUMIF(ATB!D:D,CS!B:B,ATB!M:M) -> 0
B16: Plant and Machinery | D16: =SUMIF(ATB!D:D,CS!B:B,ATB!F:F) -> 0 | E16: =SUMIF(ATB!D:D,CS!B:B,ATB!G:G) -> 0 | F16: =SUMIF(ATB!D:D,CS!B:B,ATB!H:H)+SUMIF(ATB!D:D,CS!B:B,ATB!J:J) -> 0 | G16: =SUMIF(ATB!D:D,CS!B:B,ATB!I:I)+SUMIF(ATB!D:D,CS!B:B,ATB!K:K) -> 0 | H16: =SUMIF(ATB!D:D,CS!B:B,ATB!L:L) -> 0 | I16: =SUMIF(ATB!D:D,CS!B:B,ATB!M:M) -> 0
B17: Generator | D17: =SUMIF(ATB!D:D,CS!B:B,ATB!F:F) -> 0 | E17: =SUMIF(ATB!D:D,CS!B:B,ATB!G:G) -> 0 | F17: =SUMIF(ATB!D:D,CS!B:B,ATB!H:H)+SUMIF(ATB!D:D,CS!B:B,ATB!J:J) -> 0 | G17: =SUMIF(ATB!D:D,CS!B:B,ATB!I:I)+SUMIF(ATB!D:D,CS!B:B,ATB!K:K) -> 0 | H17: =SUMIF(ATB!D:D,CS!B:B,ATB!L:L) -> 0 | I17: =SUMIF(ATB!D:D,CS!B:B,ATB!M:M) -> 0
B18: Office Equipment | D18: =SUMIF(ATB!D:D,CS!B:B,ATB!F:F) -> 0 | E18: =SUMIF(ATB!D:D,CS!B:B,ATB!G:G) -> 0 | F18: =SUMIF(ATB!D:D,CS!B:B,ATB!H:H)+SUMIF(ATB!D:D,CS!B:B,ATB!J:J) -> 0 | G18: =SUMIF(ATB!D:D,CS!B:B,ATB!I:I)+SUMIF(ATB!D:D,CS!B:B,ATB!K:K) -> 0 | H18: =SUMIF(ATB!D:D,CS!B:B,ATB!L:L) -> 0 | I18: =SUMIF(ATB!D:D,CS!B:B,ATB!M:M) -> 0
B19: Computers | D19: =SUMIF(ATB!D:D,CS!B:B,ATB!F:F) -> 0 | E19: =SUMIF(ATB!D:D,CS!B:B,ATB!G:G) -> 0 | F19: =SUMIF(ATB!D:D,CS!B:B,ATB!H:H)+SUMIF(ATB!D:D,CS!B:B,ATB!J:J) -> 0 | G19: =SUMIF(ATB!D:D,CS!B:B,ATB!I:I)+SUMIF(ATB!D:D,CS!B:B,ATB!K:K) -> 0 | H19: =SUMIF(ATB!D:D,CS!B:B,ATB!L:L) -> 0 | I19: =SUMIF(ATB!D:D,CS!B:B,ATB!M:M) -> 0
B20: Electric Equipment & Installations | D20: =SUMIF(ATB!D:D,CS!B:B,ATB!F:F) -> 0 | E20: =SUMIF(ATB!D:D,CS!B:B,ATB!G:G) -> 0 | F20: =SUMIF(ATB!D:D,CS!B:B,ATB!H:H)+SUMIF(ATB!D:D,CS!B:B,ATB!J:J) -> 0 | G20: =SUMIF(ATB!D:D,CS!B:B,ATB!I:I)+SUMIF(ATB!D:D,CS!B:B,ATB!K:K) -> 0 | H20: =SUMIF(ATB!D:D,CS!B:B,ATB!L:L) -> 0 | I20: =SUMIF(ATB!D:D,CS!B:B,ATB!M:M) -> 0
B21: Furniture and Fixture | D21: =SUMIF(ATB!D:D,CS!B:B,ATB!F:F) -> 0 | E21: =SUMIF(ATB!D:D,CS!B:B,ATB!G:G) -> 0 | F21: =SUMIF(ATB!D:D,CS!B:B,ATB!H:H)+SUMIF(ATB!D:D,CS!B:B,ATB!J:J) -> 0 | G21: =SUMIF(ATB!D:D,CS!B:B,ATB!I:I)+SUMIF(ATB!D:D,CS!B:B,ATB!K:K) -> 0 | H21: =SUMIF(ATB!D:D,CS!B:B,ATB!L:L) -> 0 | I21: =SUMIF(ATB!D:D,CS!B:B,ATB!M:M) -> 0
B22: Vehicles | D22: =SUMIF(ATB!D:D,CS!B:B,ATB!F:F) -> 0 | E22: =SUMIF(ATB!D:D,CS!B:B,ATB!G:G) -> 0 | F22: =SUMIF(ATB!D:D,CS!B:B,ATB!H:H)+SUMIF(ATB!D:D,CS!B:B,ATB!J:J) -> 0 | G22: =SUMIF(ATB!D:D,CS!B:B,ATB!I:I)+SUMIF(ATB!D:D,CS!B:B,ATB!K:K) -> 0 | H22: =SUMIF(ATB!D:D,CS!B:B,ATB!L:L) -> 0 | I22: =SUMIF(ATB!D:D,CS!B:B,ATB!M:M) -> 0
D23: =SUMIF(ATB!D:D,CS!B:B,ATB!F:F) -> 0 | E23: =SUMIF(ATB!D:D,CS!B:B,ATB!G:G) -> 0 | F23: =SUMIF(ATB!D:D,CS!B:B,ATB!H:H)+SUMIF(ATB!D:D,CS!B:B,ATB!J:J) -> 0 | G23: =SUMIF(ATB!D:D,CS!B:B,ATB!I:I)+SUMIF(ATB!D:D,CS!B:B,ATB!K:K) -> 0 | H23: =SUMIF(ATB!D:D,CS!B:B,ATB!L:L) -> 0 | I23: =SUMIF(ATB!D:D,CS!B:B,ATB!M:M) -> 0
B24: Investment properties | D24: =SUMIF(ATB!D:D,CS!B:B,ATB!F:F) -> 0 | E24: =SUMIF(ATB!D:D,CS!B:B,ATB!G:G) -> 0 | F24: =SUMIF(ATB!D:D,CS!B:B,ATB!H:H)+SUMIF(ATB!D:D,CS!B:B,ATB!J:J) -> 0 | G24: =SUMIF(ATB!D:D,CS!B:B,ATB!I:I)+SUMIF(ATB!D:D,CS!B:B,ATB!K:K) -> 0 | H24: =SUMIF(ATB!D:D,CS!B:B,ATB!L:L) -> 0 | I24: =SUMIF(ATB!D:D,CS!B:B,ATB!M:M) -> 0
D25: =SUMIF(ATB!D:D,CS!B:B,ATB!F:F) -> 0 | E25: =SUMIF(ATB!D:D,CS!B:B,ATB!G:G) -> 0 | F25: =SUMIF(ATB!D:D,CS!B:B,ATB!H:H)+SUMIF(ATB!D:D,CS!B:B,ATB!J:J) -> 0 | G25: =SUMIF(ATB!D:D,CS!B:B,ATB!I:I)+SUMIF(ATB!D:D,CS!B:B,ATB!K:K) -> 0 | H25: =SUMIF(ATB!D:D,CS!B:B,ATB!L:L) -> 0 | I25: =SUMIF(ATB!D:D,CS!B:B,ATB!M:M) -> 0
D26: =SUMIF(ATB!D:D,CS!B:B,ATB!F:F) -> 0 | E26: =SUMIF(ATB!D:D,CS!B:B,ATB!G:G) -> 0 | F26: =SUMIF(ATB!D:D,CS!B:B,ATB!H:H)+SUMIF(ATB!D:D,CS!B:B,ATB!J:J) -> 0 | G26: =SUMIF(ATB!D:D,CS!B:B,ATB!I:I)+SUMIF(ATB!D:D,CS!B:B,ATB!K:K) -> 0 | H26: =SUMIF(ATB!D:D,CS!B:B,ATB!L:L) -> 0 | I26: =SUMIF(ATB!D:D,CS!B:B,ATB!M:M) -> 0
D27: =SUMIF(ATB!D:D,CS!B:B,ATB!F:F) -> 0 | E27: =SUMIF(ATB!D:D,CS!B:B,ATB!G:G) -> 0 | F27: =SUMIF(ATB!D:D,CS!B:B,ATB!H:H)+SUMIF(ATB!D:D,CS!B:B,ATB!J:J) -> 0 | G27: =SUMIF(ATB!D:D,CS!B:B,ATB!I:I)+SUMIF(ATB!D:D,CS!B:B,ATB!K:K) -> 0 | H27: =SUMIF(ATB!D:D,CS!B:B,ATB!L:L) -> 0 | I27: =SUMIF(ATB!D:D,CS!B:B,ATB!M:M) -> 0
B28: Intangible assets | D28: =SUMIF(ATB!D:D,CS!B:B,ATB!F:F) -> 0 | E28: =SUMIF(ATB!D:D,CS!B:B,ATB!G:G) -> 0 | F28: =SUMIF(ATB!D:D,CS!B:B,ATB!H:H)+SUMIF(ATB!D:D,CS!B:B,ATB!J:J) -> 0 | G28: =SUMIF(ATB!D:D,CS!B:B,ATB!I:I)+SUMIF(ATB!D:D,CS!B:B,ATB!K:K) -> 0 | H28: =SUMIF(ATB!D:D,CS!B:B,ATB!L:L) -> 0 | I28: =SUMIF(ATB!D:D,CS!B:B,ATB!M:M) -> 0
D29: =SUMIF(ATB!D:D,CS!B:B,ATB!F:F) -> 0 | E29: =SUMIF(ATB!D:D,CS!B:B,ATB!G:G) -> 0 | F29: =SUMIF(ATB!D:D,CS!B:B,ATB!H:H)+SUMIF(ATB!D:D,CS!B:B,ATB!J:J) -> 0 | G29: =SUMIF(ATB!D:D,CS!B:B,ATB!I:I)+SUMIF(ATB!D:D,CS!B:B,ATB!K:K) -> 0 | H29: =SUMIF(ATB!D:D,CS!B:B,ATB!L:L) -> 0 | I29: =SUMIF(ATB!D:D,CS!B:B,ATB!M:M) -> 0
D30: =SUMIF(ATB!D:D,CS!B:B,ATB!F:F) -> 0 | E30: =SUMIF(ATB!D:D,CS!B:B,ATB!G:G) -> 0 | F30: =SUMIF(ATB!D:D,CS!B:B,ATB!H:H)+SUMIF(ATB!D:D,CS!B:B,ATB!J:J) -> 0 | G30: =SUMIF(ATB!D:D,CS!B:B,ATB!I:I)+SUMIF(ATB!D:D,CS!B:B,ATB!K:K) -> 0 | H30: =SUMIF(ATB!D:D,CS!B:B,ATB!L:L) -> 0 | I30: =SUMIF(ATB!D:D,CS!B:B,ATB!M:M) -> 0
D31: =SUMIF(ATB!D:D,CS!B:B,ATB!F:F) -> 0 | E31: =SUMIF(ATB!D:D,CS!B:B,ATB!G:G) -> 0 | F31: =SUMIF(ATB!D:D,CS!B:B,ATB!H:H)+SUMIF(ATB!D:D,CS!B:B,ATB!J:J) -> 0 | G31: =SUMIF(ATB!D:D,CS!B:B,ATB!I:I)+SUMIF(ATB!D:D,CS!B:B,ATB!K:K) -> 0 | H31: =SUMIF(ATB!D:D,CS!B:B,ATB!L:L) -> 0 | I31: =SUMIF(ATB!D:D,CS!B:B,ATB!M:M) -> 0
B32: Deferred tax assets | D32: =SUMIF(ATB!D:D,CS!B:B,ATB!F:F) -> 0 | E32: =SUMIF(ATB!D:D,CS!B:B,ATB!G:G) -> 0 | F32: =SUMIF(ATB!D:D,CS!B:B,ATB!H:H)+SUMIF(ATB!D:D,CS!B:B,ATB!J:J) -> 0 | G32: =SUMIF(ATB!D:D,CS!B:B,ATB!I:I)+SUMIF(ATB!D:D,CS!B:B,ATB!K:K) -> 0 | H32: =SUMIF(ATB!D:D,CS!B:B,ATB!L:L) -> 0 | I32: =SUMIF(ATB!D:D,CS!B:B,ATB!M:M) -> 0
D33: =SUMIF(ATB!D:D,CS!B:B,ATB!F:F) -> 0 | E33: =SUMIF(ATB!D:D,CS!B:B,ATB!G:G) -> 0 | F33: =SUMIF(ATB!D:D,CS!B:B,ATB!H:H)+SUMIF(ATB!D:D,CS!B:B,ATB!J:J) -> 0 | G33: =SUMIF(ATB!D:D,CS!B:B,ATB!I:I)+SUMIF(ATB!D:D,CS!B:B,ATB!K:K) -> 0 | H33: =SUMIF(ATB!D:D,CS!B:B,ATB!L:L) -> 0 | I33: =SUMIF(ATB!D:D,CS!B:B,ATB!M:M) -> 0
D34: =SUMIF(ATB!D:D,CS!B:B,ATB!F:F) -> 0 | E34: =SUMIF(ATB!D:D,CS!B:B,ATB!G:G) -> 0 | F34: =SUMIF(ATB!D:D,CS!B:B,ATB!H:H)+SUMIF(ATB!D:D,CS!B:B,ATB!J:J) -> 0 | G34: =SUMIF(ATB!D:D,CS!B:B,ATB!I:I)+SUMIF(ATB!D:D,CS!B:B,ATB!K:K) -> 0 | H34: =SUMIF(ATB!D:D,CS!B:B,ATB!L:L) -> 0 | I34: =SUMIF(ATB!D:D,CS!B:B,ATB!M:M) -> 0
D35: =SUMIF(ATB!D:D,CS!B:B,ATB!F:F) -> 0 | E35: =SUMIF(ATB!D:D,CS!B:B,ATB!G:G) -> 0 | F35: =SUMIF(ATB!D:D,CS!B:B,ATB!H:H)+SUMIF(ATB!D:D,CS!B:B,ATB!J:J) -> 0 | G35: =SUMIF(ATB!D:D,CS!B:B,ATB!I:I)+SUMIF(ATB!D:D,CS!B:B,ATB!K:K) -> 0 | H35: =SUMIF(ATB!D:D,CS!B:B,ATB!L:L) -> 0 | I35: =SUMIF(ATB!D:D,CS!B:B,ATB!M:M) -> 0
B36: Held-to-maturity investments | D36: =SUMIF(ATB!D:D,CS!B:B,ATB!F:F) -> 0 | E36: =SUMIF(ATB!D:D,CS!B:B,ATB!G:G) -> 0 | F36: =SUMIF(ATB!D:D,CS!B:B,ATB!H:H)+SUMIF(ATB!D:D,CS!B:B,ATB!J:J) -> 0 | G36: =SUMIF(ATB!D:D,CS!B:B,ATB!I:I)+SUMIF(ATB!D:D,CS!B:B,ATB!K:K) -> 0 | H36: =SUMIF(ATB!D:D,CS!B:B,ATB!L:L) -> 0 | I36: =SUMIF(ATB!D:D,CS!B:B,ATB!M:M) -> 0
B37: Debentures - NCA | D37: =SUMIF(ATB!D:D,CS!B:B,ATB!F:F) -> 0 | E37: =SUMIF(ATB!D:D,CS!B:B,ATB!G:G) -> 0 | F37: =SUMIF(ATB!D:D,CS!B:B,ATB!H:H)+SUMIF(ATB!D:D,CS!B:B,ATB!J:J) -> 0 | G37: =SUMIF(ATB!D:D,CS!B:B,ATB!I:I)+SUMIF(ATB!D:D,CS!B:B,ATB!K:K) -> 0 | H37: =SUMIF(ATB!D:D,CS!B:B,ATB!L:L) -> 0 | I37: =SUMIF(ATB!D:D,CS!B:B,ATB!M:M) -> 0
B38: Zero coupon bonds | D38: =SUMIF(ATB!D:D,CS!B:B,ATB!F:F) -> 0 | E38: =SUMIF(ATB!D:D,CS!B:B,ATB!G:G) -> 0 | F38: =SUMIF(ATB!D:D,CS!B:B,ATB!H:H)+SUMIF(ATB!D:D,CS!B:B,ATB!J:J) -> 0 | G38: =SUMIF(ATB!D:D,CS!B:B,ATB!I:I)+SUMIF(ATB!D:D,CS!B:B,ATB!K:K) -> 0 | H38: =SUMIF(ATB!D:D,CS!B:B,ATB!L:L) -> 0 | I38: =SUMIF(ATB!D:D,CS!B:B,ATB!M:M) -> 0
D39: =SUMIF(ATB!D:D,CS!B:B,ATB!F:F) -> 0 | E39: =SUMIF(ATB!D:D,CS!B:B,ATB!G:G) -> 0 | F39: =SUMIF(ATB!D:D,CS!B:B,ATB!H:H)+SUMIF(ATB!D:D,CS!B:B,ATB!J:J) -> 0 | G39: =SUMIF(ATB!D:D,CS!B:B,ATB!I:I)+SUMIF(ATB!D:D,CS!B:B,ATB!K:K) -> 0 | H39: =SUMIF(ATB!D:D,CS!B:B,ATB!L:L) -> 0 | I39: =SUMIF(ATB!D:D,CS!B:B,ATB!M:M) -> 0
D40: =SUMIF(ATB!D:D,CS!B:B,ATB!F:F) -> 0 | E40: =SUMIF(ATB!D:D,CS!B:B,ATB!G:G) -> 0 | F40: =SUMIF(ATB!D:D,CS!B:B,ATB!H:H)+SUMIF(ATB!D:D,CS!B:B,ATB!J:J) -> 0 | G40: =SUMIF(ATB!D:D,CS!B:B,ATB!I:I)+SUMIF(ATB!D:D,CS!B:B,ATB!K:K) -> 0 | H40: =SUMIF(ATB!D:D,CS!B:B,ATB!L:L) -> 0 | I40: =SUMIF(ATB!D:D,CS!B:B,ATB!M:M) -> 0
D41: =SUMIF(ATB!D:D,CS!B:B,ATB!F:F) -> 0 | E41: =SUMIF(ATB!D:D,CS!B:B,ATB!G:G) -> 0 | F41: =SUMIF(ATB!D:D,CS!B:B,ATB!H:H)+SUMIF(ATB!D:D,CS!B:B,ATB!J:J) -> 0 | G41: =SUMIF(ATB!D:D,CS!B:B,ATB!I:I)+SUMIF(ATB!D:D,CS!B:B,ATB!K:K) -> 0 | H41: =SUMIF(ATB!D:D,CS!B:B,ATB!L:L) -> 0 | I41: =SUMIF(ATB!D:D,CS!B:B,ATB!M:M) -> 0
B42: Available-for-sale financial assets | D42: =SUMIF(ATB!D:D,CS!B:B,ATB!F:F) -> 0 | E42: =SUMIF(ATB!D:D,CS!B:B,ATB!G:G) -> 0 | F42: =SUMIF(ATB!D:D,CS!B:B,ATB!H:H)+SUMIF(ATB!D:D,CS!B:B,ATB!J:J) -> 0 | G42: =SUMIF(ATB!D:D,CS!B:B,ATB!I:I)+SUMIF(ATB!D:D,CS!B:B,ATB!K:K) -> 0 | H42: =SUMIF(ATB!D:D,CS!B:B,ATB!L:L) -> 0 | I42: =SUMIF(ATB!D:D,CS!B:B,ATB!M:M) -> 0
B43: Listed securities | D43: =SUMIF(ATB!D:D,CS!B:B,ATB!F:F) -> 0 | E43: =SUMIF(ATB!D:D,CS!B:B,ATB!G:G) -> 0 | F43: =SUMIF(ATB!D:D,CS!B:B,ATB!H:H)+SUMIF(ATB!D:D,CS!B:B,ATB!J:J) -> 0 | G43: =SUMIF(ATB!D:D,CS!B:B,ATB!I:I)+SUMIF(ATB!D:D,CS!B:B,ATB!K:K) -> 0 | H43: =SUMIF(ATB!D:D,CS!B:B,ATB!L:L) -> 0 | I43: =SUMIF(ATB!D:D,CS!B:B,ATB!M:M) -> 0
B44: Equity securities - Listed | D44: =SUMIF(ATB!D:D,CS!B:B,ATB!F:F) -> 0 | E44: =SUMIF(ATB!D:D,CS!B:B,ATB!G:G) -> 0 | F44: =SUMIF(ATB!D:D,CS!B:B,ATB!H:H)+SUMIF(ATB!D:D,CS!B:B,ATB!J:J) -> 0 | G44: =SUMIF(ATB!D:D,CS!B:B,ATB!I:I)+SUMIF(ATB!D:D,CS!B:B,ATB!K:K) -> 0 | H44: =SUMIF(ATB!D:D,CS!B:B,ATB!L:L) -> 0 | I44: =SUMIF(ATB!D:D,CS!B:B,ATB!M:M) -> 0
B45: Debentures - Listed | D45: =SUMIF(ATB!D:D,CS!B:B,ATB!F:F) -> 0 | E45: =SUMIF(ATB!D:D,CS!B:B,ATB!G:G) -> 0 | F45: =SUMIF(ATB!D:D,CS!B:B,ATB!H:H)+SUMIF(ATB!D:D,CS!B:B,ATB!J:J) -> 0 | G45: =SUMIF(ATB!D:D,CS!B:B,ATB!I:I)+SUMIF(ATB!D:D,CS!B:B,ATB!K:K) -> 0 | H45: =SUMIF(ATB!D:D,CS!B:B,ATB!L:L) -> 0 | I45: =SUMIF(ATB!D:D,CS!B:B,ATB!M:M) -> 0
B46: Corporate bonds - Listed | D46: =SUMIF(ATB!D:D,CS!B:B,ATB!F:F) -> 0 | E46: =SUMIF(ATB!D:D,CS!B:B,ATB!G:G) -> 0 | F46: =SUMIF(ATB!D:D,CS!B:B,ATB!H:H)+SUMIF(ATB!D:D,CS!B:B,ATB!J:J) -> 0 | G46: =SUMIF(ATB!D:D,CS!B:B,ATB!I:I)+SUMIF(ATB!D:D,CS!B:B,ATB!K:K) -> 0 | H46: =SUMIF(ATB!D:D,CS!B:B,ATB!L:L) -> 0 | I46: =SUMIF(ATB!D:D,CS!B:B,ATB!M:M) -> 0
B47: Unlisted securities | D47: =SUMIF(ATB!D:D,CS!B:B,ATB!F:F) -> 0 | E47: =SUMIF(ATB!D:D,CS!B:B,ATB!G:G) -> 0 | F47: =SUMIF(ATB!D:D,CS!B:B,ATB!H:H)+SUMIF(ATB!D:D,CS!B:B,ATB!J:J) -> 0 | G47: =SUMIF(ATB!D:D,CS!B:B,ATB!I:I)+SUMIF(ATB!D:D,CS!B:B,ATB!K:K) -> 0 | H47: =SUMIF(ATB!D:D,CS!B:B,ATB!L:L) -> 0 | I47: =SUMIF(ATB!D:D,CS!B:B,ATB!M:M) -> 0
B48: Equity securities - Unlisted | D48: =SUMIF(ATB!D:D,CS!B:B,ATB!F:F) -> 0 | E48: =SUMIF(ATB!D:D,CS!B:B,ATB!G:G) -> 0 | F48: =SUMIF(ATB!D:D,CS!B:B,ATB!H:H)+SUMIF(ATB!D:D,CS!B:B,ATB!J:J) -> 0 | G48: =SUMIF(ATB!D:D,CS!B:B,ATB!I:I)+SUMIF(ATB!D:D,CS!B:B,ATB!K:K) -> 0 | H48: =SUMIF(ATB!D:D,CS!B:B,ATB!L:L) -> 0 | I48: =SUMIF(ATB!D:D,CS!B:B,ATB!M:M) -> 0
B49: Debentures - Unlisted | D49: =SUMIF(ATB!D:D,CS!B:B,ATB!F:F) -> 0 | E49: =SUMIF(ATB!D:D,CS!B:B,ATB!G:G) -> 0 | F49: =SUMIF(ATB!D:D,CS!B:B,ATB!H:H)+SUMIF(ATB!D:D,CS!B:B,ATB!J:J) -> 0 | G49: =SUMIF(ATB!D:D,CS!B:B,ATB!I:I)+SUMIF(ATB!D:D,CS!B:B,ATB!K:K) -> 0 | H49: =SUMIF(ATB!D:D,CS!B:B,ATB!L:L) -> 0 | I49: =SUMIF(ATB!D:D,CS!B:B,ATB!M:M) -> 0
B50: Preference shares - Unlisted | D50: =SUMIF(ATB!D:D,CS!B:B,ATB!F:F) -> 0 | E50: =SUMIF(ATB!D:D,CS!B:B,ATB!G:G) -> 0 | F50: =SUMIF(ATB!D:D,CS!B:B,ATB!H:H)+SUMIF(ATB!D:D,CS!B:B,ATB!J:J) -> 0 | G50: =SUMIF(ATB!D:D,CS!B:B,ATB!I:I)+SUMIF(ATB!D:D,CS!B:B,ATB!K:K) -> 0 | H50: =SUMIF(ATB!D:D,CS!B:B,ATB!L:L) -> 0 | I50: =SUMIF(ATB!D:D,CS!B:B,ATB!M:M) -> 0
D51: =SUMIF(ATB!D:D,CS!B:B,ATB!F:F) -> 0 | E51: =SUMIF(ATB!D:D,CS!B:B,ATB!G:G) -> 0 | F51: =SUMIF(ATB!D:D,CS!B:B,ATB!H:H)+SUMIF(ATB!D:D,CS!B:B,ATB!J:J) -> 0 | G51: =SUMIF(ATB!D:D,CS!B:B,ATB!I:I)+SUMIF(ATB!D:D,CS!B:B,ATB!K:K) -> 0 | H51: =SUMIF(ATB!D:D,CS!B:B,ATB!L:L) -> 0 | I51: =SUMIF(ATB!D:D,CS!B:B,ATB!M:M) -> 0
D52: =SUMIF(ATB!D:D,CS!B:B,ATB!F:F) -> 0 | E52: =SUMIF(ATB!D:D,CS!B:B,ATB!G:G) -> 0 | F52: =SUMIF(ATB!D:D,CS!B:B,ATB!H:H)+SUMIF(ATB!D:D,CS!B:B,ATB!J:J) -> 0 | G52: =SUMIF(ATB!D:D,CS!B:B,ATB!I:I)+SUMIF(ATB!D:D,CS!B:B,ATB!K:K) -> 0 | H52: =SUMIF(ATB!D:D,CS!B:B,ATB!L:L) -> 0 | I52: =SUMIF(ATB!D:D,CS!B:B,ATB!M:M) -> 0
D53: =SUMIF(ATB!D:D,CS!B:B,ATB!F:F) -> 0 | E53: =SUMIF(ATB!D:D,CS!B:B,ATB!G:G) -> 0 | F53: =SUMIF(ATB!D:D,CS!B:B,ATB!H:H)+SUMIF(ATB!D:D,CS!B:B,ATB!J:J) -> 0 | G53: =SUMIF(ATB!D:D,CS!B:B,ATB!I:I)+SUMIF(ATB!D:D,CS!B:B,ATB!K:K) -> 0 | H53: =SUMIF(ATB!D:D,CS!B:B,ATB!L:L) -> 0 | I53: =SUMIF(ATB!D:D,CS!B:B,ATB!M:M) -> 0
B54: Current assets | D54: =SUMIF(ATB!D:D,CS!B:B,ATB!F:F) -> 0 | E54: =SUMIF(ATB!D:D,CS!B:B,ATB!G:G) -> 0 | F54: =SUMIF(ATB!D:D,CS!B:B,ATB!H:H)+SUMIF(ATB!D:D,CS!B:B,ATB!J:J) -> 0 | G54: =SUMIF(ATB!D:D,CS!B:B,ATB!I:I)+SUMIF(ATB!D:D,CS!B:B,ATB!K:K) -> 0 | H54: =SUMIF(ATB!D:D,CS!B:B,ATB!L:L) -> 0 | I54: =SUMIF(ATB!D:D,CS!B:B,ATB!M:M) -> 0
B55: Inventories | D55: =SUMIF(ATB!D:D,CS!B:B,ATB!F:F) -> 0 | E55: =SUMIF(ATB!D:D,CS!B:B,ATB!G:G) -> 0 | F55: =SUMIF(ATB!D:D,CS!B:B,ATB!H:H)+SUMIF(ATB!D:D,CS!B:B,ATB!J:J) -> 0 | G55: =SUMIF(ATB!D:D,CS!B:B,ATB!I:I)+SUMIF(ATB!D:D,CS!B:B,ATB!K:K) -> 0 | H55: =SUMIF(ATB!D:D,CS!B:B,ATB!L:L) -> 0 | I55: =SUMIF(ATB!D:D,CS!B:B,ATB!M:M) -> 0
B56: Stores, spares and loose tools | D56: =SUMIF(ATB!D:D,CS!B:B,ATB!F:F) -> 0 | E56: =SUMIF(ATB!D:D,CS!B:B,ATB!G:G) -> 0 | F56: =SUMIF(ATB!D:D,CS!B:B,ATB!H:H)+SUMIF(ATB!D:D,CS!B:B,ATB!J:J) -> 0 | G56: =SUMIF(ATB!D:D,CS!B:B,ATB!I:I)+SUMIF(ATB!D:D,CS!B:B,ATB!K:K) -> 0 | H56: =SUMIF(ATB!D:D,CS!B:B,ATB!L:L) -> 0 | I56: =SUMIF(ATB!D:D,CS!B:B,ATB!M:M) -> 0
B57: Raw materials | D57: =SUMIF(ATB!D:D,CS!B:B,ATB!F:F) -> 0 | E57: =SUMIF(ATB!D:D,CS!B:B,ATB!G:G) -> 0 | F57: =SUMIF(ATB!D:D,CS!B:B,ATB!H:H)+SUMIF(ATB!D:D,CS!B:B,ATB!J:J) -> 0 | G57: =SUMIF(ATB!D:D,CS!B:B,ATB!I:I)+SUMIF(ATB!D:D,CS!B:B,ATB!K:K) -> 0 | H57: =SUMIF(ATB!D:D,CS!B:B,ATB!L:L) -> 0 | I57: =SUMIF(ATB!D:D,CS!B:B,ATB!M:M) -> 0
B58: Work in progress | D58: =SUMIF(ATB!D:D,CS!B:B,ATB!F:F) -> 0 | E58: =SUMIF(ATB!D:D,CS!B:B,ATB!G:G) -> 0 | F58: =SUMIF(ATB!D:D,CS!B:B,ATB!H:H)+SUMIF(ATB!D:D,CS!B:B,ATB!J:J) -> 0 | G58: =SUMIF(ATB!D:D,CS!B:B,ATB!I:I)+SUMIF(ATB!D:D,CS!B:B,ATB!K:K) -> 0 | H58: =SUMIF(ATB!D:D,CS!B:B,ATB!L:L) -> 0 | I58: =SUMIF(ATB!D:D,CS!B:B,ATB!M:M) -> 0
B59: Finished goods – at cost | D59: =SUMIF(ATB!D:D,CS!B:B,ATB!F:F) -> 0 | E59: =SUMIF(ATB!D:D,CS!B:B,ATB!G:G) -> 0 | F59: =SUMIF(ATB!D:D,CS!B:B,ATB!H:H)+SUMIF(ATB!D:D,CS!B:B,ATB!J:J) -> 0 | G59: =SUMIF(ATB!D:D,CS!B:B,ATB!I:I)+SUMIF(ATB!D:D,CS!B:B,ATB!K:K) -> 0 | H59: =SUMIF(ATB!D:D,CS!B:B,ATB!L:L) -> 0 | I59: =SUMIF(ATB!D:D,CS!B:B,ATB!M:M) -> 0
B60: Finished goods – at fair value less cost to sell | D60: =SUMIF(ATB!D:D,CS!B:B,ATB!F:F) -> 0 | E60: =SUMIF(ATB!D:D,CS!B:B,ATB!G:G) -> 0 | F60: =SUMIF(ATB!D:D,CS!B:B,ATB!H:H)+SUMIF(ATB!D:D,CS!B:B,ATB!J:J) -> 0 | G60: =SUMIF(ATB!D:D,CS!B:B,ATB!I:I)+SUMIF(ATB!D:D,CS!B:B,ATB!K:K) -> 0 | H60: =SUMIF(ATB!D:D,CS!B:B,ATB!L:L) -> 0 | I60: =SUMIF(ATB!D:D,CS!B:B,ATB!M:M) -> 0
B61: Stock in transit | D61: =SUMIF(ATB!D:D,CS!B:B,ATB!F:F) -> 0 | E61: =SUMIF(ATB!D:D,CS!B:B,ATB!G:G) -> 0 | F61: =SUMIF(ATB!D:D,CS!B:B,ATB!H:H)+SUMIF(ATB!D:D,CS!B:B,ATB!J:J) -> 0 | G61: =SUMIF(ATB!D:D,CS!B:B,ATB!I:I)+SUMIF(ATB!D:D,CS!B:B,ATB!K:K) -> 0 | H61: =SUMIF(ATB!D:D,CS!B:B,ATB!L:L) -> 0 | I61: =SUMIF(ATB!D:D,CS!B:B,ATB!M:M) -> 0
B62: Scrap stock | D62: =SUMIF(ATB!D:D,CS!B:B,ATB!F:F) -> 0 | E62: =SUMIF(ATB!D:D,CS!B:B,ATB!G:G) -> 0 | F62: =SUMIF(ATB!D:D,CS!B:B,ATB!H:H)+SUMIF(ATB!D:D,CS!B:B,ATB!J:J) -> 0 | G62: =SUMIF(ATB!D:D,CS!B:B,ATB!I:I)+SUMIF(ATB!D:D,CS!B:B,ATB!K:K) -> 0 | H62: =SUMIF(ATB!D:D,CS!B:B,ATB!L:L) -> 0 | I62: =SUMIF(ATB!D:D,CS!B:B,ATB!M:M) -> 0
D63: =SUMIF(ATB!D:D,CS!B:B,ATB!F:F) -> 0 | E63: =SUMIF(ATB!D:D,CS!B:B,ATB!G:G) -> 0 | F63: =SUMIF(ATB!D:D,CS!B:B,ATB!H:H)+SUMIF(ATB!D:D,CS!B:B,ATB!J:J) -> 0 | G63: =SUMIF(ATB!D:D,CS!B:B,ATB!I:I)+SUMIF(ATB!D:D,CS!B:B,ATB!K:K) -> 0 | H63: =SUMIF(ATB!D:D,CS!B:B,ATB!L:L) -> 0 | I63: =SUMIF(ATB!D:D,CS!B:B,ATB!M:M) -> 0
D64: =SUMIF(ATB!D:D,CS!B:B,ATB!F:F) -> 0 | E64: =SUMIF(ATB!D:D,CS!B:B,ATB!G:G) -> 0 | F64: =SUMIF(ATB!D:D,CS!B:B,ATB!H:H)+SUMIF(ATB!D:D,CS!B:B,ATB!J:J) -> 0 | G64: =SUMIF(ATB!D:D,CS!B:B,ATB!I:I)+SUMIF(ATB!D:D,CS!B:B,ATB!K:K) -> 0 | H64: =SUMIF(ATB!D:D,CS!B:B,ATB!L:L) -> 0 | I64: =SUMIF(ATB!D:D,CS!B:B,ATB!M:M) -> 0
B65: Trade receivables - net | D65: =SUMIF(ATB!D:D,CS!B:B,ATB!F:F) -> 0 | E65: =SUMIF(ATB!D:D,CS!B:B,ATB!G:G) -> 0 | F65: =SUMIF(ATB!D:D,CS!B:B,ATB!H:H)+SUMIF(ATB!D:D,CS!B:B,ATB!J:J) -> 0 | G65: =SUMIF(ATB!D:D,CS!B:B,ATB!I:I)+SUMIF(ATB!D:D,CS!B:B,ATB!K:K) -> 0 | H65: =SUMIF(ATB!D:D,CS!B:B,ATB!L:L) -> 0 | I65: =SUMIF(ATB!D:D,CS!B:B,ATB!M:M) -> 0
B66: Trade receivables | D66: =SUMIF(ATB!D:D,CS!B:B,ATB!F:F) -> 0 | E66: =SUMIF(ATB!D:D,CS!B:B,ATB!G:G) -> 0 | F66: =SUMIF(ATB!D:D,CS!B:B,ATB!H:H)+SUMIF(ATB!D:D,CS!B:B,ATB!J:J) -> 0 | G66: =SUMIF(ATB!D:D,CS!B:B,ATB!I:I)+SUMIF(ATB!D:D,CS!B:B,ATB!K:K) -> 0 | H66: =SUMIF(ATB!D:D,CS!B:B,ATB!L:L) -> 0 | I66: =SUMIF(ATB!D:D,CS!B:B,ATB!M:M) -> 0
B67: Provision for impairment | D67: =SUMIF(ATB!D:D,CS!B:B,ATB!F:F) -> 0 | E67: =SUMIF(ATB!D:D,CS!B:B,ATB!G:G) -> 0 | F67: =SUMIF(ATB!D:D,CS!B:B,ATB!H:H)+SUMIF(ATB!D:D,CS!B:B,ATB!J:J) -> 0 | G67: =SUMIF(ATB!D:D,CS!B:B,ATB!I:I)+SUMIF(ATB!D:D,CS!B:B,ATB!K:K) -> 0 | H67: =SUMIF(ATB!D:D,CS!B:B,ATB!L:L) -> 0 | I67: =SUMIF(ATB!D:D,CS!B:B,ATB!M:M) -> 0
B68: Total trade receivables - net | D68: =SUMIF(ATB!D:D,CS!B:B,ATB!F:F) -> 0 | E68: =SUMIF(ATB!D:D,CS!B:B,ATB!G:G) -> 0 | F68: =SUMIF(ATB!D:D,CS!B:B,ATB!H:H)+SUMIF(ATB!D:D,CS!B:B,ATB!J:J) -> 0 | G68: =SUMIF(ATB!D:D,CS!B:B,ATB!I:I)+SUMIF(ATB!D:D,CS!B:B,ATB!K:K) -> 0 | H68: =SUMIF(ATB!D:D,CS!B:B,ATB!L:L) -> 0 | I68: =SUMIF(ATB!D:D,CS!B:B,ATB!M:M) -> 0
D69: =SUMIF(ATB!D:D,CS!B:B,ATB!F:F) -> 0 | E69: =SUMIF(ATB!D:D,CS!B:B,ATB!G:G) -> 0 | F69: =SUMIF(ATB!D:D,CS!B:B,ATB!H:H)+SUMIF(ATB!D:D,CS!B:B,ATB!J:J) -> 0 | G69: =SUMIF(ATB!D:D,CS!B:B,ATB!I:I)+SUMIF(ATB!D:D,CS!B:B,ATB!K:K) -> 0 | H69: =SUMIF(ATB!D:D,CS!B:B,ATB!L:L) -> 0 | I69: =SUMIF(ATB!D:D,CS!B:B,ATB!M:M) -> 0
D70: =SUMIF(ATB!D:D,CS!B:B,ATB!F:F) -> 0 | E70: =SUMIF(ATB!D:D,CS!B:B,ATB!G:G) -> 0 | F70: =SUMIF(ATB!D:D,CS!B:B,ATB!H:H)+SUMIF(ATB!D:D,CS!B:B,ATB!J:J) -> 0 | G70: =SUMIF(ATB!D:D,CS!B:B,ATB!I:I)+SUMIF(ATB!D:D,CS!B:B,ATB!K:K) -> 0 | H70: =SUMIF(ATB!D:D,CS!B:B,ATB!L:L) -> 0 | I70: =SUMIF(ATB!D:D,CS!B:B,ATB!M:M) -> 0
D71: =SUMIF(ATB!D:D,CS!B:B,ATB!F:F) -> 0 | E71: =SUMIF(ATB!D:D,CS!B:B,ATB!G:G) -> 0 | F71: =SUMIF(ATB!D:D,CS!B:B,ATB!H:H)+SUMIF(ATB!D:D,CS!B:B,ATB!J:J) -> 0 | G71: =SUMIF(ATB!D:D,CS!B:B,ATB!I:I)+SUMIF(ATB!D:D,CS!B:B,ATB!K:K) -> 0 | H71: =SUMIF(ATB!D:D,CS!B:B,ATB!L:L) -> 0 | I71: =SUMIF(ATB!D:D,CS!B:B,ATB!M:M) -> 0
B72: Advances, deposits and prepayments | D72: =SUMIF(ATB!D:D,CS!B:B,ATB!F:F) -> 0 | E72: =SUMIF(ATB!D:D,CS!B:B,ATB!G:G) -> 0 | F72: =SUMIF(ATB!D:D,CS!B:B,ATB!H:H)+SUMIF(ATB!D:D,CS!B:B,ATB!J:J) -> 0 | G72: =SUMIF(ATB!D:D,CS!B:B,ATB!I:I)+SUMIF(ATB!D:D,CS!B:B,ATB!K:K) -> 0 | H72: =SUMIF(ATB!D:D,CS!B:B,ATB!L:L) -> 0 | I72: =SUMIF(ATB!D:D,CS!B:B,ATB!M:M) -> 0
B73: Advances to employees against salary | D73: =SUMIF(ATB!D:D,CS!B:B,ATB!F:F) -> 0 | E73: =SUMIF(ATB!D:D,CS!B:B,ATB!G:G) -> 0 | F73: =SUMIF(ATB!D:D,CS!B:B,ATB!H:H)+SUMIF(ATB!D:D,CS!B:B,ATB!J:J) -> 0 | G73: =SUMIF(ATB!D:D,CS!B:B,ATB!I:I)+SUMIF(ATB!D:D,CS!B:B,ATB!K:K) -> 0 | H73: =SUMIF(ATB!D:D,CS!B:B,ATB!L:L) -> 0 | I73: =SUMIF(ATB!D:D,CS!B:B,ATB!M:M) -> 0
B74: Advances to employees against expenses | D74: =SUMIF(ATB!D:D,CS!B:B,ATB!F:F) -> 0 | E74: =SUMIF(ATB!D:D,CS!B:B,ATB!G:G) -> 0 | F74: =SUMIF(ATB!D:D,CS!B:B,ATB!H:H)+SUMIF(ATB!D:D,CS!B:B,ATB!J:J) -> 0 | G74: =SUMIF(ATB!D:D,CS!B:B,ATB!I:I)+SUMIF(ATB!D:D,CS!B:B,ATB!K:K) -> 0 | H74: =SUMIF(ATB!D:D,CS!B:B,ATB!L:L) -> 0 | I74: =SUMIF(ATB!D:D,CS!B:B,ATB!M:M) -> 0
B75: Short term security deposits | D75: =SUMIF(ATB!D:D,CS!B:B,ATB!F:F) -> 0 | E75: =SUMIF(ATB!D:D,CS!B:B,ATB!G:G) -> 0 | F75: =SUMIF(ATB!D:D,CS!B:B,ATB!H:H)+SUMIF(ATB!D:D,CS!B:B,ATB!J:J) -> 0 | G75: =SUMIF(ATB!D:D,CS!B:B,ATB!I:I)+SUMIF(ATB!D:D,CS!B:B,ATB!K:K) -> 0 | H75: =SUMIF(ATB!D:D,CS!B:B,ATB!L:L) -> 0 | I75: =SUMIF(ATB!D:D,CS!B:B,ATB!M:M) -> 0
B76: Letter of credit margin | D76: =SUMIF(ATB!D:D,CS!B:B,ATB!F:F) -> 0 | E76: =SUMIF(ATB!D:D,CS!B:B,ATB!G:G) -> 0 | F76: =SUMIF(ATB!D:D,CS!B:B,ATB!H:H)+SUMIF(ATB!D:D,CS!B:B,ATB!J:J) -> 0 | G76: =SUMIF(ATB!D:D,CS!B:B,ATB!I:I)+SUMIF(ATB!D:D,CS!B:B,ATB!K:K) -> 0 | H76: =SUMIF(ATB!D:D,CS!B:B,ATB!L:L) -> 0 | I76: =SUMIF(ATB!D:D,CS!B:B,ATB!M:M) -> 0
B77: Sales tax refundable | D77: =SUMIF(ATB!D:D,CS!B:B,ATB!F:F) -> 0 | E77: =SUMIF(ATB!D:D,CS!B:B,ATB!G:G) -> 0 | F77: =SUMIF(ATB!D:D,CS!B:B,ATB!H:H)+SUMIF(ATB!D:D,CS!B:B,ATB!J:J) -> 0 | G77: =SUMIF(ATB!D:D,CS!B:B,ATB!I:I)+SUMIF(ATB!D:D,CS!B:B,ATB!K:K) -> 0 | H77: =SUMIF(ATB!D:D,CS!B:B,ATB!L:L) -> 0 | I77: =SUMIF(ATB!D:D,CS!B:B,ATB!M:M) -> 0
B78: Bank guarantee margin | D78: =SUMIF(ATB!D:D,CS!B:B,ATB!F:F) -> 0 | E78: =SUMIF(ATB!D:D,CS!B:B,ATB!G:G) -> 0 | F78: =SUMIF(ATB!D:D,CS!B:B,ATB!H:H)+SUMIF(ATB!D:D,CS!B:B,ATB!J:J) -> 0 | G78: =SUMIF(ATB!D:D,CS!B:B,ATB!I:I)+SUMIF(ATB!D:D,CS!B:B,ATB!K:K) -> 0 | H78: =SUMIF(ATB!D:D,CS!B:B,ATB!L:L) -> 0 | I78: =SUMIF(ATB!D:D,CS!B:B,ATB!M:M) -> 0
B79: Prepaid insurance | D79: =SUMIF(ATB!D:D,CS!B:B,ATB!F:F) -> 0 | E79: =SUMIF(ATB!D:D,CS!B:B,ATB!G:G) -> 0 | F79: =SUMIF(ATB!D:D,CS!B:B,ATB!H:H)+SUMIF(ATB!D:D,CS!B:B,ATB!J:J) -> 0 | G79: =SUMIF(ATB!D:D,CS!B:B,ATB!I:I)+SUMIF(ATB!D:D,CS!B:B,ATB!K:K) -> 0 | H79: =SUMIF(ATB!D:D,CS!B:B,ATB!L:L) -> 0 | I79: =SUMIF(ATB!D:D,CS!B:B,ATB!M:M) -> 0
B80: Prepaid rent | D80: =SUMIF(ATB!D:D,CS!B:B,ATB!F:F) -> 0 | E80: =SUMIF(ATB!D:D,CS!B:B,ATB!G:G) -> 0 | F80: =SUMIF(ATB!D:D,CS!B:B,ATB!H:H)+SUMIF(ATB!D:D,CS!B:B,ATB!J:J) -> 0 | G80: =SUMIF(ATB!D:D,CS!B:B,ATB!I:I)+SUMIF(ATB!D:D,CS!B:B,ATB!K:K) -> 0 | H80: =SUMIF(ATB!D:D,CS!B:B,ATB!L:L) -> 0 | I80: =SUMIF(ATB!D:D,CS!B:B,ATB!M:M) -> 0
D81: =SUMIF(ATB!D:D,CS!B:B,ATB!F:F) -> 0 | E81: =SUMIF(ATB!D:D,CS!B:B,ATB!G:G) -> 0 | F81: =SUMIF(ATB!D:D,CS!B:B,ATB!H:H)+SUMIF(ATB!D:D,CS!B:B,ATB!J:J) -> 0 | G81: =SUMIF(ATB!D:D,CS!B:B,ATB!I:I)+SUMIF(ATB!D:D,CS!B:B,ATB!K:K) -> 0 | H81: =SUMIF(ATB!D:D,CS!B:B,ATB!L:L) -> 0 | I81: =SUMIF(ATB!D:D,CS!B:B,ATB!M:M) -> 0
D82: =SUMIF(ATB!D:D,CS!B:B,ATB!F:F) -> 0 | E82: =SUMIF(ATB!D:D,CS!B:B,ATB!G:G) -> 0 | F82: =SUMIF(ATB!D:D,CS!B:B,ATB!H:H)+SUMIF(ATB!D:D,CS!B:B,ATB!J:J) -> 0 | G82: =SUMIF(ATB!D:D,CS!B:B,ATB!I:I)+SUMIF(ATB!D:D,CS!B:B,ATB!K:K) -> 0 | H82: =SUMIF(ATB!D:D,CS!B:B,ATB!L:L) -> 0 | I82: =SUMIF(ATB!D:D,CS!B:B,ATB!M:M) -> 0
D83: =SUMIF(ATB!D:D,CS!B:B,ATB!F:F) -> 0 | E83: =SUMIF(ATB!D:D,CS!B:B,ATB!G:G) -> 0 | F83: =SUMIF(ATB!D:D,CS!B:B,ATB!H:H)+SUMIF(ATB!D:D,CS!B:B,ATB!J:J) -> 0 | G83: =SUMIF(ATB!D:D,CS!B:B,ATB!I:I)+SUMIF(ATB!D:D,CS!B:B,ATB!K:K) -> 0 | H83: =SUMIF(ATB!D:D,CS!B:B,ATB!L:L) -> 0 | I83: =SUMIF(ATB!D:D,CS!B:B,ATB!M:M) -> 0
B84: Other financial assets - at amortized cost | D84: =SUMIF(ATB!D:D,CS!B:B,ATB!F:F) -> 0 | E84: =SUMIF(ATB!D:D,CS!B:B,ATB!G:G) -> 0 | F84: =SUMIF(ATB!D:D,CS!B:B,ATB!H:H)+SUMIF(ATB!D:D,CS!B:B,ATB!J:J) -> 0 | G84: =SUMIF(ATB!D:D,CS!B:B,ATB!I:I)+SUMIF(ATB!D:D,CS!B:B,ATB!K:K) -> 0 | H84: =SUMIF(ATB!D:D,CS!B:B,ATB!L:L) -> 0 | I84: =SUMIF(ATB!D:D,CS!B:B,ATB!M:M) -> 0
B85: Loans to related parties | D85: =SUMIF(ATB!D:D,CS!B:B,ATB!F:F) -> 0 | E85: =SUMIF(ATB!D:D,CS!B:B,ATB!G:G) -> 0 | F85: =SUMIF(ATB!D:D,CS!B:B,ATB!H:H)+SUMIF(ATB!D:D,CS!B:B,ATB!J:J) -> 0 | G85: =SUMIF(ATB!D:D,CS!B:B,ATB!I:I)+SUMIF(ATB!D:D,CS!B:B,ATB!K:K) -> 0 | H85: =SUMIF(ATB!D:D,CS!B:B,ATB!L:L) -> 0 | I85: =SUMIF(ATB!D:D,CS!B:B,ATB!M:M) -> 0
B86: Loans to key management personnel | D86: =SUMIF(ATB!D:D,CS!B:B,ATB!F:F) -> 0 | E86: =SUMIF(ATB!D:D,CS!B:B,ATB!G:G) -> 0 | F86: =SUMIF(ATB!D:D,CS!B:B,ATB!H:H)+SUMIF(ATB!D:D,CS!B:B,ATB!J:J) -> 0 | G86: =SUMIF(ATB!D:D,CS!B:B,ATB!I:I)+SUMIF(ATB!D:D,CS!B:B,ATB!K:K) -> 0 | H86: =SUMIF(ATB!D:D,CS!B:B,ATB!L:L) -> 0 | I86: =SUMIF(ATB!D:D,CS!B:B,ATB!M:M) -> 0
B87: Other receivables | D87: =SUMIF(ATB!D:D,CS!B:B,ATB!F:F) -> 0 | E87: =SUMIF(ATB!D:D,CS!B:B,ATB!G:G) -> 0 | F87: =SUMIF(ATB!D:D,CS!B:B,ATB!H:H)+SUMIF(ATB!D:D,CS!B:B,ATB!J:J) -> 0 | G87: =SUMIF(ATB!D:D,CS!B:B,ATB!I:I)+SUMIF(ATB!D:D,CS!B:B,ATB!K:K) -> 0 | H87: =SUMIF(ATB!D:D,CS!B:B,ATB!L:L) -> 0 | I87: =SUMIF(ATB!D:D,CS!B:B,ATB!M:M) -> 0
B88: Financial assets at fair value through profit or loss | D88: =SUMIF(ATB!D:D,CS!B:B,ATB!F:F) -> 0 | E88: =SUMIF(ATB!D:D,CS!B:B,ATB!G:G) -> 0 | F88: =SUMIF(ATB!D:D,CS!B:B,ATB!H:H)+SUMIF(ATB!D:D,CS!B:B,ATB!J:J) -> 0 | G88: =SUMIF(ATB!D:D,CS!B:B,ATB!I:I)+SUMIF(ATB!D:D,CS!B:B,ATB!K:K) -> 0 | H88: =SUMIF(ATB!D:D,CS!B:B,ATB!L:L) -> 0 | I88: =SUMIF(ATB!D:D,CS!B:B,ATB!M:M) -> 0
B89: Listed equity securities | D89: =SUMIF(ATB!D:D,CS!B:B,ATB!F:F) -> 0 | E89: =SUMIF(ATB!D:D,CS!B:B,ATB!G:G) -> 0 | F89: =SUMIF(ATB!D:D,CS!B:B,ATB!H:H)+SUMIF(ATB!D:D,CS!B:B,ATB!J:J) -> 0 | G89: =SUMIF(ATB!D:D,CS!B:B,ATB!I:I)+SUMIF(ATB!D:D,CS!B:B,ATB!K:K) -> 0 | H89: =SUMIF(ATB!D:D,CS!B:B,ATB!L:L) -> 0 | I89: =SUMIF(ATB!D:D,CS!B:B,ATB!M:M) -> 0
B90: Unlisted equity securities | D90: =SUMIF(ATB!D:D,CS!B:B,ATB!F:F) -> 0 | E90: =SUMIF(ATB!D:D,CS!B:B,ATB!G:G) -> 0 | F90: =SUMIF(ATB!D:D,CS!B:B,ATB!H:H)+SUMIF(ATB!D:D,CS!B:B,ATB!J:J) -> 0 | G90: =SUMIF(ATB!D:D,CS!B:B,ATB!I:I)+SUMIF(ATB!D:D,CS!B:B,ATB!K:K) -> 0 | H90: =SUMIF(ATB!D:D,CS!B:B,ATB!L:L) -> 0 | I90: =SUMIF(ATB!D:D,CS!B:B,ATB!M:M) -> 0
B91: Total financial assets at fair value through profit or loss | D91: =SUMIF(ATB!D:D,CS!B:B,ATB!F:F) -> 0 | E91: =SUMIF(ATB!D:D,CS!B:B,ATB!G:G) -> 0 | F91: =SUMIF(ATB!D:D,CS!B:B,ATB!H:H)+SUMIF(ATB!D:D,CS!B:B,ATB!J:J) -> 0 | G91: =SUMIF(ATB!D:D,CS!B:B,ATB!I:I)+SUMIF(ATB!D:D,CS!B:B,ATB!K:K) -> 0 | H91: =SUMIF(ATB!D:D,CS!B:B,ATB!L:L) -> 0 | I91: =SUMIF(ATB!D:D,CS!B:B,ATB!M:M) -> 0
D92: =SUMIF(ATB!D:D,CS!B:B,ATB!F:F) -> 0 | E92: =SUMIF(ATB!D:D,CS!B:B,ATB!G:G) -> 0 | F92: =SUMIF(ATB!D:D,CS!B:B,ATB!H:H)+SUMIF(ATB!D:D,CS!B:B,ATB!J:J) -> 0 | G92: =SUMIF(ATB!D:D,CS!B:B,ATB!I:I)+SUMIF(ATB!D:D,CS!B:B,ATB!K:K) -> 0 | H92: =SUMIF(ATB!D:D,CS!B:B,ATB!L:L) -> 0 | I92: =SUMIF(ATB!D:D,CS!B:B,ATB!M:M) -> 0
D93: =SUMIF(ATB!D:D,CS!B:B,ATB!F:F) -> 0 | E93: =SUMIF(ATB!D:D,CS!B:B,ATB!G:G) -> 0 | F93: =SUMIF(ATB!D:D,CS!B:B,ATB!H:H)+SUMIF(ATB!D:D,CS!B:B,ATB!J:J) -> 0 | G93: =SUMIF(ATB!D:D,CS!B:B,ATB!I:I)+SUMIF(ATB!D:D,CS!B:B,ATB!K:K) -> 0 | H93: =SUMIF(ATB!D:D,CS!B:B,ATB!L:L) -> 0 | I93: =SUMIF(ATB!D:D,CS!B:B,ATB!M:M) -> 0
B94: Tax refunds due from government | D94: =SUMIF(ATB!D:D,CS!B:B,ATB!F:F) -> 0 | E94: =SUMIF(ATB!D:D,CS!B:B,ATB!G:G) -> 0 | F94: =SUMIF(ATB!D:D,CS!B:B,ATB!H:H)+SUMIF(ATB!D:D,CS!B:B,ATB!J:J) -> 0 | G94: =SUMIF(ATB!D:D,CS!B:B,ATB!I:I)+SUMIF(ATB!D:D,CS!B:B,ATB!K:K) -> 0 | H94: =SUMIF(ATB!D:D,CS!B:B,ATB!L:L) -> 0 | I94: =SUMIF(ATB!D:D,CS!B:B,ATB!M:M) -> 0
B95: Withheld on cash transactions | D95: =SUMIF(ATB!D:D,CS!B:B,ATB!F:F) -> 0 | E95: =SUMIF(ATB!D:D,CS!B:B,ATB!G:G) -> 0 | F95: =SUMIF(ATB!D:D,CS!B:B,ATB!H:H)+SUMIF(ATB!D:D,CS!B:B,ATB!J:J) -> 0 | G95: =SUMIF(ATB!D:D,CS!B:B,ATB!I:I)+SUMIF(ATB!D:D,CS!B:B,ATB!K:K) -> 0 | H95: =SUMIF(ATB!D:D,CS!B:B,ATB!L:L) -> 0 | I95: =SUMIF(ATB!D:D,CS!B:B,ATB!M:M) -> 0
B96: Withheld on non-cash transactions | D96: =SUMIF(ATB!D:D,CS!B:B,ATB!F:F) -> 0 | E96: =SUMIF(ATB!D:D,CS!B:B,ATB!G:G) -> 0
B97: Withheld by customers | D97: =SUMIF(ATB!D:D,CS!B:B,ATB!F:F) -> 0 | E97: =SUMIF(ATB!D:D,CS!B:B,ATB!G:G) -> 0 | F97: =SUMIF(ATB!D:D,CS!B:B,ATB!H:H)+SUMIF(ATB!D:D,CS!B:B,ATB!J:J) -> 0 | G97: =SUMIF(ATB!D:D,CS!B:B,ATB!I:I)+SUMIF(ATB!D:D,CS!B:B,ATB!K:K) -> 0 | H97: =SUMIF(ATB!D:D,CS!B:B,ATB!L:L) -> 0 | I97: =SUMIF(ATB!D:D,CS!B:B,ATB!M:M) -> 0
B98: Withheld on electricity | D98: =SUMIF(ATB!D:D,CS!B:B,ATB!F:F) -> 0 | E98: =SUMIF(ATB!D:D,CS!B:B,ATB!G:G) -> 0 | F98: =SUMIF(ATB!D:D,CS!B:B,ATB!H:H)+SUMIF(ATB!D:D,CS!B:B,ATB!J:J) -> 0 | G98: =SUMIF(ATB!D:D,CS!B:B,ATB!I:I)+SUMIF(ATB!D:D,CS!B:B,ATB!K:K) -> 0 | H98: =SUMIF(ATB!D:D,CS!B:B,ATB!L:L) -> 0 | I98: =SUMIF(ATB!D:D,CS!B:B,ATB!M:M) -> 0
B99: Cash and cash equivalents (excluding bank overdrafts) | D99: =SUMIF(ATB!D:D,CS!B:B,ATB!F:F) -> 0 | E99: =SUMIF(ATB!D:D,CS!B:B,ATB!G:G) -> 0 | F99: =SUMIF(ATB!D:D,CS!B:B,ATB!H:H)+SUMIF(ATB!D:D,CS!B:B,ATB!J:J) -> 0 | G99: =SUMIF(ATB!D:D,CS!B:B,ATB!I:I)+SUMIF(ATB!D:D,CS!B:B,ATB!K:K) -> 0 | H99: =SUMIF(ATB!D:D,CS!B:B,ATB!L:L) -> 0 | I99: =SUMIF(ATB!D:D,CS!B:B,ATB!M:M) -> 0
B100: Cash in hand | D100: =SUMIF(ATB!D:D,CS!B:B,ATB!F:F) -> 0 | E100: =SUMIF(ATB!D:D,CS!B:B,ATB!G:G) -> 0 | F100: =SUMIF(ATB!D:D,CS!B:B,ATB!H:H)+SUMIF(ATB!D:D,CS!B:B,ATB!J:J) -> 0 | G100: =SUMIF(ATB!D:D,CS!B:B,ATB!I:I)+SUMIF(ATB!D:D,CS!B:B,ATB!K:K) -> 0 | H100: =SUMIF(ATB!D:D,CS!B:B,ATB!L:L) -> 0 | I100: =SUMIF(ATB!D:D,CS!B:B,ATB!M:M) -> 0
B101: Balances with banks in: | D101: =SUMIF(ATB!D:D,CS!B:B,ATB!F:F) -> 0 | E101: =SUMIF(ATB!D:D,CS!B:B,ATB!G:G) -> 0 | F101: =SUMIF(ATB!D:D,CS!B:B,ATB!H:H)+SUMIF(ATB!D:D,CS!B:B,ATB!J:J) -> 0 | G101: =SUMIF(ATB!D:D,CS!B:B,ATB!I:I)+SUMIF(ATB!D:D,CS!B:B,ATB!K:K) -> 0 | H101: =SUMIF(ATB!D:D,CS!B:B,ATB!L:L) -> 0 | I101: =SUMIF(ATB!D:D,CS!B:B,ATB!M:M) -> 0
B102: - current accounts | D102: =SUMIF(ATB!D:D,CS!B:B,ATB!F:F) -> 0 | E102: =SUMIF(ATB!D:D,CS!B:B,ATB!G:G) -> 0 | F102: =SUMIF(ATB!D:D,CS!B:B,ATB!H:H)+SUMIF(ATB!D:D,CS!B:B,ATB!J:J) -> 0 | G102: =SUMIF(ATB!D:D,CS!B:B,ATB!I:I)+SUMIF(ATB!D:D,CS!B:B,ATB!K:K) -> 0 | H102: =SUMIF(ATB!D:D,CS!B:B,ATB!L:L) -> 0 | I102: =SUMIF(ATB!D:D,CS!B:B,ATB!M:M) -> 0
...

Sheet ATB
B1: =Cover!C1 -> ABC LIMITED
B2: ADJUSTED TRAIL BALANCE
B3: =Cover!C3 -> FOR THE YEAR ENDED JUNE 30, 2023
G5: =F6-G6 -> 0 | I5: =H6-I6 -> 0 | K5: =J6-K6 -> 0 | M5: =L6-M6 -> 0
F6: =F1993 -> 0 | G6: =G1993 -> 0 | H6: =H1993 -> 0 | I6: =I1993 -> 0 | J6: =J1993 -> 0 | K6: =K1993 -> 0 | L6: =L1993 -> 0 | M6: =M1993 -> 0
B7: Account Code | C7: Head of Account | D7: Mapping | F7: Opening Balances | H7: Activity during the year | J7: Adjustments | L7: Closing Balances
F8: Debit | G8: Credit | H8: Debit | I8: Credit | J8: Debit | K8: Credit | L8: Debit | M8: Credit
M10: =-ROUND(IF(F10+H10+J10-G10-I10-K10<0,F10+H10+J10-G10-I10-K10,0),0) -> 0
M11: =-ROUND(IF(F11+H11+J11-G11-I11-K11<0,F11+H11+J11-G11-I11-K11,0),0) -> 0
M12: =-ROUND(IF(F12+H12+J12-G12-I12-K12<0,F12+H12+J12-G12-I12-K12,0),0) -> 0
M13: =-ROUND(IF(F13+H13+J13-G13-I13-K13<0,F13+H13+J13-G13-I13-K13,0),0) -> 0
M14: =-ROUND(IF(F14+H14+J14-G14-I14-K14<0,F14+H14+J14-G14-I14-K14,0),0) -> 0
M15: =-ROUND(IF(F15+H15+J15-G15-I15-K15<0,F15+H15+J15-G15-I15-K15,0),0) -> 0
M16: =-ROUND(IF(F16+H16+J16-G16-I16-K16<0,F16+H16+J16-G16-I16-K16,0),0) -> 0
M17: =-ROUND(IF(F17+H17+J17-G17-I17-K17<0,F17+H17+J17-G17-I17-K17,0),0) -> 0
M18: =-ROUND(IF(F18+H18+J18-G18-I18-K18<0,F18+H18+J18-G18-I18-K18,0),0) -> 0
M19: =-ROUND(IF(F19+H19+J19-G19-I19-K19<0,F19+H19+J19-G19-I19-K19,0),0) -> 0
M20: =-ROUND(IF(F20+H20+J20-G20-I20-K20<0,F20+H20+J20-G20-I20-K20,0),0) -> 0
M21: =-ROUND(IF(F21+H21+J21-G21-I21-K21<0,F21+H21+J21-G21-I21-K21,0),0) -> 0
... M97: =-ROUND(IF(F97+H97+J97-G97-I97-K97<0,F97+H97+J97-G97-I97-K97,0),0) -> 0
K98: =SUMIF(AE!C:C,ATB!C:C,AE!F:F) -> 0 | L98: =ROUND(IF(F98+H98+J98-G98-I98-K98>0,F98+H98+J98-G98-I98-K98,0),0) -> 0 | M98: =-ROUND(IF(F98+H98+J98-G98-I98-K98<0,F98+H98+J98-G98-I98-K98,0),0) -> 0
K99: =SUMIF(AE!C:C,ATB!C:C,AE!F:F) -> 0 | L99: =ROUND(IF(F99+H99+J99-G99-I99-K99>0,F99+H99+J99-G99-I99-K99,0),0) -> 0 | M99: =-ROUND(IF(F99+H99+J99-G99-I99-K99<0,F99+H99+J99-G99-I99-K99,0),0) -> 0
K100: =SUMIF(AE!C:C,ATB!C:C,AE!F:F) -> 0 | L100: =ROUND(IF(F100+H100+J100-G100-I100-K100>0,F100+H100+J100-G100-I100-K100,0),0) -> 0 | M100: =-ROUND(IF(F100+H100+J100-G100-I100-K100<0,F100+H100+J100-G100-I100-K100,0),0) -> 0
K101: =SUMIF(AE!C:C,ATB!C:C,AE!F:F) -> 0 | L101: =ROUND(IF(F101+H101+J101-G101-I101-K101>0,F101+H101+J101-G101-I101-K101,0),0) -> 0 | M101: =-ROUND(IF(F101+H101+J101-G101-I101-K101<0,F101+H101+J101-G101-I101-K101,0),0) -> 0
K102: =SUMIF(AE!C:C,ATB!C:C,AE!F:F) -> 0 | L102: =ROUND(IF(F102+H102+J102-G102-I102-K102>0,F102+H102+J102-G102-I102-K102,0),0) -> 0 | M102: =-ROUND(IF(F102+H102+J102-G102-I102-K102<0,F102+H102+J102-G102-I102-K102,0),0) -> 0
K103: =SUMIF(AE!C:C,ATB!C:C,AE!F:F) -> 0 | L103: =ROUND(IF(F103+H103+J103-G103-I103-K103>0,F103+H103+J103-G103-I103-K103,0),0) -> 0 | M103: =-ROUND(IF(F103+H103+J103-G103-I103-K103<0,F103+H103+J103-G103-I103-K103,0),0) -> 0
K104: =SUMIF(AE!C:C,ATB!C:C,AE!F:F) -> 0 | L104: =ROUND(IF(F104+H104+J104-G104-I104-K104>0,F104+H104+J104-G104-I104-K104,0),0) -> 0 | M104: =-ROUND(IF(F104+H104+J104-G104-I104-K104<0,F104+H104+J104-G104-I104-K104,0),0) -> 0
K105: =SUMIF(AE!C:C,ATB!C:C,AE!F:F) -> 0 | L105: =ROUND(IF(F105+H105+J105-G105-I105-K105>0,F105+H105+J105-G105-I105-K105,0),0) -> 0 | M105: =-ROUND(IF(F105+H105+J105-G105-I105-K105<0,F105+H105+J105-G105-I105-K105,0),0) -> 0
K106: =SUMIF(AE!C:C,ATB!C:C,AE!F:F) -> 0 | L106: =ROUND(IF(F106+H106+J106-G106-I106-K106>0,F106+H106+J106-G106-I106-K106,0),0) -> 0 | M106: =-ROUND(IF(F106+H106+J106-G106-I106-K106<0,F106+H106+J106-G106-I106-K106,0),0) -> 0
K107: =SUMIF(AE!C:C,ATB!C:C,AE!F:F) -> 0 | L107: =ROUND(IF(F107+H107+J107-G107-I107-K107>0,F107+H107+J107-G107-I107-K107,0),0) -> 0 | M107: =-ROUND(IF(F107+H107+J107-G107-I107-K107<0,F107+H107+J107-G107-I107-K107,0),0) -> 0
K108: =SUMIF(AE!C:C,ATB!C:C,AE!F:F) -> 0 | L108: =ROUND(IF(F108+H108+J108-G108-I108-K108>0,F108+H108+J108-G108-I108-K108,0),0) -> 0 | M108: =-ROUND(IF(F108+H108+J108-G108-I108-K108<0,F108+H108+J108-G108-I108-K108,0),0) -> 0
K109: =SUMIF(AE!C:C,ATB!C:C,AE!F:F) -> 0 | L109: =ROUND(IF(F109+H109+J109-G109-I109-K109>0,F109+H109+J109-G109-I109-K109,0),0) -> 0 | M109: =-ROUND(IF(F109+H109+J109-G109-I109-K109<0,F109+H109+J109-G109-I109-K109,0),0) -> 0
... K1991: =SUMIF(AE!C:C,ATB!C:C,AE!F:F) -> 0 | L1991: =ROUND(IF(F1991+H1991+J1991-G1991-I1991-K1991>0,F1991+H1991+J1991-G1991-I1991-K1991,0),0) -> 0 | M1991: =-ROUND(IF(F1991+H1991+J1991-G1991-I1991-K1991<0,F1991+H1991+J1991-G1991-I1991-K1991,0),0) -> 0
F1993: =SUM(F9:F1992) -> 0 | G1993: =SUM(G9:G1992) -> 0 | H1993: =SUM(H9:H1992) -> 0 | I1993: =SUM(I9:I1992) -> 0 | J1993: =SUM(J9:J1992) -> 0 | K1993: =SUM(K9:K1992) -> 0 | L1993: =SUM(L9:L1992) -> 0 | M1993: =SUM(M9:M1992) -> 0
G1994: =F1993-G1993 -> 0 | I1994: =H1993-I1993 -> 0 | K1994: =J1993-K1993 -> 0 | M1994: =L1993-M1993 -> 0

Sheet AE
A1: =Cover!C1 -> ABC LIMITED
A2: ADJUSTING ENTRIES
A3: =Cover!C3 -> FOR THE YEAR ENDED JUNE 30, 2023
A5: Sr. # | B5: Account Code | C5: Head of Account / Description | E5: Amount
E6: Debit | F6: Credit
E2000: =SUM(E7:E1999) -> 0 | F2000: =SUM(F7:F1999) -> 0

Sheet AD
B1: =Cover!C1 -> ABC LIMITED
B2: ACCOUNTING DEPRECIATION & DISPOSALS WORKING
B3: =Cover!C3 -> FOR THE YEAR ENDED JUNE 30, 2023
B5: Depreciation Working
B7: Asset Type | C7: Description | D7: Date | E7: Opening WDV | F7: Additions | G7: Total Assets | H7: Number of Month in use | I7: Depreciation Rate | J7: Depreciation Charge | K7: Total Depreciation | L7: Closing WDV
B10: =FAS!H15 -> Freehold Land | C10: Opening Balance | D10: =Cover!$I$6 -> 44743 | E10: =FAS!H64 -> 0 | G10: =E10+F10 -> 0 | H10: =IF(YEAR(D10)=2022,19-MONTH(D10),IF(YEAR(D10)=2023,7-MONTH(D10),IF(D10="","","Date Error"))) -> 12 | I10: =FAS!H62 -> 0 | J10: =IF(G10=0,0,-G10*H10*I10/12) -> 0
G11: =E11+F11 -> 0 | H11: =IF(YEAR(D11)=2022,19-MONTH(D11),IF(YEAR(D11)=2023,7-MONTH(D11),IF(D11="","","Date Error"))) | I11: =IF(H11="","",I10) | J11: =IF(G11=0,0,-G11*H11*I11/12) -> 0
G12: =E12+F12 -> 0 | H12: =IF(YEAR(D12)=2022,19-MONTH(D12),IF(YEAR(D12)=2023,7-MONTH(D12),IF(D12="","","Date Error"))) | I12: =IF(H12="","",I11) | J12: =IF(G12=0,0,-G12*H12*I12/12) -> 0
B13: Disposal | G13: =-O69 -> 0 | J13: =R69 -> 0
K14: =ROUND(SUM(J10:J14),0) -> 0 | L14: =SUM(G10:G14)+K14 -> 0
B15: =FAS!J15 -> Building on Freehold Land | C15: Opening Balance | D15: =Cover!$I$6 -> 44743 | E15: =FAS!J64 -> 0 | G15: =E15+F15 -> 0 | H15: =IF(YEAR(D15)=2022,19-MONTH(D15),IF(YEAR(D15)=2023,7-MONTH(D15),IF(D15="","","Date Error"))) -> 12 | I15: =FAS!J62 -> 0 | J15: =IF(G15=0,0,-G15*H15*I15/12) -> 0
G16: =E16+F16 -> 0 | H16: =IF(YEAR(D16)=2022,19-MONTH(D16),IF(YEAR(D16)=2023,7-MONTH(D16),IF(D16="","","Date Error"))) | I16: =IF(H16="","",I15) | J16: =IF(G16=0,0,-G16*H16*I16/12) -> 0
G17: =E17+F17 -> 0 | H17: =IF(YEAR(D17)=2022,19-MONTH(D17),IF(YEAR(D17)=2023,7-MONTH(D17),IF(D17="","","Date Error"))) | J17: =IF(G17=0,0,-G17*H17*I17/12) -> 0
B18: Disposal | G18: =-O73 -> 0 | J18: =R73 -> 0
K19: =ROUND(SUM(J15:J19),0) -> 0 | L19: =SUM(G15:G19)+K19 -> 0
B20: =FAS!L15 -> Plant and Machinery | C20: Opening Balance | D20: =Cover!$I$6 -> 44743 | E20: =FAS!L64 -> 0 | G20: =E20+F20 -> 0 | H20: =IF(YEAR(D20)=2022,19-MONTH(D20),IF(YEAR(D20)=2023,7-MONTH(D20),IF(D20="","","Date Error"))) -> 12 | I20: =FAS!L62 -> 0 | J20: =IF(G20=0,0,-G20*H20*I20/12) -> 0
G21: =E21+F21 -> 0 | H21: =IF(YEAR(D21)=2022,19-MONTH(D21),IF(YEAR(D21)=2023,7-MONTH(D21),IF(D21="","","Date Error"))) | I21: =IF(H21="","",I20) | J21: =IF(G21=0,0,-G21*H21*I21/12) -> 0
G22: =E22+F22 -> 0 | H22: =IF(YEAR(D22)=2022,19-MONTH(D22),IF(YEAR(D22)=2023,7-MONTH(D22),IF(D22="","","Date Error"))) | I22: =IF(H22="","",I21) | J22: =IF(G22=0,0,-G22*H22*I22/12) -> 0
B23: Disposal | G23: =-O77 -> 0 | J23: =R77 -> 0
K24: =ROUND(SUM(J20:J24),0) -> 0 | L24: =SUM(G20:G24)+K24 -> 0
B25: =FAS!N15 -> Generator | C25: Opening Balance | D25: =Cover!$I$6 -> 44743 | E25: =FAS!N64 -> 0 | G25: =E25+F25 -> 0 | H25: =IF(YEAR(D25)=2022,19-MONTH(D25),IF(YEAR(D25)=2023,7-MONTH(D25),IF(D25="","","Date Error"))) -> 12 | I25: =FAS!N62 -> 0 | J25: =IF(G25=0,0,-G25*H25*I25/12) -> 0
G26: =E26+F26 -> 0 | H26: =IF(YEAR(D26)=2022,19-MONTH(D26),IF(YEAR(D26)=2023,7-MONTH(D26),IF(D26="","","Date Error"))) | I26: =IF(H26="","",I25) | J26: =IF(G26=0,0,-G26*H26*I26/12) -> 0
G27: =E27+F27 -> 0 | H27: =IF(YEAR(D27)=2022,19-MONTH(D27),IF(YEAR(D27)=2023,7-MONTH(D27),IF(D27="","","Date Error"))) | I27: =IF(H27="","",I26) | J27: =IF(G27=0,0,-G27*H27*I27/12) -> 0
B28: Disposal | G28: =-O81 -> 0 | J28: =R81 -> 0
K29: =ROUND(SUM(J25:J29),0) -> 0 | L29: =SUM(G25:G29)+K29 -> 0
B30: =FAS!P15 -> Office Equipment | C30: Opening Balance | D30: =Cover!$I$6 -> 44743 | E30: =FAS!P64 -> 0 | G30: =E30+F30 -> 0 | H30: =IF(YEAR(D30)=2022,19-MONTH(D30),IF(YEAR(D30)=2023,7-MONTH(D30),IF(D30="","","Date Error"))) -> 12 | I30: =FAS!P62 -> 0 | J30: =IF(G30=0,0,-G30*H30*I30/12) -> 0
G31: =E31+F31 -> 0 | H31: =IF(YEAR(D31)=2022,19-MONTH(D31),IF(YEAR(D31)=2023,7-MONTH(D31),IF(D31="","","Date Error"))) | I31: =IF(H31="","",I30) | J31: =IF(G31=0,0,-G31*H31*I31/12) -> 0
G32: =E32+F32 -> 0 | H32: =IF(YEAR(D32)=2022,19-MONTH(D32),IF(YEAR(D32)=2023,7-MONTH(D32),IF(D32="","","Date Error"))) | I32: =IF(H32="","",I31) | J32: =IF(G32=0,0,-G32*H32*I32/12) -> 0
B33: Disposal | G33: =-O85 -> 0 | J33: =R85 -> 0
K34: =ROUND(SUM(J30:J34),0) -> 0 | L34: =SUM(G30:G34)+K34 -> 0
B35: =FAS!R15 -> Computers | C35: Opening Balance | D35: =Cover!$I$6 -> 44743 | E35: =FAS!R64 -> 0 | G35: =E35+F35 -> 0 | H35: =IF(YEAR(D35)=2022,19-MONTH(D35),IF(YEAR(D35)=2023,7-MONTH(D35),IF(D35="","","Date Error"))) -> 12 | I35: =FAS!R62 -> 0 | J35: =IF(G35=0,0,-G35*H35*I35/12) -> 0
G36: =E36+F36 -> 0 | H36: =IF(YEAR(D36)=2022,19-MONTH(D36),IF(YEAR(D36)=2023,7-MONTH(D36),IF(D36="","","Date Error"))) | I36: =IF(H36="","",I35) | J36: =IF(G36=0,0,-G36*H36*I36/12) -> 0
G37: =E37+F37 -> 0 | H37: =IF(YEAR(D37)=2022,19-MONTH(D37),IF(YEAR(D37)=2023,7-MONTH(D37),IF(D37="","","Date Error"))) | I37: =IF(H37="","",I36) | J37: =IF(G37=0,0,-G37*H37*I37/12) -> 0
B38: Disposal | G38: =-O89 -> 0 | J38: =R89 -> 0
K39: =ROUND(SUM(J35:J39),0) -> 0 | L39: =SUM(G35:G39)+K39 -> 0
B40: =FAS!T15 -> Electric Equipment & Installations | C40: Opening Balance | D40: =Cover!$I$6 -> 44743 | E40: =FAS!T64 -> 0 | G40: =E40+F40 -> 0 | H40: =IF(YEAR(D40)=2022,19-MONTH(D40),IF(YEAR(D40)=2023,7-MONTH(D40),IF(D40="","","Date Error"))) -> 12 | I40: =FAS!T62 -> 0 | J40: =IF(G40=0,0,-G40*H40*I40/12) -> 0
G41: =E41+F41 -> 0 | H41: =IF(YEAR(D41)=2022,19-MONTH(D41),IF(YEAR(D41)=2023,7-MONTH(D41),IF(D41="","","Date Error"))) | I41: =IF(H41="","",I40) | J41: =IF(G41=0,0,-G41*H41*I41/12) -> 0
G42: =E42+F42 -> 0 | H42: =IF(YEAR(D42)=2022,19-MONTH(D42),IF(YEAR(D42)=2023,7-MONTH(D42),IF(D42="","","Date Error"))) | I42: =IF(H42="","",I41) | J42: =IF(G42=0,0,-G42*H42*I42/12) -> 0
B43: Disposal | G43: =-O93 -> 0 | J43: =R93 -> 0
K44: =ROUND(SUM(J40:J44),0) -> 0 | L44: =SUM(G40:G44)+K44 -> 0
B45: =FAS!V15 -> Furniture and Fixture | C45: Opening Balance | D45: =Cover!$I$6 -> 44743 | E45: =FAS!V64 -> 0 | G45: =E45+F45 -> 0 | H45: =IF(YEAR(D45)=2022,19-MONTH(D45),IF(YEAR(D45)=2023,7-MONTH(D45),IF(D45="","","Date Error"))) -> 12 | I45: =FAS!V62 -> 0 | J45: =IF(G45=0,0,-G45*H45*I45/12) -> 0
G46: =E46+F46 -> 0 | H46: =IF(YEAR(D46)=2022,19-MONTH(D46),IF(YEAR(D46)=2023,7-MONTH(D46),IF(D46="","","Date Error"))) | I46: =IF(H46="","",I45) | J46: =IF(G46=0,0,-G46*H46*I46/12) -> 0
G47: =E47+F47 -> 0 | H47: =IF(YEAR(D47)=2022,19-MONTH(D47),IF(YEAR(D47)=2023,7-MONTH(D47),IF(D47="","","Date Error"))) | I47: =IF(H47="","",I46) | J47: =IF(G47=0,0,-G47*H47*I47/12) -> 0
B48: Disposal | G48: =-O97 -> 0 | J48: =R97 -> 0
K49: =ROUND(SUM(J45:J49),0) -> 0 | L49: =SUM(G45:G49)+K49 -> 0
B50: =FAS!X15 -> Vehicles | C50: Opening Balance | D50: =Cover!$I$6 -> 44743 | E50: =FAS!X64 -> 0 | G50: =E50+F50 -> 0 | H50: =IF(YEAR(D50)=2022,19-MONTH(D50),IF(YEAR(D50)=2023,7-MONTH(D50),IF(D50="","","Date Error"))) -> 12 | I50: =FAS!X62 -> 0 | J50: =IF(G50=0,0,-G50*H50*I50/12) -> 0
G51: =E51+F51 -> 0 | H51: =IF(YEAR(D51)=2022,19-MONTH(D51),IF(YEAR(D51)=2023,7-MONTH(D51),IF(D51="","","Date Error"))) | I51: =IF(H51="","",I50) | J51: =IF(G51=0,0,-G51*H51*I51/12) -> 0
G52: =E52+F52 -> 0 | H52: =IF(YEAR(D52)=2022,19-MONTH(D52),IF(YEAR(D52)=2023,7-MONTH(D52),IF(D52="","","Date Error"))) | I52: =IF(H52="","",I51) | J52: =IF(G52=0,0,-G52*H52*I52/12) -> 0
B53: Disposal | G53: =-O101 -> 0 | J53: =R101 -> 0
K54: =ROUND(SUM(J50:J54),0) -> 0 | L54: =SUM(G50:G54)+K54 -> 0
C59: Total | E59: =SUM(E10:E58) -> 0 | F59: =SUM(F10:F58) -> 0 | G59: =SUM(G10:G58) -> 0 | J59: =SUM(J10:J58) -> 0 | K59: =SUM(K10:K58) -> 0 | L59: =SUM(L10:L58) -> 0
B62: Disposals Working
B64: Asset Type | C64: Description | D64: Date of Acquisition | E64: Date of Disposal | F64: Number of Years in use (Previous Years) | G64: Number of months (other than years in previous column) in use (Previous Years) | H64: Number of months in use (Current Years) | I64: Cost | J64: Depreciation Rate | K64: Opening Net Book Value | L64: Opening Accumulated Depreciation | M64: Depreciation Charge for the year | N64: Accumulated depreciation at date of disposal | O64: Closing Net Book Value | P64: Sales Proceeds | Q64: Gain / (Loss) on Disposals | R64: Depreciation to added back in above depreciation
B66: =B10 -> Freehold Land | D66: 42644 | E66: 44743 | F66: =DATEDIF(D66,Cover!$J$7,"y") -> 5 | G66: =DATEDIF(D66,Cover!$J$7,"ym")+1 -> 9 | H66: =DATEDIF(Cover!$I$6,E66,"m")+1 -> 1 | J66: =I10 -> 0 | K66: =(I66-(I66*J66*G66/12))*(1-J66)^F66 -> 0 | L66: =I66-K66 -> 0 | M66: =K66*J66*H66/12 -> 0 | N66: =L66+M66 -> 0 | O66: =K66-M66 -> 0 | Q66: =P66-O66 -> 0 | R66: =K66*J66*(12-H66)/12 -> 0
D67: 42644 | E67: 44743 | F67: =DATEDIF(D67,Cover!$J$7,"y") -> 5 | G67: =DATEDIF(D67,Cover!$J$7,"ym")+1 -> 9 | H67: =DATEDIF(Cover!$I$6,E67,"m")+1 -> 1 | J67: =J66 -> 0 | K67: =(I67-(I67*J67*G67/12))*(1-J67)^F67 -> 0 | L67: =I67-K67 -> 0 | M67: =K67*J67*H67/12 -> 0 | N67: =L67+M67 -> 0 | O67: =K67-M67 -> 0 | Q67: =P67-O67 -> 0 | R67: =K67*J67*(12-H67)/12 -> 0
D68: 42644 | E68: 44743 | F68: =DATEDIF(D68,Cover!$J$7,"y") -> 5 | G68: =DATEDIF(D68,Cover!$J$7,"ym")+1 -> 9 | H68: =DATEDIF(Cover!$I$6,E68,"m")+1 -> 1 | J68: =J67 -> 0 | K68: =(I68-(I68*J68*G68/12))*(1-J68)^F68 -> 0 | L68: =I68-K68 -> 0 | M68: =K68*J68*H68/12 -> 0 | N68: =L68+M68 -> 0 | O68: =K68-M68 -> 0 | Q68: =P68-O68 -> 0 | R68: =K68*J68*(12-H68)/12 -> 0
K69: =SUM(K66:K68) -> 0 | L69: =SUM(L66:L68) -> 0 | M69: =SUM(M66:M68) -> 0 | N69: =SUM(N66:N68) -> 0 | O69: =SUM(O66:O68) -> 0 | P69: =SUM(P66:P68) -> 0 | Q69: =SUM(Q66:Q68) -> 0 | R69: =SUM(R66:R68) -> 0
B70: =B15 -> Building on Freehold Land | D70: 42644 | E70: 44743 | F70: =DATEDIF(D70,Cover!$J$7,"y") -> 5 | G70: =DATEDIF(D70,Cover!$J$7,"ym")+1 -> 9 | H70: =DATEDIF(Cover!$I$6,E70,"m")+1 -> 1 | J70: =I15 -> 0 | K70: =(I70-(I70*J70*G70/12))*(1-J70)^F70 -> 0 | L70: =I70-K70 -> 0 | M70: =K70*J70*H70/12 -> 0 | N70: =L70+M70 -> 0 | O70: =K70-M70 -> 0 | Q70: =P70-O70 -> 0 | R70: =K70*J70*(12-H70)/12 -> 0
D71: 42644 | E71: 44743 | F71: =DATEDIF(D71,Cover!$J$7,"y") -> 5 | G71: =DATEDIF(D71,Cover!$J$7,"ym")+1 -> 9 | H71: =DATEDIF(Cover!$I$6,E71,"m")+1 -> 1 | J71: =J70 -> 0 | K71: =(I71-(I71*J71*G71/12))*(1-J71)^F71 -> 0 | L71: =I71-K71 -> 0 | M71: =K71*J71*H71/12 -> 0 | N71: =L71+M71 -> 0 | O71: =K71-M71 -> 0 | Q71: =P71-O71 -> 0 | R71: =K71*J71*(12-H71)/12 -> 0
D72: 42644 | E72: 44743 | F72: =DATEDIF(D72,Cover!$J$7,"y") -> 5 | G72: =DATEDIF(D72,Cover!$J$7,"ym")+1 -> 9 | H72: =DATEDIF(Cover!$I$6,E72,"m")+1 -> 1 | J72: =J71 -> 0 | K72: =(I72-(I72*J72*G72/12))*(1-J72)^F72 -> 0 | L72: =I72-K72 -> 0 | M72: =K72*J72*H72/12 -> 0 | N72: =L72+M72 -> 0 | O72: =K72-M72 -> 0 | Q72: =P72-O72 -> 0 | R72: =K72*J72*(12-H72)/12 -> 0
K73: =SUM(K70:K72) -> 0 | L73: =SUM(L70:L72) -> 0 | M73: =SUM(M70:M72) -> 0 | N73: =SUM(N70:N72) -> 0 | O73: =SUM(O70:O72) -> 0 | P73: =SUM(P70:P72) -> 0 | Q73: =SUM(Q70:Q72) -> 0 | R73: =SUM(R70:R72) -> 0
B74: =B20 -> Plant and Machinery | C74: plant | D74: 43009 | E74: 44743 | F74: =DATEDIF(D74,Cover!$J$7,"y") -> 4 | G74: =DATEDIF(D74,Cover!$J$7,"ym")+1 -> 9 | H74: =DATEDIF(Cover!$I$6,E74,"m")+1 -> 1 | I74: =-FAS!L36 -> 0 | J74: =I20 -> 0 | K74: =(I74-(I74*J74*G74/12))*(1-J74)^F74 -> 0 | L74: =I74-K74 -> 0 | M74: =K74*J74*H74/12 -> 0 | N74: =L74+M74 -> 0 | O74: =K74-M74 -> 0 | Q74: =P74-O74 -> 0 | R74: =K74*J74*(12-H74)/12 -> 0
D75: 42644 | E75: 44743 | F75: =DATEDIF(D75,Cover!$J$7,"y") -> 5 | G75: =DATEDIF(D75,Cover!$J$7,"ym")+1 -> 9 | H75: =DATEDIF(Cover!$I$6,E75,"m")+1 -> 1 | J75: =J74 -> 0 | K75: =(I75-(I75*J75*G75/12))*(1-J75)^F75 -> 0 | L75: =I75-K75 -> 0 | M75: =K75*J75*H75/12 -> 0 | N75: =L75+M75 -> 0 | O75: =K75-M75 -> 0 | Q75: =P75-O75 -> 0 | R75: =K75*J75*(12-H75)/12 -> 0
D76: 42644 | E76: 44743 | F76: =DATEDIF(D76,Cover!$J$7,"y") -> 5 | G76: =DATEDIF(D76,Cover!$J$7,"ym")+1 -> 9 | H76: =DATEDIF(Cover!$I$6,E76,"m")+1 -> 1 | J76: =J75 -> 0 | K76: =(I76-(I76*J76*G76/12))*(1-J76)^F76 -> 0 | L76: =I76-K76 -> 0 | M76: =K76*J76*H76/12 -> 0 | N76: =L76+M76 -> 0 | O76: =K76-M76 -> 0 | Q76: =P76-O76 -> 0 | R76: =K76*J76*(12-H76)/12 -> 0
K77: =SUM(K74:K76) -> 0 | L77: =SUM(L74:L76) -> 0 | M77: =SUM(M74:M76) -> 0 | N77: =SUM(N74:N76) -> 0 | O77: =SUM(O74:O76) -> 0 | P77: =SUM(P74:P76) -> 0 | Q77: =SUM(Q74:Q76) -> 0 | R77: =SUM(R74:R76) -> 0
B78: =B25 -> Generator | D78: 42644 | E78: 44743 | F78: =DATEDIF(D78,Cover!$J$7,"y") -> 5 | G78: =DATEDIF(D78,Cover!$J$7,"ym")+1 -> 9 | H78: =DATEDIF(Cover!$I$6,E78,"m")+1 -> 1 | J78: =I25 -> 0 | K78: =(I78-(I78*J78*G78/12))*(1-J78)^F78 -> 0 | L78: =I78-K78 -> 0 | M78: =K78*J78*H78/12 -> 0 | N78: =L78+M78 -> 0 | O78: =K78-M78 -> 0 | Q78: =P78-O78 -> 0 | R78: =K78*J78*(12-H78)/12 -> 0
D79: 42644 | E79: 44743 | F79: =DATEDIF(D79,Cover!$J$7,"y") -> 5 | G79: =DATEDIF(D79,Cover!$J$7,"ym")+1 -> 9 | H79: =DATEDIF(Cover!$I$6,E79,"m")+1 -> 1 | J79: =J78 -> 0 | K79: =(I79-(I79*J79*G79/12))*(1-J79)^F79 -> 0 | L79: =I79-K79 -> 0 | M79: =K79*J79*H79/12 -> 0 | N79: =L79+M79 -> 0 | O79: =K79-M79 -> 0 | Q79: =P79-O79 -> 0 | R79: =K79*J79*(12-H79)/12 -> 0
D80: 42644 | E80: 44743 | F80: =DATEDIF(D80,Cover!$J$7,"y") -> 5 | G80: =DATEDIF(D80,Cover!$J$7,"ym")+1 -> 9 | H80: =DATEDIF(Cover!$I$6,E80,"m")+1 -> 1 | J80: =J79 -> 0 | K80: =(I80-(I80*J80*G80/12))*(1-J80)^F80 -> 0 | L80: =I80-K80 -> 0 | M80: =K80*J80*H80/12 -> 0 | N80: =L80+M80 -> 0 | O80: =K80-M80 -> 0 | Q80: =P80-O80 -> 0 | R80: =K80*J80*(12-H80)/12 -> 0
K81: =SUM(K78:K80) -> 0 | L81: =SUM(L78:L80) -> 0 | M81: =SUM(M78:M80) -> 0 | N81: =SUM(N78:N80) -> 0 | O81: =SUM(O78:O80) -> 0 | P81: =SUM(P78:P80) -> 0 | Q81: =SUM(Q78:Q80) -> 0 | R81: =SUM(R78:R80) -> 0
B82: =B30 -> Office Equipment | D82: 42644 | E82: 44743 | F82: =DATEDIF(D82,Cover!$J$7,"y") -> 5 | G82: =DATEDIF(D82,Cover!$J$7,"ym")+1 -> 9 | H82: =DATEDIF(Cover!$I$6,E82,"m")+1 -> 1 | J82: =I30 -> 0 | K82: =(I82-(I82*J82*G82/12))*(1-J82)^F82 -> 0 | L82: =I82-K82 -> 0 | M82: =K82*J82*H82/12 -> 0 | N82: =L82+M82 -> 0 | O82: =K82-M82 -> 0 | Q82: =P82-O82 -> 0 | R82: =K82*J82*(12-H82)/12 -> 0
D83: 42644 | E83: 44743 | F83: =DATEDIF(D83,Cover!$J$7,"y") -> 5 | G83: =DATEDIF(D83,Cover!$J$7,"ym")+1 -> 9 | H83: =DATEDIF(Cover!$I$6,E83,"m")+1 -> 1 | J83: =J82 -> 0 | K83: =(I83-(I83*J83*G83/12))*(1-J83)^F83 -> 0 | L83: =I83-K83 -> 0 | M83: =K83*J83*H83/12 -> 0 | N83: =L83+M83 -> 0 | O83: =K83-M83 -> 0 | Q83: =P83-O83 -> 0 | R83: =K83*J83*(12-H83)/12 -> 0
D84: 42644 | E84: 44743 | F84: =DATEDIF(D84,Cover!$J$7,"y") -> 5 | G84: =DATEDIF(D84,Cover!$J$7,"ym")+1 -> 9 | H84: =DATEDIF(Cover!$I$6,E84,"m")+1 -> 1 | J84: =J83 -> 0 | K84: =(I84-(I84*J84*G84/12))*(1-J84)^F84 -> 0 | L84: =I84-K84 -> 0 | M84: =K84*J84*H84/12 -> 0 | N84: =L84+M84 -> 0 | O84: =K84-M84 -> 0 | Q84: =P84-O84 -> 0 | R84: =K84*J84*(12-H84)/12 -> 0
K85: =SUM(K82:K84) -> 0 | L85: =SUM(L82:L84) -> 0 | M85: =SUM(M82:M84) -> 0 | N85: =SUM(N82:N84) -> 0 | O85: =SUM(O82:O84) -> 0 | P85: =SUM(P82:P84) -> 0 | Q85: =SUM(Q82:Q84) -> 0 | R85: =SUM(R82:R84) -> 0
B86: =B35 -> Computers | D86: 42644 | E86: 44743 | F86: =DATEDIF(D86,Cover!$J$7,"y") -> 5 | G86: =DATEDIF(D86,Cover!$J$7,"ym")+1 -> 9 | H86: =DATEDIF(Cover!$I$6,E86,"m")+1 -> 1 | J86: =I35 -> 0 | K86: =(I86-(I86*J86*G86/12))*(1-J86)^F86 -> 0 | L86: =I86-K86 -> 0 | M86: =K86*J86*H86/12 -> 0 | N86: =L86+M86 -> 0 | O86: =K86-M86 -> 0 | Q86: =P86-O86 -> 0 | R86: =K86*J86*(12-H86)/12 -> 0
D87: 42644 | E87: 44743 | F87: =DATEDIF(D87,Cover!$J$7,"y") -> 5 | G87: =DATEDIF(D87,Cover!$J$7,"ym")+1 -> 9 | H87: =DATEDIF(Cover!$I$6,E87,"m")+1 -> 1 | J87: =J86 -> 0 | K87: =(I87-(I87*J87*G87/12))*(1-J87)^F87 -> 0 | L87: =I87-K87 -> 0 | M87: =K87*J87*H87/12 -> 0 | N87: =L87+M87 -> 0 | O87: =K87-M87 -> 0 | Q87: =P87-O87 -> 0 | R87: =K87*J87*(12-H87)/12 -> 0
D88: 42644 | E88: 44743 | F88: =DATEDIF(D88,Cover!$J$7,"y") -> 5 | G88: =DATEDIF(D88,Cover!$J$7,"ym")+1 -> 9 | H88: =DATEDIF(Cover!$I$6,E88,"m")+1 -> 1 | J88: =J87 -> 0 | K88: =(I88-(I88*J88*G88/12))*(1-J88)^F88 -> 0 | L88: =I88-K88 -> 0 | M88: =K88*J88*H88/12 -> 0 | N88: =L88+M88 -> 0 | O88: =K88-M88 -> 0 | Q88: =P88-O88 -> 0 | R88: =K88*J88*(12-H88)/12 -> 0
K89: =SUM(K86:K88) -> 0 | L89: =SUM(L86:L88) -> 0 | M89: =SUM(M86:M88) -> 0 | N89: =SUM(N86:N88) -> 0 | O89: =SUM(O86:O88) -> 0 | P89: =SUM(P86:P88) -> 0 | Q89: =SUM(Q86:Q88) -> 0 | R89: =SUM(R86:R88) -> 0
B90: =B40 -> Electric Equipment & Installations | D90: 42644 | E90: 44743 | F90: =DATEDIF(D90,Cover!$J$7,"y") -> 5 | G90: =DATEDIF(D90,Cover!$J$7,"ym")+1 -> 9 | H90: =DATEDIF(Cover!$I$6,E90,"m")+1 -> 1 | J90: =I40 -> 0 | K90: =(I90-(I90*J90*G90/12))*(1-J90)^F90 -> 0 | L90: =I90-K90 -> 0 | M90: =K90*J90*H90/12 -> 0 | N90: =L90+M90 -> 0 | O90: =K90-M90 -> 0 | Q90: =P90-O90 -> 0 | R90: =K90*J90*(12-H90)/12 -> 0
D91: 42644 | E91: 44743 | F91: =DATEDIF(D91,Cover!$J$7,"y") -> 5 | G91: =DATEDIF(D91,Cover!$J$7,"ym")+1 -> 9 | H91: =DATEDIF(Cover!$I$6,E91,"m")+1 -> 1 | J91: =J90 -> 0 | K91: =(I91-(I91*J91*G91/12))*(1-J91)^F91 -> 0 | L91: =I91-K91 -> 0 | M91: =K91*J91*H91/12 -> 0 | N91: =L91+M91 -> 0 | O91: =K91-M91 -> 0 | Q91: =P91-O91 -> 0 | R91: =K91*J91*(12-H91)/12 -> 0
D92: 42644 | E92: 44743 | F92: =DATEDIF(D92,Cover!$J$7,"y") -> 5 | G92: =DATEDIF(D92,Cover!$J$7,"ym")+1 -> 9 | H92: =DATEDIF(Cover!$I$6,E92,"m")+1 -> 1 | J92: =J91 -> 0 | K92: =(I92-(I92*J92*G92/12))*(1-J92)^F92 -> 0 | L92: =I92-K92 -> 0 | M92: =K92*J92*H92/12 -> 0 | N92: =L92+M92 -> 0 | O92: =K92-M92 -> 0 | Q92: =P92-O92 -> 0 | R92: =K92*J92*(12-H92)/12 -> 0
K93: =SUM(K90:K92) -> 0 | L93: =SUM(L90:L92) -> 0 | M93: =SUM(M90:M92) -> 0 | N93: =SUM(N90:N92) -> 0 | O93: =SUM(O90:O92) -> 0 | P93: =SUM(P90:P92) -> 0 | Q93: =SUM(Q90:Q92) -> 0 | R93: =SUM(R90:R92) -> 0
B94: =B45 -> Furniture and Fixture | D94: 42644 | E94: 44743 | F94: =DATEDIF(D94,Cover!$J$7,"y") -> 5 | G94: =DATEDIF(D94,Cover!$J$7,"ym")+1 -> 9 | H94: =DATEDIF(Cover!$I$6,E94,"m")+1 -> 1 | J94: =I45 -> 0 | K94: =(I94-(I94*J94*G94/12))*(1-J94)^F94 -> 0 | L94: =I94-K94 -> 0 | M94: =K94*J94*H94/12 -> 0 | N94: =L94+M94 -> 0 | O94: =K94-M94 -> 0 | Q94: =P94-O94 -> 0 | R94: =K94*J94*(12-H94)/12 -> 0
D95: 42644 | E95: 44743 | F95: =DATEDIF(D95,Cover!$J$7,"y") -> 5 | G95: =DATEDIF(D95,Cover!$J$7,"ym")+1 -> 9 | H95: =DATEDIF(Cover!$I$6,E95,"m")+1 -> 1 | J95: =J94 -> 0 | K95: =(I95-(I95*J95*G95/12))*(1-J95)^F95 -> 0 | L95: =I95-K95 -> 0 | M95: =K95*J95*H95/12 -> 0 | N95: =L95+M95 -> 0 | O95: =K95-M95 -> 0 | Q95: =P95-O95 -> 0 | R95: =K95*J95*(12-H95)/12 -> 0
D96: 42644 | E96: 44743 | F96: =DATEDIF(D96,Cover!$J$7,"y") -> 5 | G96: =DATEDIF(D96,Cover!$J$7,"ym")+1 -> 9 | H96: =DATEDIF(Cover!$I$6,E96,"m")+1 -> 1 | J96: =J95 -> 0 | K96: =(I96-(I96*J96*G96/12))*(1-J96)^F96 -> 0 | L96: =I96-K96 -> 0 | M96: =K96*J96*H96/12 -> 0 | N96: =L96+M96 -> 0 | O96: =K96-M96 -> 0 | Q96: =P96-O96 -> 0 | R96: =K96*J96*(12-H96)/12 -> 0
K97: =SUM(K94:K96) -> 0 | L97: =SUM(L94:L96) -> 0 | M97: =SUM(M94:M96) -> 0 | N97: =SUM(N94:N96) -> 0 | O97: =SUM(O94:O96) -> 0 | P97: =SUM(P94:P96) -> 0 | Q97: =SUM(Q94:Q96) -> 0 | R97: =SUM(R94:R96) -> 0
B98: =B50 -> Vehicles | D98: 42644 | E98: 44743 | F98: =DATEDIF(D98,Cover!$J$7,"y") -> 5 | G98: =DATEDIF(D98,Cover!$J$7,"ym")+1 -> 9 | H98: =DATEDIF(Cover!$I$6,E98,"m")+1 -> 1 | J98: =I50 -> 0 | K98: =(I98-(I98*J98*G98/12))*(1-J98)^F98 -> 0 | L98: =I98-K98 -> 0 | M98: =K98*J98*H98/12 -> 0 | N98: =L98+M98 -> 0 | O98: =K98-M98 -> 0 | Q98: =P98-O98 -> 0 | R98: =K98*J98*(12-H98)/12 -> 0
D99: 42644 | E99: 44743 | F99: =DATEDIF(D99,Cover!$J$7,"y") -> 5 | G99: =DATEDIF(D99,Cover!$J$7,"ym")+1 -> 9 | H99: =DATEDIF(Cover!$I$6,E99,"m")+1 -> 1 | J99: =J98 -> 0 | K99: =(I99-(I99*J99*G99/12))*(1-J99)^F99 -> 0 | L99: =I99-K99 -> 0 | M99: =K99*J99*H99/12 -> 0 | N99: =L99+M99 -> 0 | O99: =K99-M99 -> 0 | Q99: =P99-O99 -> 0 | R99: =K99*J99*(12-H99)/12 -> 0
D100: 42644 | E100: 44743 | F100: =DATEDIF(D100,Cover!$J$7,"y") -> 5 | G100: =DATEDIF(D100,Cover!$J$7,"ym")+1 -> 9 | H100: =DATEDIF(Cover!$I$6,E100,"m")+1 -> 1 | J100: =J99 -> 0 | K100: =(I100-(I100*J100*G100/12))*(1-J100)^F100 -> 0 | L100: =I100-K100 -> 0 | M100: =K100*J100*H100/12 -> 0 | N100: =L100+M100 -> 0 | O100: =K100-M100 -> 0 | Q100: =P100-O100 -> 0 | R100: =K100*J100*(12-H100)/12 -> 0
K101: =SUM(K98:K100) -> 0 | L101: =SUM(L98:L100) -> 0 | M101: =SUM(M98:M100) -> 0 | N101: =SUM(N98:N100) -> 0 | O101: =SUM(O98:O100) -> 0 | P101: =SUM(P98:P100) -> 0 | Q101: =SUM(Q98:Q100) -> 0 | R101: =SUM(R98:R100) -> 0
I103: =SUM(I66:I102) -> 0 | K103: =SUM(K66:K102)/2 -> 0 | L103: =SUM(L66:L102)/2 -> 0 | M103: =SUM(M66:M102)/2 -> 0 | N103: =SUM(N66:N102)/2 -> 0 | O103: =SUM(O66:O102)/2 -> 0 | P103: =SUM(P66:P102)/2 -> 0 | Q103: =SUM(Q66:Q102)/2 -> 0 | R103: =SUM(R66:R102)/2 -> 0

Sheet TD
A1: =Cover!C1 -> ABC LIMITED
A2: TAX DEPRECIATION
A3: =Cover!C3 -> FOR THE YEAR ENDED JUNE 30, 2023
A5: Description | B5: Opening WDV | C5: Additions | D5: Deletions | E5: Total | F5: Initial Allowance | H5: Depreciation | J5: Total Depreciation | K5: Closing WDV
F6: Rate % | G6: Amount | H6: Rate % | I6: Amount
A8: Building | E8: =SUM(B8:D8) -> 0 | F8: 0 | G8: =C8*F8 -> 0 | H8: 0.1 | I8: =(E8-G8)*H8 -> 0 | J8: =G8+I8 -> 0 | K8: =E8-J8 -> 0
A9: Plant and machinery | E9: =SUM(B9:D9) -> 0 | F9: 0.25 | G9: =C9*F9 -> 0 | H9: 0.15 | I9: =(E9-G9)*H9 -> 0 | J9: =G9+I9 -> 0 | K9: =E9-J9 -> 0
A10: Motor vehicles | E10: =SUM(B10:D10) -> 0 | F10: 0 | G10: =C10*F10 -> 0 | H10: 0.15 | I10: =(E10-G10)*H10 -> 0 | J10: =G10+I10 -> 0 | K10: =E10-J10 -> 0
A11: Furniture and fixtures | E11: =SUM(B11:D11) -> 0 | F11: 0 | G11: =C11*F11 -> 0 | H11: 0.15 | I11: =(E11-G11)*H11 -> 0 | J11: =G11+I11 -> 0 | K11: =E11-J11 -> 0
A12: Computers | E12: =SUM(B12:D12) -> 0 | F12: 0 | G12: =C12*F12 -> 0 | H12: 0.3 | I12: =(E12-G12)*H12 -> 0 | J12: =G12+I12 -> 0 | K12: =E12-J12 -> 0
A14: Total | B14: =SUM(B7:B13) -> 0 | C14: =SUM(C7:C13) -> 0 | D14: =SUM(D7:D13) -> 0 | E14: =SUM(E7:E13) -> 0 | G14: =SUM(G7:G13) -> 0 | I14: =SUM(I7:I13) -> 0 | J14: =SUM(J7:J13) -> 0 | K14: =SUM(K7:K13) -> 0
A17: Description | B17: Opening Cost | C17: Opening Amortization | D17: Opening WDV | E17: Additions | F17: Deletions | G17: Total | H17: Useful Life | I17: Amortization | J17: Total Amortization | K17: Closing WDV
C18: Amount | D18: Amount | H18: Years | I18: Amount
A20: Financial software | B20: 0 | C20: 0 | D20: =B20-C20 -> 0 | E20: 0 | F20: 0 | G20: =SUM(D20:F20) -> 0 | H20: 10 | I20: =B20/H20 -> 0 | J20: =C20+I20 -> 0 | K20: =G20-I20 -> 0
A22: Total | B22: =SUM(B19:B21) -> 0 | C22: =SUM(C19:C21) -> 0 | D22: =SUM(D19:D21) -> 0 | E22: =SUM(E19:E21) -> 0 | F22: =SUM(F19:F21) -> 0 | G22: =SUM(G19:G21) -> 0 | I22: =SUM(I19:I21) -> 0 | J22: =SUM(J19:J21) -> 0 | K22: =SUM(K19:K21) -> 0
A26: Asset Type | B26: Description | C26: Date of Acquisition | D26: Date of Disposal | E26: Cost | F26: Depreciation Rate | G26: Number of Years in use (Previous Years) | H26: Net Book Value | I26: Sales Proceeds | J26: Tax Gain / (Loss) on Disposals
A28: =IF(AD!B66=0,"",AD!B66) -> Freehold Land | B28: =IF(AD!C66=0,"",AD!C66) | C28: =IF(B28="","",AD!D66) | D28: =IF(B28="","",AD!E66) | E28: =IF(B28="","",AD!I66) | F28: 0 | G28: =YEAR(D28)-YEAR(C28) -> #VALUE! | I28: =IF(B28="",0,AD!P66) -> 0 | J28: =I28-H28 -> 0
A29: =IF(AD!B67=0,"",AD!B67) | B29: =IF(AD!C67=0,"",AD!C67) | C29: =IF(B29="","",AD!D67) | D29: =IF(B29="","",AD!E67) | E29: =IF(B29="","",AD!I67) | F29: 0 | G29: =YEAR(D29)-YEAR(C29) -> #VALUE! | I29: =IF(B29="",0,AD!P67) -> 0 | J29: =I29-H29 -> 0
A30: =IF(AD!B68=0,"",AD!B68) | B30: =IF(AD!C68=0,"",AD!C68) | C30: =IF(B30="","",AD!D68) | D30: =IF(B30="","",AD!E68) | E30: =IF(B30="","",AD!I68) | F30: 0 | G30: =YEAR(D30)-YEAR(C30) -> #VALUE! | I30: =IF(B30="",0,AD!P68) -> 0 | J30: =I30-H30 -> 0
A31: =IF(AD!B69=0,"",AD!B69) | B31: =IF(AD!C69=0,"",AD!C69) | C31: =IF(B31="","",AD!D69) | D31: =IF(B31="","",AD!E69) | E31: =IF(B31="","",AD!I69) | I31: =IF(B31="",0,AD!P69) -> 0 | J31: =I31-H31 -> 0
A32: =IF(AD!B70=0,"",AD!B70) -> Building on Freehold Land | B32: =IF(AD!C70=0,"",AD!C70) | C32: =IF(B32="","",AD!D70) | D32: =IF(B32="","",AD!E70) | E32: =IF(B32="","",AD!I70) | F32: =H8 -> 0.1 | G32: =YEAR(D32)-YEAR(C32) -> #VALUE! | I32: =IF(B32="",0,AD!P70) -> 0 | J32: =I32-H32 -> 0
A33: =IF(AD!B71=0,"",AD!B71) | B33: =IF(AD!C71=0,"",AD!C71) | C33: =IF(B33="","",AD!D71) | D33: =IF(B33="","",AD!E71) | E33: =IF(B33="","",AD!I71) | F33: =F32 -> 0.1 | G33: =YEAR(D33)-YEAR(C33) -> #VALUE! | I33: =IF(B33="",0,AD!P71) -> 0 | J33: =I33-H33 -> 0
A34: =IF(AD!B72=0,"",AD!B72) | B34: =IF(AD!C72=0,"",AD!C72) | C34: =IF(B34="","",AD!D72) | D34: =IF(B34="","",AD!E72) | E34: =IF(B34="","",AD!I72) | F34: =F33 -> 0.1 | G34: =YEAR(D34)-YEAR(C34) -> #VALUE! | I34: =IF(B34="",0,AD!P72) -> 0 | J34: =I34-H34 -> 0
A35: =IF(AD!B73=0,"",AD!B73) | B35: =IF(AD!C73=0,"",AD!C73) | C35: =IF(B35="","",AD!D73) | D35: =IF(B35="","",AD!E73) | E35: =IF(B35="","",AD!I73) | I35: =IF(B35="",0,AD!P73) -> 0 | J35: =I35-H35 -> 0
A36: =IF(AD!B74=0,"",AD!B74) -> Plant and Machinery | B36: =IF(AD!C74=0,"",AD!C74) -> plant | C36: =IF(B36="","",AD!D74) -> 43009 | D36: =IF(B36="","",AD!E74) -> 44743 | E36: =IF(B36="","",AD!I74) -> 0 | F36: =H9 -> 0.15 | G36: =YEAR(D36)-YEAR(C36) -> 5 | H36: =E36*(1-F36)^(SUM(G36)) -> 0 | I36: =IF(B36="",0,AD!P74) -> 0 | J36: =I36-H36 -> 0
A37: =IF(AD!B75=0,"",AD!B75) | B37: =IF(AD!C75=0,"",AD!C75) | C37: =IF(B37="","",AD!D75) | D37: =IF(B37="","",AD!E75) | E37: =IF(B37="","",AD!I75) | F37: =F36 -> 0.15 | I37: =IF(B37="",0,AD!P75) -> 0 | J37: =I37-H37 -> 0
A38: =IF(AD!B76=0,"",AD!B76) | B38: =IF(AD!C76=0,"",AD!C76) | C38: =IF(B38="","",AD!D76) | D38: =IF(B38="","",AD!E76) | E38: =IF(B38="","",AD!I76) | F38: =F37 -> 0.15 | I38: =IF(B38="",0,AD!P76) -> 0 | J38: =I38-H38 -> 0
A39: =IF(AD!B77=0,"",AD!B77) | B39: =IF(AD!C77=0,"",AD!C77) | C39: =IF(B39="","",AD!D77) | D39: =IF(B39="","",AD!E77) | E39: =IF(B39="","",AD!I77) | I39: =IF(B39="",0,AD!P77) -> 0 | J39: =I39-H39 -> 0
A40: =IF(AD!B78=0,"",AD!B78) -> Generator | B40: =IF(AD!C78=0,"",AD!C78) | C40: =IF(B40="","",AD!D78) | D40: =IF(B40="","",AD!E78) | E40: =IF(B40="","",AD!I78) | I40: =IF(B40="",0,AD!P78) -> 0 | J40: =I40-H40 -> 0
A41: =IF(AD!B79=0,"",AD!B79) | B41: =IF(AD!C79=0,"",AD!C79) | C41: =IF(B41="","",AD!D79) | D41: =IF(B41="","",AD!E79) | E41: =IF(B41="","",AD!I79) | I41: =IF(B41="",0,AD!P79) -> 0 | J41: =I41-H41 -> 0
A42: =IF(AD!B80=0,"",AD!B80) | B42: =IF(AD!C80=0,"",AD!C80) | C42: =IF(B42="","",AD!D80) | D42: =IF(B42="","",AD!E80) | E42: =IF(B42="","",AD!I80) | I42: =IF(B42="",0,AD!P80) -> 0 | J42: =I42-H42 -> 0
A43: =IF(AD!B81=0,"",AD!B81) | B43: =IF(AD!C81=0,"",AD!C81) | C43: =IF(B43="","",AD!D81) | D43: =IF(B43="","",AD!E81) | E43: =IF(B43="","",AD!I81) | I43: =IF(B43="",0,AD!P81) -> 0 | J43: =I43-H43 -> 0
A44: =IF(AD!B82=0,"",AD!B82) -> Office Equipment | B44: =IF(AD!C82=0,"",AD!C82) | C44: =IF(B44="","",AD!D82) | D44: =IF(B44="","",AD!E82) | E44: =IF(B44="","",AD!I82) | I44: =IF(B44="",0,AD!P82) -> 0 | J44: =I44-H44 -> 0
A45: =IF(AD!B83=0,"",AD!B83) | B45: =IF(AD!C83=0,"",AD!C83) | C45: =IF(B45="","",AD!D83) | D45: =IF(B45="","",AD!E83) | E45: =IF(B45="","",AD!I83) | I45: =IF(B45="",0,AD!P83) -> 0 | J45: =I45-H45 -> 0
A46: =IF(AD!B84=0,"",AD!B84) | B46: =IF(AD!C84=0,"",AD!C84) | C46: =IF(B46="","",AD!D84) | D46: =IF(B46="","",AD!E84) | E46: =IF(B46="","",AD!I84) | I46: =IF(B46="",0,AD!P84) -> 0 | J46: =I46-H46 -> 0
A47: =IF(AD!B85=0,"",AD!B85) | B47: =IF(AD!C85=0,"",AD!C85) | C47: =IF(B47="","",AD!D85) | D47: =IF(B47="","",AD!E85) | E47: =IF(B47="","",AD!I85) | I47: =IF(B47="",0,AD!P85) -> 0 | J47: =I47-H47 -> 0
A48: =IF(AD!B86=0,"",AD!B86) -> Computers | B48: =IF(AD!C86=0,"",AD!C86) | C48: =IF(B48="","",AD!D86) | D48: =IF(B48="","",AD!E86) | E48: =IF(B48="","",AD!I86) | I48: =IF(B48="",0,AD!P86) -> 0 | J48: =I48-H48 -> 0
A49: =IF(AD!B87=0,"",AD!B87) | B49: =IF(AD!C87=0,"",AD!C87) | C49: =IF(B49="","",AD!D87) | D49: =IF(B49="","",AD!E87) | E49: =IF(B49="","",AD!I87) | I49: =IF(B49="",0,AD!P87) -> 0 | J49: =I49-H49 -> 0
A50: =IF(AD!B88=0,"",AD!B88) | B50: =IF(AD!C88=0,"",AD!C88) | C50: =IF(B50="","",AD!D88) | D50: =IF(B50="","",AD!E88) | E50: =IF(B50="","",AD!I88) | I50: =IF(B50="",0,AD!P88) -> 0 | J50: =I50-H50 -> 0
... A63: =IF(AD!B101=0,"",AD!B101) | B63: =IF(AD!C101=0,"",AD!C101) | C63: =IF(B63="","",AD!D101) | D63: =IF(B63="","",AD!E101) | E63: =IF(B63="","",AD!I101) | I63: =IF(B63="",0,AD!P101) -> 0 | J63: =I63-H63 -> 0
A64: =IF(AD!B102=0,"",AD!B102) | B64: =IF(AD!C102=0,"",AD!C102)
A65: =IF(AD!B103=0,"",AD!B103)

Sheet CT
A1: =Cover!C1 -> ABC LIMITED
A2: CURRENT TAX
A3: =Cover!C3 -> FOR THE YEAR ENDED JUNE 30, 2023
G5: FTR | I5: NTR | K5: TOTAL
G6: =G18/K18 -> 0 | I6: =I18/K18 -> 1 | K6: =G6+I6 -> 1
B7: Revenue
C8: Subject to Final Taxation
C9: Export Sales | G9: 0 | K9: =G9+I9 -> 0
C10: Contract income | G10: 0 | K10: =G10+I10 -> 0
C11: Indenting Commission | G11: 0 | K11: =G11+I11 -> 0
C13: Subject to Normal Taxation
C14: Local Sales | I14: 0.01 | K14: =G14+I14 -> 0.01
C15: Less: Sales return | I15: 0 | K15: =G15+I15 -> 0
C16: Less: Discounts | I16: 0 | K16: =G16+I16 -> 0
C17: Less: Sales tax | I17: 0 | K17: =G17+I17 -> 0
G18: =SUM(G9:G17) -> 0 | I18: =SUM(I9:I17) -> 0.01 | K18: =G18+I18 -> 0.01
B20: Cost of sales | G20: =K20*$G$6 -> 0 | I20: =K20*$I$6 -> 0 | K20: 0
B22: =IF(K22>=0,"Gross Profit","Gross Loss") -> Gross Profit | G22: =G18+G20 -> 0 | I22: =I18+I20 -> 0.01 | K22: =K18+K20 -> 0.01
B24: =SOPL!B14 -> Distribution costs | G24: =K24*$G$6 -> 0 | I24: =K24*$I$6 -> 0 | K24: 0
B25: =SOPL!B15 -> Administrative expenses | G25: =K25*$G$6 -> 0 | I25: =K25*$I$6 -> 0 | K25: 0
B26: =SOPL!B16 -> Other operating income / (expenses) | G26: =K26*$G$6 -> 0 | I26: =K26*$I$6 -> 0 | K26: 0
B27: =SOPL!B17 -> Other gains/(losses) | G27: =K27*$G$6 -> 0 | I27: =K27*$I$6 -> 0 | K27: 0
B29: =IF(K29>=0,"Operating Profit","Operating Loss") -> Operating Profit | G29: =SUM(G22:G28) -> 0 | I29: =SUM(I22:I28) -> 0.01 | K29: =SUM(K22:K28) -> 0.01
B31: =SOPL!B23 -> Other income | G31: =K31*$G$6 -> 0 | I31: =K31*$I$6 -> 0 | K31: 0
B32: =SOPL!B24 -> Finance costs | G32: =K32*$G$6 -> 0 | I32: =K32*$I$6 -> 0 | K32: 0
B34: =IF(K34>=0,"Accounting Profit before WPPF and WWF","Accounting Loss before WPPF and WWF") -> Accounting Profit before WPPF and WWF | G34: =SUM(G29:G33) -> 0 | I34: =SUM(I29:I33) -> 0.01 | K34: =SUM(K29:K33) -> 0.01
B36: Inadmissible expenses and admissible income
C37: Accounting depreciation | G37: =K37*$G$6 -> 0 | I37: =K37*$I$6 -> 0 | K37: 0
C38: Accounting amortization | G38: =K38*$G$6 -> 0 | I38: =K38*$I$6 -> 0 | K38: 0
C39: Accounting loss on disposal | G39: =K39*$G$6 -> 0 | I39: =K39*$I$6 -> 0 | K39: 0
C40: Interest on finance lease | G40: =K40*$G$6 -> 0 | I40: =K40*$I$6 -> 0 | K40: 0
C41: Interest on WPPF | G41: =K41*$G$6 -> 0 | I41: =K41*$I$6 -> 0 | K41: 0
C42: Charity And donations | G42: =K42*$G$6 -> 0 | I42: =K42*$I$6 -> 0 | K42: 0
C43: Fine and Penalties | G43: =K43*$G$6 -> 0 | I43: =K43*$I$6 -> 0 | K43: 0
C44: Provision for gratuity | G44: =K44*$G$6 -> 0 | I44: =K44*$I$6 -> 0 | K44: 0
C45: Provision for doubtful debts | G45: =K45*$G$6 -> 0 | I45: =K45*$I$6 -> 0 | K45: 0
G47: =SUM(G37:G46) -> 0 | I47: =SUM(I37:I46) -> 0 | K47: =SUM(K37:K46) -> 0
B50: Admissible expenses and Inadmissible income
C51: Accounting gain on disposal | G51: =K51*$G$6 -> 0 | I51: =K51*$I$6 -> 0 | K51: 0
C52: Tax amortization | G52: =K52*$G$6 -> 0 | I52: =K52*$I$6 -> 0 | K52: 0
C53: Tax depreciation | G53: =K53*$G$6 -> 0 | I53: =K53*$I$6 -> 0 | K53: 0
C54: Tax loss on disposal | G54: =K54*$G$6 -> 0 | I54: =K54*$I$6 -> 0 | K54: 0
C55: Bad debts written off | G55: =K55*$G$6 -> 0 | I55: =K55*$I$6 -> 0 | K55: 0
C56: Lease rentals paid | G56: =K56*$G$6 -> 0 | I56: =K56*$I$6 -> 0 | K56: 0
C57: Gratuity paid | G57: =K57*$G$6 -> 0 | I57: =K57*$I$6 -> 0 | K57: 0
C58: Loss on investment | G58: =K58*$G$6 -> 0 | I58: =K58*$I$6 -> 0 | K58: 0
C59: Dividend Income | G59: =K59*$G$6 -> 0 | I59: =K59*$I$6 -> 0 | K59: 0
C60: Unused Tax losses b/f | G60: =K60*$G$6 -> 0 | I60: =K60*$I$6 -> 0 | K60: 0
G62: =SUM(G51:G61) -> 0 | I62: =SUM(I51:I61) -> 0 | K62: =SUM(K51:K61) -> 0
B64: =IF(K64>=0,"Taxable Profit before WPPF and WWF","Taxable Loss before WPPF and WWF") -> Taxable Profit before WPPF and WWF | G64: =G34+G47+G62 -> 0 | I64: =I34+I47+I62 -> 0.01 | K64: =K34+K47+K62 -> 0.01
C67: WPPF | G67: =K67*$G$6 -> 0 | I67: =K67*$I$6 -> -0.0005 | K67: =-K34*0.05 -> -0.0005
C68: WWF | G68: =K68*$G$6 -> 0 | I68: =K68*$I$6 -> -0.0002 | K68: =-K64*0.02 -> -0.0002
G69: =SUM(G67:G68) -> 0 | I69: =SUM(I67:I68) -> -0.0007 | K69: =SUM(K67:K68) -> -0.0007
B71: =IF(K71>=0,"Taxable Profit after WPPF and WWF","Taxable Loss after WPPF and WWF") -> Taxable Profit after WPPF and WWF | G71: =G64+G69 -> 0 | I71: =I64+I69 -> 0.0093 | K71: =K64+K69 -> 0.0093
C73: Less: WPPF Paid | G73: =K73*$G$6 -> 0 | I73: =K73*$I$6 -> 0 | K73: 0
C74: Add: WPPF CY Allocation | G74: =-G67 -> 0 | I74: =-I67 -> 0.0005 | K74: =-K67 -> 0.0005
G75: =SUM(G73:G74) -> 0 | I75: =SUM(I73:I74) -> 0.0005 | K75: =SUM(K73:K74) -> 0.0005
B77: =IF(K77>=0,"Taxable Profit subject to Taxation","Taxable Loss subject to Taxation") -> Taxable Profit subject to Taxation | G77: =G71+G75 -> 0 | I77: =I71+I75 -> 0.0098 | K77: =K71+K75 -> 0.0098
B79: Maximum of
C80: Subject to Final Taxation
C81: =E81*100&"% of Tax on "&C9 -> 1% of Tax on Export Sales | E81: 0.01 | G81: =K102*E81 -> 0
C82: =E82*100&"% of Tax on "&C10 -> 7% of Tax on Contract income | E82: 0.07 | G82: =K10*E82 -> 0
C83: =E83*100&"% of Tax on "&C11 -> 0% of Tax on Indenting Commission | E83: 0 | G83: =K11*E83 -> 0
C85: Subject to Normal Taxation
C86: =E86*100&"% of Revenue" -> 1.5% of Revenue | E86: 0.015 | I86: =IF(I18>0,I18*E86,0) -> 0.00015
C87: =E87*100&"% of taxable income" -> 29% of taxable income | E87: 0.29 | I87: =IF(I77>0,I77*E87,0) -> 0.002842
C88: =E88*100&"% of Accounting Profit before WWF" -> 17% of Accounting Profit before WWF | E88: 0.17 | I88: =IF((K34-K67)>0,(K34-K67)*E88,0) -> 0.001785
B90: Total Tax Expense | G90: =SUM(G81:G88) -> 0 | I90: =MAX(I81:I88) -> 0.002842 | K90: =G90+I90 -> 0.002842
B92: Less: Tax Credits
C93: Credit u/s 65B @ Plant & Machinery additions @ 10% | K93: 0
C94: Rebate on donation @ 20% | K94: 0
K95: 0
K96: =SUM(K93:K95) -> 0
B98: Less: Tax Already paid on
C99: Imports | K99: 0
C100: Exports | K100: 0
C101: Cash withdrawals | K101: 0
C102: Bank Profit | K102: 0
C103: Electricity Bills | K103: 0
C104: Telephone Bills | K104: 0
C105: Mobile Bills | K105: 0
C106: Bank Profit | K106: 0
C107: Sale of goods (i.e. Deducted by Customers) | K107: 0
C108: Vehicles Registration / Renewal | K108: 0
C109: Advance tax deposited | K109: 0
K110: 0
K111: =-SUM(K99:K110) -> 0
B113: =IF(K113>=0,"Tax Payable with Return","Tax Refundable with Return") -> Tax Payable with Return | K113: =K90+K111+K96 -> 0.002842
B115: =IF(K115>=0,"Tax Payable with Return including WWF","Tax Refundable with Return including WWF") -> Tax Payable with Return including WWF | K115: =K113-K68 -> 0.003042

Sheet DT
A1: =Cover!C1 -> ABC LIMITED
A2: DEFEERED TAX
A3: =Cover!C3 -> FOR THE YEAR ENDED JUNE 30, 2023
A5: Items | C5: Carrying Value -Cost | D5: Carrying Value -Revaluation | E5: Total Carrying Value | F5: Tax Base | G5: Deductible Temporary Difference | H5: Taxable Temporary Difference | J5: Broght Forward Of Losses | L5: Adjustment Against Income Of Tax Year | M5: Amount | N5: Balance Available For Adjustment | O5: Unabsorbed Depreciation Broght Forward | Q5: Unabsorbed Amortisation Broght Forward
J6: Year | K6: --------------------------Rupees--------------------------- | O6: Year | P6: --Rupees-- | Q6: Year | R6: --Rupees--
A7: Assets | J7: 2015 | K7: 0 | N7: =SUM(K7:M7) -> 0 | O7: 2015 and before | Q7: 2015 and before
C8: =E8-D8 -> 0 | G8: =-IF(E8-F8<0,E8-F8,0) -> 0 | H8: =IF((E8-F8)>0,(E8-F8),0) -> 0 | J8: =J7+1 -> 2016 | K8: =N7 -> 0 | N8: =SUM(K8:M8) -> 0 | O8: 2016 | Q8: 2016
C9: =E9-D9 -> 0 | G9: =-IF(E9-F9<0,E9-F9,0) -> 0 | H9: =IF((E9-F9)>0,(E9-F9),0) -> 0 | J9: =J8+1 -> 2017 | K9: =N8 -> 0 | N9: =SUM(K9:M9) -> 0 | O9: =O8+1 -> 2017 | Q9: =Q8+1 -> 2017
C10: =E10-D10 -> 0 | G10: =-IF(E10-F10<0,E10-F10,0) -> 0 | H10: =IF((E10-F10)>0,(E10-F10),0) -> 0 | J10: =J9+1 -> 2018 | K10: =N9 -> 0 | N10: =SUM(K10:M10) -> 0 | O10: =O9+1 -> 2018 | Q10: =Q9+1 -> 2018
C11: =E11-D11 -> 0 | G11: =-IF(E11-F11<0,E11-F11,0) -> 0 | H11: =IF((E11-F11)>0,(E11-F11),0) -> 0 | J11: =J10+1 -> 2019 | K11: =N10 -> 0 | N11: =SUM(K11:M11) -> 0 | O11: =O10+1 -> 2019 | Q11: =Q10+1 -> 2019
C12: =E12-D12 -> 0 | G12: =-IF(E12-F12<0,E12-F12,0) -> 0 | H12: =IF((E12-F12)>0,(E12-F12),0) -> 0 | J12: =J11+1 -> 2020 | K12: =N11 -> 0 | N12: =SUM(K12:M12) -> 0 | O12: =O11+1 -> 2020 | Q12: =Q11+1 -> 2020
C13: =E13-D13 -> 0 | G13: =-IF(E13-F13<0,E13-F13,0) -> 0 | H13: =IF((E13-F13)>0,(E13-F13),0) -> 0 | J13: =J12+1 -> 2021 | K13: =N12 -> 0 | N13: =SUM(K13:M13) -> 0 | O13: =O12+1 -> 2021 | Q13: =Q12+1 -> 2021
C14: =E14-D14 -> 0 | G14: =-IF(E14-F14<0,E14-F14,0) -> 0 | H14: =IF((E14-F14)>0,(E14-F14),0) -> 0
C15: =E15-D15 -> 0 | G15: =-IF(E15-F15<0,E15-F15,0) -> 0 | H15: =IF((E15-F15)>0,(E15-F15),0) -> 0
C16: =E16-D16 -> 0 | G16: =-IF(E16-F16<0,E16-F16,0) -> 0 | H16: =IF((E16-F16)>0,(E16-F16),0) -> 0
A18: Liabilities
C19: =E19-D19 -> 0 | G19: =IF(E19-F19>0,E19,0) -> 0 | H19: =-IF(E19-F19<0,E19,0) -> 0
C20: =E20-D20 -> 0 | G20: =IF(E20-F20>0,E20,0) -> 0 | H20: =-IF(E20-F20<0,E20,0) -> 0
C21: =E21-D21 -> 0 | G21: =IF(E21-F21>0,E21,0) -> 0 | H21: =-IF(E21-F21<0,E21,0) -> 0
C22: =E22-D22 -> 0 | G22: =IF(E22-F22>0,E22,0) -> 0 | H22: =-IF(E22-F22<0,E22,0) -> 0 | J22: Total | L22: =SUM(L7:L21) -> 0 | M22: =SUM(M7:M21) -> 0 | P22: =SUM(P7:P21) -> 0 | R22: =SUM(R7:R21) -> 0
A24: Total | G24: =SUM(G8:G22) -> 0 | H24: =SUM(H8:H22) -> 0 | J24: UNUSED TAX CREDITS
J25: Year | K25: Normal Income Tax | L25: Accounting Profit / Tax Chargeable u/s 113C @17% | M25: Minimum Tax Chargeable u/s 113 | N25: ACT to be C/F (10 years) | O25: Minimum Tax to be C/F (5 years) | P25: Adjustment in Tax Year | Q25: Amount Adjusted | R25: Balance Available For Adjustment
A26: =IF(H26>=0,"Net Taxable temporary difference","Net Deductible temporary difference") -> Net Taxable temporary difference | H26: =(H24-G24) -> 0 | J26: 2012 | N26: =IF(T26=K26,0,IF(T26=L26,L26-M26,0)) -> 0 | O26: =IF(M26-K26-N26>0,M26-K26,0) -> 0 | Q26: 0 | R26: =N26+O26+Q26 -> 0 | T26: =MAX(K26:M26) -> 0
J27: =J26+1 -> 2013 | N27: =IF(T27=K27,0,IF(T27=L27,L27-M27,0)) -> 0 | O27: =IF(M27-K27-N27>0,M27-K27,0) -> 0 | Q27: 0 | R27: =R26+N27+O27+Q27 -> 0 | T27: =MAX(K27:M27) -> 0
A28: Recognised under normal tax regime @ __ % | H28: =H26*100% -> 0 | J28: =J27+1 -> 2014 | N28: =IF(T28=K28,0,IF(T28=L28,L28-M28,0)) -> 0 | O28: =IF(M28-K28-N28>0,M28-K28,0) -> 0 | Q28: 0 | R28: =R27+N28+O28+Q28 -> 0 | T28: =MAX(K28:M28) -> 0
J29: =J28+1 -> 2015 | N29: =IF(T29=K29,0,IF(T29=L29,L29-M29,0)) -> 0 | O29: =IF(M29-K29-N29>0,M29-K29,0) -> 0 | Q29: 0 | R29: =R28+N29+O29+Q29 -> 0 | T29: =MAX(K29:M29) -> 0
A30: Less: Unused tax losses | H30: =N13+R22+P22 -> 0 | J30: =J29+1 -> 2016 | N30: =IF(T30=K30,0,IF(T30=L30,L30-M30,0)) -> 0 | O30: =IF(M30-K30-N30>0,M30-K30,0) -> 0 | Q30: 0 | R30: =R29+N30+O30+Q30 -> 0 | T30: =MAX(K30:M30) -> 0
J31: =J30+1 -> 2017 | N31: =IF(T31=K31,0,IF(T31=L31,L31-M31,0)) -> 0 | O31: =IF(M31-K31-N31>0,M31-K31,0) -> 0 | Q31: =-O26 -> 0 | R31: =R30+N31+O31+Q31 -> 0 | T31: =MAX(K31:M31) -> 0
A32: Deferred tax liability / (asset) @ 29% | H32: =SUM(H28:H31)*29% -> 0 | J32: =J31+1 -> 2018 | N32: =IF(T32=K32,0,IF(T32=L32,L32-M32,0)) -> 0 | O32: =IF(M32-K32-N32>0,M32-K32,0) -> 0 | Q32: =-O27 -> 0 | R32: =R31+N32+O32+Q32 -> 0 | T32: =MAX(K32:M32) -> 0
J33: =J32+1 -> 2019 | N33: =IF(T33=K33,0,IF(T33=L33,L33-M33,0)) -> 0 | O33: =IF(M33-K33-N33>0,M33-K33,0) -> 0 | Q33: =-O28 -> 0 | R33: =R32+N33+O33+Q33 -> 0 | T33: =MAX(K33:M33) -> 0
A34: Less: Unused tax credits | H34: =R35 -> 0 | J34: =J33+1 -> 2020 | N34: =IF(T34=K34,0,IF(T34=L34,L34-M34,0)) -> 0 | O34: =IF(M34-K34-N34>0,M34-K34,0) -> 0 | Q34: =-O29 -> 0 | R34: =R33+N34+O34+Q34 -> 0 | T34: =MAX(K34:M34) -> 0
J35: =J34+1 -> 2021 | K35: =CT!I87 -> 0.002842 | L35: =CT!I88 -> 0.001785 | M35: =CT!I86 -> 0.00015 | N35: =IF(T35=K35,0,IF(T35=L35,L35-M35,0)) -> 0 | O35: =IF(M35-K35-N35>0,M35-K35,0) -> 0 | Q35: =-O30 -> 0 | R35: =R34+N35+O35+Q35 -> 0 | T35: =MAX(K35:M35) -> 0.002842
A36: Net deferred tax liability / (asset) | H36: =SUM(H32:H35) -> 0
J37: Total | K37: =SUM(N26:N31) -> 0 | N37: =SUM(N26:N36) -> 0 | O37: =SUM(O26:O36) -> 0
E39: DEFERRED TAX A/C
E40: B/f DTA - UTC | F40: =R34 -> 0 | G40: B/f DTL - CIE
E41: B/f DTA - PNL | G41: B/f DTL - OCI
G42: B/f DTL - PNL
E44: Unused tax credit | F44: =H51-F40 -> 0
E46: PNL | G46: PNL
E47: OCI | G47: OCI
E48: CIE | G48: CIE
E50: C/f DTL - CIE
E51: C/f DTL - OCI | G51: B/f DTA - UTC | H51: =R35 -> 0
E52: C/f DTL - PNL | F52: =IF(H32>0,H32,0) -> 0 | G52: B/f DTA - PNL | H52: =IF(H32<0,-H32,0) -> 0
F55: =SUM(F40:F54) -> 0 | H55: =SUM(H40:H54) -> 0
