Workbook

Sheet Index
B1: ABC & Co. | H1: BS.08
B2: (Chartered Accountants)
B4: Client: | C4: ABC Limited | G4: Prepared by:
B5: Period: | C5: Year ended June 30, 2023 | G5: Date prepared:
B6: Head: | C6: Stock in Trade | G6: Reviewed by:
G7: Date reviewed:
B8: INDEX
B10: Sr. # | C10: Description | E10: W.P. Ref. | G10: Whether Placed in File | H10: Initials of Reviewer
B12: 1 | C12: Audit Objectives and Conclusions | E12: =$H$1&" - "&B12 -> BS.08 - 1
B14: =B12+1 -> 2 | C14: Lead Schedule | E14: =$H$1&" - "&B14 -> BS.08 - 2
B16: =B14+1 -> 3 | C16: Sub-Lead Schedule | E16: =$H$1&" - "&B16 -> BS.08 - 3
B18: =B16+1 -> 4 | C18: Vouching - Additions | E18: =$H$1&" - "&B18 -> BS.08 - 4
B20: =B18+1 -> 5 | C20: Confirmation summary, reconciliation | E20: =$H$1&" - "&B20 -> BS.08 - 5
B22: =B20+1 -> 6 | C22: Copies of Documents/Summary | E22: =$H$1&" - "&B22 -> BS.08 - 6
B24: =B22+1 -> 7 | C24: Impairment Testing | E24: =$H$1&" - "&B24 -> BS.08 - 7
B26: =B24+1 -> 8 | C26: Adjusting Entries | E26: =$H$1&" - "&B26 -> BS.08 - 8

Sheet AOC
B1: =Index!$B$1 -> ABC & Co. | E1: =Index!E12 -> BS.08 - 1
B2: =Index!$B$2 -> (Chartered Accountants)
B4: =Index!$B$4 -> Client: | C4: =Index!$C$4 -> ABC Limited | D4: =Index!$G$4 -> Prepared by: | E4: =IF(Index!$H$4="","",Index!$H$4)
B5: =Index!$B$5 -> Period: | C5: =Index!$C$5 -> Year ended June 30, 2023 | D5: =Index!$G$5 -> Date prepared: | E5: =IF(Index!$H$5="","",Index!$H$5)
B6: =Index!$B$6 -> Head: | C6: =Index!$C$6 -> Stock in Trade | D6: =Index!$G$6 -> Reviewed by: | E6: =IF(Index!$H$6="","",Index!$H$6)
D7: =Index!$G$7 -> Date reviewed: | E7: =IF(Index!$H$7="","",Index!$H$7)
B8: =UPPER("Audit Objectives and Conclusions") -> AUDIT OBJECTIVES AND CONCLUSIONS
B10: Sr. # | C10: Audit Objectives | D10: Objective Met
D11: Yes/No | E11: Initials
B13: 1 | C13: Stock in trade is completely and accurately recorded.
B14: =B13+1 -> 2 | C14: All recorded stock in trade actually exist.
B15: =B14+1 -> 3 | C15: Stock in trade is recorded at appropriate values.
B16: =B15+1 -> 4 | C16: Recorded stock in trade is owned by the client and title is also in the name of client.
B17: =B16+1 -> 5 | C17: Stock in trade is presented and all disclosures have been given in accordance with the Fourth / Fifth Schedule of the Companies Act, 2017 and relevant IASs/IFRSs.
B20: Sr. # | C20: Conclusion | D20: Satisfactory
D21: Yes/No | E21: Initials
B23: 1 | C23: The audit has been completed in accordance with Audit program.
B24: =B23+1 -> 2 | C24: The working papers demonstrate that adequate work has been undertaken.
B25: =B24+1 -> 3 | C25: The working papers contain sufficient information, details of significant features and notes of unusual matters to enable us to form an opinion on financial statements.
B26: =B25+1 -> 4 | C26: In my opinion above amounts are fairly stated and on a consistent basis with the previous period.

Sheet Lead
B1: =Index!$B$1 -> ABC & Co. | K1: =Index!E14 -> BS.08 - 2
B2: =Index!$B$2 -> (Chartered Accountants)
B4: =Index!$B$4 -> Client: | C4: =Index!$C$4 -> ABC Limited | J4: =Index!$G$4 -> Prepared by: | K4: =IF(Index!$H$4="","",Index!$H$4)
B5: =Index!$B$5 -> Period: | C5: =Index!$C$5 -> Year ended June 30, 2023 | J5: =Index!$G$5 -> Date prepared: | K5: =IF(Index!$H$5="","",Index!$H$5)
B6: =Index!$B$6 -> Head: | C6: =Index!$C$6 -> Stock in Trade | J6: =Index!$G$6 -> Reviewed by: | K6: =IF(Index!$H$6="","",Index!$H$6)
J7: =Index!$G$7 -> Date reviewed: | K7: =IF(Index!$H$7="","",Index!$H$7)
B8: LEAD SCHEDULE
B9: Work performed
B10: Analytical Procesures:
B11: Compared current year balances and expense with last year and reasons for significant variations have been properly documented.
B13: Test of Details
B14: Tested cut-off of inventory:
B15: Selected transactions from purchases, purchase returns and sales (stock outs) of some days before and after the year end; and
B16: Ensured proper recording of transactions in correct period.
B17: Ensured that closing balances as per our working paper file are matched with general ledger.
B18: Determined that disclosures have been made in accordance with the requirements of Fifth Schedule to the Companies Act, 2017 and the applicable IASs/IFRSs.
B20: Observations
B21: None.
... B24: Satisfactory
B26: Description | E26: W.P. Ref. | G26: 2022 | H26: =G26-1 -> 2021 | I26: Variance | J26: Variance | K26: Reason for Variance
G27: Rupees | H27: Rupees | I27: Rupees | J27: %
B29: =C6 -> Stock in Trade
B30: Raw Material | I30: =G30-H30 -> 0 | J30: =IFERROR(I30/H30,"")
B31: Packing Material | I31: =G31-H31 -> 0 | J31: =IFERROR(I31/H31,"")
B32: Work in Process | I32: =G32-H32 -> 0 | J32: =IFERROR(I32/H32,"")
B33: Finished Goods | I33: =G33-H33 -> 0 | J33: =IFERROR(I33/H33,"")
B34: Waste stock | I34: =G34-H34 -> 0 | J34: =IFERROR(I34/H34,"")
B35: Stock-in-Bond | I35: =G35-H35 -> 0 | J35: =IFERROR(I35/H35,"")
B36: Stock-in-transit | I36: =G36-H36 -> 0 | J36: =IFERROR(I36/H36,"")
B37: Other stocks | I37: =G37-H37 -> 0 | J37: =IFERROR(I37/H37,"")
B42: T O T A L | G42: =SUM(G28:G41) -> 0 | H42: =SUM(H28:H40) -> 0 | I42: =SUM(I28:I40) -> 0

Sheet SubLead-RawMaterial
B1: =Index!$B$1 -> ABC & Co. | I1: =Index!E16 -> BS.08 - 3
B2: =Index!$B$2 -> (Chartered Accountants)
B4: =Index!$B$4 -> Client: | C4: =Index!$C$4 -> ABC Limited | H4: =Index!$G$4 -> Prepared by: | I4: =IF(Index!$H$4="","",Index!$H$4)
B5: =Index!$B$5 -> Period: | C5: =Index!$C$5 -> Year ended June 30, 2023 | H5: =Index!$G$5 -> Date prepared: | I5: =IF(Index!$H$5="","",Index!$H$5)
B6: =Index!$B$6 -> Head: | C6: =Index!$C$6 -> Stock in Trade | H6: =Index!$G$6 -> Reviewed by: | I6: =IF(Index!$H$6="","",Index!$H$6)
H7: =Index!$G$7 -> Date reviewed: | I7: =IF(Index!$H$7="","",Index!$H$7)
B8: SUB-LEAD SCHEDULE
B9: Work performed
B10: Analytical Procedures:
B11: Assessed the appropriateness of purchases and consumptions method and rate in view of the flow of economic benefits.
B12: Checked the reasonableness of consumption allocated to inventories at different stages.
B13: Documented logical commercial reasons for purchases and consumption made during the year.
B14: Checked the appropriateness of compilation of overheads and allocation basis of the same to different products.
B16: Test of Details:
B17: Observed physical counting of inventories carried out by the client (at year-end or at any other date).
B18: Perform tests of intervening transactions to ensure existence and conditions (unless impracticable).
B19: Also checked on sample basis some items to ensure reliability. (Sample Attached)
B20: Checked that third party inventories are identified and excluded from physical count.
... B36: Satisfactory
B38: Description | D38: W.P. Ref. | E38: =Lead!G26 -> 2022 | F38: =Lead!H26 -> 2021 | G38: Variance | H38: Variance | I38: Reason for Variance
E39: Rupees | F39: Rupees | G39: Rupees | H39: %
B41: =Lead!B30 -> Raw Material
B42: Opening balance | G42: =E42-F42 -> 0 | H42: =IFERROR(G42/F42,"")
B43: Add: Purchases during the year | G43: =E43-F43 -> 0 | H43: =IFERROR(G43/F43,"")
B44: Less: Issued to production during the year | G44: =E44-F44 -> 0 | H44: =IFERROR(G44/F44,"")
B46: Total closing balance | E46: =SUM(E42:E45) -> 0 | F46: =SUM(F42:F45) -> 0 | G46: =SUM(G42:G45) -> 0

Sheet SubLead-PackingMaterial
B1: =Index!$B$1 -> ABC & Co. | K1: =Index!E16 -> BS.08 - 3
B2: =Index!$B$2 -> (Chartered Accountants)
B4: =Index!$B$4 -> Client: | C4: =Index!$C$4 -> ABC Limited | J4: =Index!$G$4 -> Prepared by: | K4: =IF(Index!$H$4="","",Index!$H$4)
B5: =Index!$B$5 -> Period: | C5: =Index!$C$5 -> Year ended June 30, 2023 | J5: =Index!$G$5 -> Date prepared: | K5: =IF(Index!$H$5="","",Index!$H$5)
B6: =Index!$B$6 -> Head: | C6: =Index!$C$6 -> Stock in Trade | J6: =Index!$G$6 -> Reviewed by: | K6: =IF(Index!$H$6="","",Index!$H$6)
J7: =Index!$G$7 -> Date reviewed: | K7: =IF(Index!$H$7="","",Index!$H$7)
B8: SUB-LEAD SCHEDULE
B9: Work performed
B10: Analytical Procedures:
B11: Assessed the appropriateness of purchases and consumptions method and rate in view of the flow of economic benefits.
B12: Checked the reasonableness of consumption allocated to inventories at different stages.
B13: Documented logical commercial reasons for purchases and consumption made during the year.
B14: Checked the appropriateness of compilation of overheads and allocation basis of the same to different products.
B16: Test of Details:
B17: Observed physical counting of inventories carried out by the client (at year-end or at any other date).
B18: Perform tests of intervening transactions to ensure existence and conditions (unless impracticable).
B19: Also checked on sample basis some items to ensure reliability. (Sample Attached)
B20: Obtain final inventory compilation schedule and perform the following:
... B32: Satisfactory
B34: Description | E34: W.P. Ref. | G34: =Lead!G26 -> 2022 | H34: =Lead!H26 -> 2021 | I34: Variance | J34: Variance | K34: Reason for Variance
G35: Rupees | H35: Rupees | I35: Rupees | J35: %
B37: =Lead!B31 -> Packing Material
B38: Opening balance | I38: =G38-H38 -> 0 | J38: =IFERROR(I38/H38,"")
B39: Add: Purchases during the year | I39: =G39-H39 -> 0 | J39: =IFERROR(I39/H39,"")
B40: Less: Consumed during the year | I40: =G40-H40 -> 0 | J40: =IFERROR(I40/H40,"")
B42: Total closing balance | G42: =SUM(G38:G41) -> 0 | H42: =SUM(H38:H41) -> 0 | I42: =SUM(I38:I41) -> 0

Sheet SubLead-WIP
B1: =Index!$B$1 -> ABC & Co. | K1: =Index!E16 -> BS.08 - 3
B2: =Index!$B$2 -> (Chartered Accountants)
B4: =Index!$B$4 -> Client: | C4: =Index!$C$4 -> ABC Limited | J4: =Index!$G$4 -> Prepared by: | K4: =IF(Index!$H$4="","",Index!$H$4)
B5: =Index!$B$5 -> Period: | C5: =Index!$C$5 -> Year ended June 30, 2023 | J5: =Index!$G$5 -> Date prepared: | K5: =IF(Index!$H$5="","",Index!$H$5)
B6: =Index!$B$6 -> Head: | C6: =Index!$C$6 -> Stock in Trade | J6: =Index!$G$6 -> Reviewed by: | K6: =IF(Index!$H$6="","",Index!$H$6)
J7: =Index!$G$7 -> Date reviewed: | K7: =IF(Index!$H$7="","",Index!$H$7)
B8: SUB-LEAD SCHEDULE
B9: Work performed
B10: Analytical Procedures:
B11: Assessed the appropriateness of purchases and consumptions method and rate in view of the flow of economic benefits.
B12: Checked the reasonableness of consumption allocated to inventories at different stages.
B13: Documented logical commercial reasons for purchases and consumption made during the year.
B14: Checked the appropriateness of compilation of overheads and allocation basis of the same to different products.
B16: Test of Details:
B17: Observed physical counting of inventories carried out by the client (at year-end or at any other date).
B18: Perform tests of intervening transactions to ensure existence and conditions (unless impracticable).
B19: Also checked on sample basis some items to ensure reliability. (Sample Attached)
B20: Checked that third party inventories are identified and excluded from physical count.
... B35: Satisfactory
B37: Description | E37: W.P. Ref. | G37: ='SubLead-PackingMaterial'!G34 -> 2022 | H37: ='SubLead-PackingMaterial'!H34 -> 2021 | I37: Variance | J37: Variance | K37: Reason for Variance
G38: Rupees | H38: Rupees | I38: Rupees | J38: %
B40: =Lead!B32 -> Work in Process
B41: Opening balance | I41: =G41-H41 -> 0 | J41: =IFERROR(I41/H41,"")
B42: Add: Purchases during the year | I42: =G42-H42 -> 0 | J42: =IFERROR(I42/H42,"")
B43: Less: Issued to production during the year | I43: =G43-H43 -> 0 | J43: =IFERROR(I43/H43,"")
B45: Total closing balance | G45: =SUM(G41:G44) -> 0 | H45: =SUM(H41:H44) -> 0 | I45: =SUM(I41:I44) -> 0

Sheet SubLead-FinishedGoods
B1: =Index!$B$1 -> ABC & Co. | K1: =Index!E16 -> BS.08 - 3
B2: =Index!$B$2 -> (Chartered Accountants)
B4: =Index!$B$4 -> Client: | C4: =Index!$C$4 -> ABC Limited | J4: =Index!$G$4 -> Prepared by: | K4: =IF(Index!$H$4="","",Index!$H$4)
B5: =Index!$B$5 -> Period: | C5: =Index!$C$5 -> Year ended June 30, 2023 | J5: =Index!$G$5 -> Date prepared: | K5: =IF(Index!$H$5="","",Index!$H$5)
B6: =Index!$B$6 -> Head: | C6: =Index!$C$6 -> Stock in Trade | J6: =Index!$G$6 -> Reviewed by: | K6: =IF(Index!$H$6="","",Index!$H$6)
J7: =Index!$G$7 -> Date reviewed: | K7: =IF(Index!$H$7="","",Index!$H$7)
B8: SUB-LEAD SCHEDULE
B9: Work performed
B10: Analytical Procedures:
B11: Assessed the appropriateness of consumptions of Raw Material and production of Finished Goods in agreement with the Standards of Production.
B12: Checked the appropriateness of compilation of overheads and allocation basis of the same to different products.
B14: Test of Details:
B15: Observed physical counting of inventories carried out by the client (at year-end or at any other date).
B16: Perform tests of intervening transactions to ensure existence and conditions (unless impracticable).
B17: Also checked on sample basis some items to ensure reliability. (Sample Attached)
B18: Checked that third party inventories are identified and excluded from physical count.
B19: For items owned by client but not physically held, obtained independent confirmations from custodians.
B20: Obtain final inventory compilation schedule and perform the following:
... B35: Satisfactory
B37: Description | E37: W.P. Ref. | G37: =Lead!G26 -> 2022 | H37: =Lead!H26 -> 2021 | I37: Variance | J37: Variance | K37: Reason for Variance
G38: Rupees | H38: Rupees | I38: Rupees | J38: %
B40: =Lead!B33 -> Finished Goods
B41: Opening balance | I41: =G41-H41 -> 0 | J41: =IFERROR(I41/H41,"")
B42: Add: Production during the year | I42: =G42-H42 -> 0 | J42: =IFERROR(I42/H42,"")
B43: Less: Sold during the year | I43: =G43-H43 -> 0 | J43: =IFERROR(I43/H43,"")
B45: Total closing balance | G45: =SUM(G41:G44) -> 0 | H45: =SUM(H41:H44) -> 0 | I45: =SUM(I41:I44) -> 0

Sheet Vouching-Additions
B1: =Index!$B$1 -> ABC & Co. | I1: =Index!E18 -> BS.08 - 4
B2: =Index!$B$2 -> (Chartered Accountants)
B4: =Index!$B$4 -> Client: | C4: =Index!$C$4 -> ABC Limited | H4: =Index!$G$4 -> Prepared by: | I4: =IF(Index!$H$4="","",Index!$H$4)
B5: =Index!$B$5 -> Period: | C5: =Index!$C$5 -> Year ended June 30, 2023 | H5: =Index!$G$5 -> Date prepared: | I5: =IF(Index!$H$5="","",Index!$H$5)
B6: =Index!$B$6 -> Head: | C6: =Index!$C$6 -> Stock in Trade | H6: =Index!$G$6 -> Reviewed by: | I6: =IF(Index!$H$6="","",Index!$H$6)
B7: Subhead: | H7: =Index!$G$7 -> Date reviewed: | I7: =IF(Index!$H$7="","",Index!$H$7)
B8: VOUCHING - ADDITIONS
B9: Work performed
B11: Date | C11: Voucher # | D11: Description | E11: Approved By | F11: Cheque # | G11: Amount | H11: Traced into Bank Statement | I11: Proper Classification

Sheet Impairnment
B1: =Index!$B$1 -> ABC & Co. | I1: =Index!E24 -> BS.08 - 7
B2: =Index!$B$2 -> (Chartered Accountants)
B4: =Index!$B$4 -> Client: | C4: =Index!$C$4 -> ABC Limited | H4: =Index!$G$4 -> Prepared by: | I4: =IF(Index!$H$4="","",Index!$H$4)
B5: =Index!$B$5 -> Period: | C5: =Index!$C$5 -> Year ended June 30, 2023 | H5: =Index!$G$5 -> Date prepared: | I5: =IF(Index!$H$5="","",Index!$H$5)
B6: =Index!$B$6 -> Head: | C6: =Index!$C$6 -> Stock in Trade | H6: =Index!$G$6 -> Reviewed by: | I6: =IF(Index!$H$6="","",Index!$H$6)
H7: =Index!$G$7 -> Date reviewed: | I7: =IF(Index!$H$7="","",Index!$H$7)
B8: IMPAIRNMENT TESTING
B9: Work performed
B10: Obtained age-analysis of Stock in trade and verified that stock in trade had been classified in correct categories.
B11: Ensured that none of the stock in trade is impaired or the recoverable amount of same is not less than its carrying amount.
B12: If the carrying amount of stock in trade is more than its recoverable amount, then same should be reduced to recoverable amount.
B13: The reduction is recognised as impairment loss.
B15: Observations
B16: None.
B18: Conclusion
B19: Satisfactory
B21: Description | D21: Amount | E21: Ageing | I21: Subsequent Position
E22: 0 - 1 year | F22: 1 - 2 year | G22: 2 - 3 years | H22: More than 3 years

Sheet Adjusting Entries
B1: =Index!$B$1 -> ABC & Co. | E1: =Index!E26 -> BS.08 - 8
B2: =Index!$B$2 -> (Chartered Accountants)
B4: =Index!$B$4 -> Client: | C4: =Index!$C$4 -> ABC Limited | D4: =Index!$G$4 -> Prepared by: | E4: =IF(Index!$H$4="","",Index!$H$4)
B5: =Index!$B$5 -> Period: | C5: =Index!$C$5 -> Year ended June 30, 2023 | D5: =Index!$G$5 -> Date prepared: | E5: =IF(Index!$H$5="","",Index!$H$5)
B6: =Index!$B$6 -> Head: | C6: =Index!$C$6 -> Stock in Trade | D6: =Index!$G$6 -> Reviewed by: | E6: =IF(Index!$H$6="","",Index!$H$6)
D7: =Index!$G$7 -> Date reviewed: | E7: =IF(Index!$H$7="","",Index!$H$7)
B8: ADJUSTING ENTRIES
B10: Sr. # | C10: Entry Proposed | D10: Amount
D11: Debit | E11: Credit
