Workbook

Sheet Index
B1: ABC & Co. | J1: BS.05
B2: (Chartered Accountants)
B4: Client: | D4: ABC Limited | H4: Prepared by:
B5: Period: | D5: Year ended June 30, 2023 | H5: Date prepared:
B6: Head: | D6: Long term loans and advances | H6: Reviewed by:
H7: Date reviewed:
B8: INDEX
B10: Sr. # | D10: Description | F10: W.P. Ref. | H10: Whether Placed in File | J10: Initials of Reviewer
B12: 1 | D12: Audit Objectives and Conclusions | F12: =$J$1&" - "&B12 -> BS.05 - 1
B14: =B12+1 -> 2 | D14: Lead Schedule | F14: =$J$1&" - "&B14 -> BS.05 - 2
B16: =B14+1 -> 3 | D16: Sub-Lead Schedule | F16: =$J$1&" - "&B16 -> BS.05 - 3
B18: =B16+1 -> 4 | D18: Vouching - Additions | F18: =$J$1&" - "&B18 -> BS.05 - 4
B20: =B18+1 -> 5 | D20: Vouching - Deletions | F20: =$J$1&" - "&B20 -> BS.05 - 5
B22: =B20+1 -> 6 | D22: Confirmation summary, reconciliation | F22: =$J$1&" - "&B22 -> BS.05 - 6
B24: =B22+1 -> 7 | D24: Copies of Documents/Summary | F24: =$J$1&" - "&B24 -> BS.05 - 7
B26: =B24+1 -> 8 | D26: Impairment Testing | F26: =$J$1&" - "&B26 -> BS.05 - 8
B28: =B26+1 -> 9 | D28: Adjusting Entries | F28: =$J$1&" - "&B28 -> BS.05 - 9

Sheet AOC
B1: =Index!B1 -> ABC & Co. | G1: =Index!F12 -> BS.05 - 1
B2: =Index!B2 -> (Chartered Accountants)
B4: =Index!B4 -> Client: | D4: =Index!D4 -> ABC Limited | F4: =Index!$H$4 -> Prepared by: | G4: =IF(Index!$J$4="","",Index!$J$4)
B5: =Index!B5 -> Period: | D5: =Index!D5 -> Year ended June 30, 2023 | F5: =Index!$H$5 -> Date prepared: | G5: =IF(Index!$J$5="","",Index!$J$5)
B6: =Index!B6 -> Head: | D6: =Index!D6 -> Long term loans and advances | F6: =Index!$H$6 -> Reviewed by: | G6: =IF(Index!$J$6="","",Index!$J$6)
F7: =Index!$H$7 -> Date reviewed: | G7: =IF(Index!$J$7="","",Index!$J$7)
B8: =UPPER("Audit Objectives and Conclusions") -> AUDIT OBJECTIVES AND CONCLUSIONS
B10: Sr. # | D10: Audit Objectives | F10: Objective Met
F11: Yes/No | G11: Initials
B13: 1 | D13: Long term loans and advances are completely and accurately recorded
B14: =B13+1 -> 2 | D14: All recorded long term loans and advances actually exist
B15: =B14+1 -> 3 | D15: Long term loans and advances are recorded at appropriate values and all bad and doubtful balances have been provided for/ written off
B16: =B15+1 -> 4 | D16: Long term loans and advances recorded are the right of the company
B17: =B16+1 -> 5 | D17: Long-term loans and advances to associated undertaking were in accordance with legal requirements
B18: =B17+1 -> 6 | D18: Long term loans and advances are presented and all disclosures have been given in accordance with the Fifth Schedule of the Companies Act, 2017 and relevant IASs/IFRSs.
B21: Sr. # | D21: Conclusion | F21: Satisfactory
F22: Yes/No | G22: Initials
B24: 1 | D24: The audit has been completed in accordance with Audit program.
B25: =B24+1 -> 2 | D25: The working papers demonstrate that adequate work has been undertaken.
B26: =B25+1 -> 3 | D26: The working papers contain sufficient information, details of significant features and notes of unusual matters to enable us to form an opinion on financial statements.
B27: =B26+1 -> 4 | D27: In my opinion above amounts are fairly stated and on a consistent basis with the previous period.

Sheet Lead
B1: =Index!$B$1 -> ABC & Co. | M1: =Index!F14 -> BS.05 - 2
B2: =Index!$B$2 -> (Chartered Accountants)
B4: Client: | C4: =Index!$D$4 -> ABC Limited | K4: =Index!$H$4 -> Prepared by: | M4: =IF(Index!$J$4="","",Index!$J$4)
B5: Period: | C5: =Index!$D$5 -> Year ended June 30, 2023 | K5: =Index!$H$5 -> Date prepared: | M5: =IF(Index!$J$5="","",Index!$J$5)
B6: Head: | C6: =Index!$D$6 -> Long term loans and advances | K6: =Index!$H$6 -> Reviewed by: | M6: =IF(Index!$J$6="","",Index!$J$6)
K7: =Index!$H$7 -> Date reviewed: | M7: =IF(Index!$J$7="","",Index!$J$7)
B8: LEAD SCHEDULE
B9: Work performed
B10: Analytical Procedures:
B11: Compared current year balances with last year balances and ensured that any significant variation has been properly and logically reasoned.
B13: Test of Details
B14: Ensured that closing balances as per our working paper file are matched with general ledger.
B15: Determined that disclosures have been made in accordance with the requirements of Fifth Schedule to the Companies Act, 2017 and the applicable IASs/IFRSs.
B17: Observations
B18: None.
B20: Conclusion
B21: Satisfactory
B24: Description | E24: W.P. Ref. | G24: 2022 | H24: 2021 | J24: Variance | K24: Variance | M24: Reason for Variance
G25: Rupees | H25: Rupees | J25: Rupees | K25: %
B27: =C6 -> Long term loans and advances
B28: - In Subsidiary Companies | J28: =G28-H28 -> 0 | K28: =IFERROR(J28/H28,"")
B29: - In Controlled Firms | J29: =G29-H29 -> 0 | K29: =IFERROR(J29/H29,"")
B30: - In Managed Modarabas | J30: =G30-H30 -> 0 | K30: =IFERROR(J30/H30,"")
B31: - Other Associated Undertakings | J31: =G31-H31 -> 0 | K31: =IFERROR(J31/H31,"")
B35: T O T A L | G35: =SUM(G26:G34) -> 0 | H35: =SUM(H26:H33) -> 0 | J35: =SUM(J26:J33) -> 0

Sheet SubLead
B1: =Index!$B$1 -> ABC & Co. | M1: =Index!F16 -> BS.05 - 3
B2: =Index!$B$2 -> (Chartered Accountants)
B4: Client: | C4: =Index!$D$4 -> ABC Limited | K4: =Index!$H$4 -> Prepared by: | M4: =IF(Index!$J$4="","",Index!$J$4)
B5: Period: | C5: =Index!$D$5 -> Year ended June 30, 2023 | K5: =Index!$H$5 -> Date prepared: | M5: =IF(Index!$J$5="","",Index!$J$5)
B6: Head: | C6: =Index!$D$6 -> Long term loans and advances | K6: =Index!$H$6 -> Reviewed by: | M6: =IF(Index!$J$6="","",Index!$J$6)
K7: =Index!$H$7 -> Date reviewed: | M7: =IF(Index!$J$7="","",Index!$J$7)
B8: SUB-LEAD SCHEDULE
B9: Work performed
B10: Test of Details
B11: For disbursements made during the year checked disbursements of funds with disbursement register and bank statement
B12: For a sample of repayments made during the year:
B13: (a) Ensured that amount and date of repayment was accordance with repayment schedule or agreement.
B14: (b) Checked receipt of funds with receipt records and bank statement.
B15: (c) Checked the recovery of interest is in accordance with the policy (i.e. along with principal or after recovery of full principal, as the case may be)
B16: Circularized confirmations to selected parties. Matched replies with the amounts outstanding against each party
B17: Obtained age-analysis of long-term loans and advances and perform the following:
B18: (a) Verified that loans have been classified in correct categories.
B19: (b) Current maturity has been appropriately calculated and separately disclosed.
... B38: Satisfactory
B40: Description | E40: W.P. Ref. | G40: =Lead!G24 -> 2022 | H40: =Lead!H24 -> 2021 | J40: Variance | K40: Variance | M40: Reason for Variance
G41: Rupees | H41: Rupees | J41: Rupees | K41: %
B43: =Lead!B28 -> - In Subsidiary Companies | J43: =G43-H43 -> 0 | K43: =IFERROR(J43/H43,"")
B44: Opening balance | J44: =G44-H44 -> 0 | K44: =IFERROR(J44/H44,"")
B45: Add: Disbursement during the year | J45: =G45-H45 -> 0 | K45: =IFERROR(J45/H45,"")
B46: Less: Repayments during the year | J46: =G46-H46 -> 0 | K46: =IFERROR(J46/H46,"")
B54: Total closing balance | G54: =G52+G47 -> 0 | H54: =H52+H47 -> 0 | J54: =J52+J47 -> 0

Sheet Vouching-Additions
B1: =Index!$B$1 -> ABC & Co. | I1: =Index!F18 -> BS.05 - 4
B2: =Index!$B$2 -> (Chartered Accountants)
B4: Client: | C4: =Index!$D$4 -> ABC Limited | H4: =Index!$H$4 -> Prepared by: | I4: =IF(Index!$J$4="","",Index!$J$4)
B5: Period: | C5: =Index!$D$5 -> Year ended June 30, 2023 | H5: =Index!$H$5 -> Date prepared: | I5: =IF(Index!$J$5="","",Index!$J$5)
B6: Head: | C6: =Index!$D$6 -> Long term loans and advances | H6: =Index!$H$6 -> Reviewed by: | I6: =IF(Index!$J$6="","",Index!$J$6)
B7: Subhead: | H7: =Index!$H$7 -> Date reviewed: | I7: =IF(Index!$J$7="","",Index!$J$7)
B9: VOUCHING - ADDITIONS
B11: Work performed
B28: Date | C28: Voucher # | D28: Description | E28: Approved By | F28: Cheque # | G28: Amount | H28: Traced into Bank Statement | I28: Proper Classification

Sheet Vouching-Deletion
B1: =Index!$B$1 -> ABC & Co. | I1: =Index!F18 -> BS.05 - 4
B2: =Index!$B$2 -> (Chartered Accountants)
B4: Client: | C4: =Index!$D$4 -> ABC Limited | H4: =Index!$H$4 -> Prepared by: | I4: =IF(Index!$J$4="","",Index!$J$4)
B5: Period: | C5: =Index!$D$5 -> Year ended June 30, 2023 | H5: =Index!$H$5 -> Date prepared: | I5: =IF(Index!$J$5="","",Index!$J$5)
B6: Head: | C6: =Index!$D$6 -> Long term loans and advances | H6: =Index!$H$6 -> Reviewed by: | I6: =IF(Index!$J$6="","",Index!$J$6)
B7: Subhead: | H7: =Index!$H$7 -> Date reviewed: | I7: =IF(Index!$J$7="","",Index!$J$7)
B9: VOUCHING - DELETIONS
B11: Work performed
B24: Date | C24: Voucher # | D24: Description | E24: Approved By | F24: Cheque # | G24: Amount | H24: Traced into Bank Statement | I24: Proper Classification

Sheet Impairnment
B1: =Index!$B$1 -> ABC & Co. | I1: =Index!F26 -> BS.05 - 8
B2: =Index!$B$2 -> (Chartered Accountants)
B4: Client: | C4: =Index!$D$4 -> ABC Limited | H4: =Index!$H$4 -> Prepared by: | I4: =IF(Index!$J$4="","",Index!$J$4)
B5: Period: | C5: =Index!$D$5 -> Year ended June 30, 2023 | H5: =Index!$H$5 -> Date prepared: | I5: =IF(Index!$J$5="","",Index!$J$5)
B6: Head: | C6: =Index!$D$6 -> Long term loans and advances | H6: =Index!$H$6 -> Reviewed by: | I6: =IF(Index!$J$6="","",Index!$J$6)
H7: =Index!$H$7 -> Date reviewed: | I7: =IF(Index!$J$7="","",Index!$J$7)
B8: IMPAIRNMENT TESTING
B10: Work performed
B11: Obtained age-analysis of long-term loans and advances and performed the following:
B12: (a) Verified that loans and advances had been classified in correct categories.
B13: (b) Current maturity had been appropriately identified and separately disclosed
B14: Ensured that none of the loans and advances are impaired or the recoverable amount of same is not less than its carrying amount.
B16: Point discussed with the engagement team: What if the carrying amount of loans and advances is more than its recoverable amount?
B17: In that case, same should be reduced to recoverable amount. The reduction is recognized as impairment loss.
B19: Observations
B20: None.
B22: Conclusion
B23: Satisfactory
B25: Description | D25: Amount | E25: Ageing | I25: Subsequent Position
E26: 0 - 1 year | F26: 1 - 2 year | G26: 2 - 3 years | H26: More than 3 years

Sheet Adjusting Entries
B1: =Index!$B$1 -> ABC & Co. | E1: =Index!F28 -> BS.05 - 9
B2: =Index!$B$2 -> (Chartered Accountants)
B4: Client: | C4: =Index!$D$4 -> ABC Limited | D4: =Index!$H$4 -> Prepared by: | E4: =IF(Index!$J$4="","",Index!$J$4)
B5: Period: | C5: =Index!$D$5 -> Year ended June 30, 2023 | D5: =Index!$H$5 -> Date prepared: | E5: =IF(Index!$J$5="","",Index!$J$5)
B6: Head: | C6: =Index!$D$6 -> Long term loans and advances | D6: =Index!$H$6 -> Reviewed by: | E6: =IF(Index!$J$6="","",Index!$J$6)
D7: =Index!$H$7 -> Date reviewed: | E7: =IF(Index!$J$7="","",Index!$J$7)
B8: ADJUSTING ENTRIES
B10: Sr. # | C10: Entry Proposed | D10: Amount
D11: Debit | E11: Credit
