Workbook

Sheet Index
B1: ABC & Co. | J1: B.S.01
B2: (Chartered Accountants)
B4: Client: | D4: ABC Limited | H4: Prepared by:
B5: Period: | D5: Year ended June 30, 2023 | H5: Date prepared:
B6: Head: | D6: Property, plant and equipment | H6: Reviewed by:
H7: Date reviewed:
B8: INDEX
B10: Sr. # | D10: Description | F10: W.P. Ref. | H10: Whether Placed in File | J10: Initials of Reviewer
B12: 1 | D12: Audit Objectives and Conclusions | F12: =$J$1&" - "&B12 -> B.S.01 - 1
B14: =B12+1 -> 2 | D14: Lead Schedule | F14: =$J$1&" - "&B14 -> B.S.01 - 2
B16: =B14+1 -> 3 | D16: Sub-Lead Schedule | F16: =$J$1&" - "&B16 -> B.S.01 - 3
B18: =B16+1 -> 4 | D18: Test of Controls | F18: =$J$1&" - "&B18 -> B.S.01 - 4
B20: =B18+1 -> 5 | D20: Asset's Physical Verification | F20: =$J$1&" - "&B20 -> B.S.01 - 5
B22: =B20+1 -> 6 | D22: Vouching for Additions | F22: =$J$1&" - "&B22 -> B.S.01 - 6
B24: =B22+1 -> 7 | D24: Vouching for Disposals | F24: =$J$1&" - "&B24 -> B.S.01 - 7
B26: =B24+1 -> 8 | D26: Recalculation of Depreciation Working | F26: =$J$1&" - "&B26 -> B.S.01 - 8
B28: =B26+1 -> 9 | D28: Vouching for CWIP | F28: =$J$1&" - "&B28 -> B.S.01 - 9
B30: =B28+1 -> 10 | D30: Adjusting Entries | F30: =$J$1&" - "&B30 -> B.S.01 - 10

Sheet AOC
B1: =Index!$B$1 -> ABC & Co. | G1: =Index!F12 -> B.S.01 - 1
B2: =Index!$B$2 -> (Chartered Accountants)
B4: =Index!B4 -> Client: | D4: =Index!$D$4 -> ABC Limited | F4: =Index!$H$4 -> Prepared by: | G4: =IF(Index!$J$4="","",Index!$J$4)
B5: =Index!B5 -> Period: | D5: =Index!$D$5 -> Year ended June 30, 2023 | F5: =Index!$H$5 -> Date prepared: | G5: =IF(Index!$J$5="","",Index!$J$5)
B6: =Index!B6 -> Head: | D6: =Index!$D$6 -> Property, plant and equipment | F6: =Index!$H$6 -> Reviewed by: | G6: =IF(Index!$J$6="","",Index!$J$6)
F7: =Index!$H$7 -> Date reviewed: | G7: =IF(Index!$J$7="","",Index!$J$7)
B8: =UPPER("Audit Objectives and Conclusions") -> AUDIT OBJECTIVES AND CONCLUSIONS
B10: Sr. # | D10: Audit Objectives | F10: Objective Met
F11: Yes/No | G11: Initials
B13: =B12+1 -> 1 | D13: Fixed assets are completely and accurately recorded.
B14: =B13+1 -> 2 | D14: All recorded fixed assets actually exist.
B15: =B14+1 -> 3 | D15: Fixed assets are recorded at appropriate values.
B16: =B15+1 -> 4 | D16: Fixed assets recorded are owned by the client and title is also in the name of client.
B17: =B16+1 -> 5 | D17: Depreciation/impairment expense and gain/ loss on disposal has been accurately calculated and appropriately disclosed.
B18: =B17+1 -> 6 | D18: Fixed assets are presented and all disclosures have been given in accordance with the Fifth Schedule of the Companies Act, 2017 and relevant IASs / IFRSs.
B21: Sr. # | D21: Conclusion | F21: Satisfactory
F22: Yes/No | G22: Initials
B24: =B23+1 -> 1 | D24: The audit has been completed in accordance with Audit program.
B25: =B24+1 -> 2 | D25: The working papers demonstrate that adequate work has been undertaken.
B26: =B25+1 -> 3 | D26: The working papers contain sufficient information, details of significant features and notes of unusual matters to enable us to form an opinion on financial statements.
B27: =B26+1 -> 4 | D27: In my opinion above amounts are fairly stated and on a consistent basis with the previous period.

Sheet Lead
B1: =Index!B1 -> ABC & Co. | M1: =Index!F14 -> B.S.01 - 2
B2: =Index!B2 -> (Chartered Accountants)
B4: Client: | C4: =Index!D4 -> ABC Limited | K4: =Index!$H$4 -> Prepared by: | M4: =IF(Index!$J$4="","",Index!$J$4)
B5: Period: | C5: =Index!D5 -> Year ended June 30, 2023 | K5: =Index!$H$5 -> Date prepared: | M5: =IF(Index!$J$5="","",Index!$J$5)
B6: Head: | C6: =Index!D6 -> Property, plant and equipment | K6: =Index!$H$6 -> Reviewed by: | M6: =IF(Index!$J$6="","",Index!$J$6)
K7: =Index!$H$7 -> Date reviewed: | M7: =IF(Index!$J$7="","",Index!$J$7)
B8: LEAD SCHEDULE
B10: Work performed
B11: Analytical Procedures:
B12: Compared current year balances with last year balances and ensured that any significant variation has been properly and logically reasoned.
B13: Test of Details
B14: Traced opening balances from fixed assets register, general ledger and last year’s working papers.
B15: Ensured that closing balances as per our working paper file are in match with closing balance as per general ledger.
B16: Determined and ensured that disclosures have been made in accordance with the requirements of Fifth Schedule to the Companies Act, 2017 and the applicable IASs / IFRSs.
B19: Observations
B20: None.
B22: Conclusion
B23: Satisfactory
B25: Description | E25: W.P. Ref. | G25: 2023 | H25: =G25-1 -> 2022 | J25: Variance | K25: Variance | M25: Reason for Variance
G26: Rupees | H26: Rupees | J26: Rupees | K26: %
B28: =C6 -> Property, plant and equipment
B29: Operating fixed assets | E29: =SubLead!T1 -> B.S.01 - 3 | J29: =G29-H29 -> 0 | K29: =IFERROR(J29/H29,"")
B30: Capital work in progress | E30: ='Vouching-CWIP.'!Z1 -> B.S.01 - 9 | J30: =G30-H30 -> 0 | K30: =IFERROR(J30/H30,"")
B40: Total | G40: =SUM(G27:G39) -> 0 | H40: =SUM(H27:H38) -> 0 | J40: =SUM(J27:J38) -> 0

Sheet SubLead
B1: =Index!B1 -> ABC & Co. | T1: =Index!F16 -> B.S.01 - 3
B2: =Index!B2 -> (Chartered Accountants)
B4: Client: | C4: =Index!D4 -> ABC Limited | R4: =Index!$H$4 -> Prepared by: | T4: =IF(Index!$J$4="","",Index!$J$4)
B5: Period: | C5: =Index!D5 -> Year ended June 30, 2023 | R5: =Index!$H$5 -> Date prepared: | T5: =IF(Index!$J$5="","",Index!$J$5)
B6: Head: | C6: =Index!D6 -> Property, plant and equipment | R6: =Index!$H$6 -> Reviewed by: | T6: =IF(Index!$J$6="","",Index!$J$6)
B7: Sub Head: | C7: =Lead!B29 -> Operating fixed assets | R7: =Index!$H$7 -> Date reviewed: | T7: =IF(Index!$J$7="","",Index!$J$7)
B9: SUB-LEAD SCHEDULE
B11: Work Performed
B12: Test of Details
B13: Obtained movement schedule of operating fixed assets and Capital work-in-progress both for cost, accumulated depreciation and impairment.
B14: Performed casting and cross casting of the schedule.
B15: Document logical commercial reasons for major additions and disposal made during the year and check whether the additions are in accordance with the objects of the company.
B17: For Revalued Assets
B18: Entire class of assets had been revalued on periodical basis.
B19: Ensures that revalued amount and incremental depreciation has been recognized in other comprehensive income.
B20: Any asset's revaluation results in deficit should not be adjusted against other assets' surplus but should be immediately charged.
B22: Observations
B23: None.
... B26: Satisfactory
G28: Owned Assets | Q28: Leased Assets | T28: Total Assets
E29: W.P. Ref. | G29: Land - freehold | H29: Building - freehold | I29: Plant and Machinery | J29: Electric Installation | K29: Tools and Equipment | L29: Furniture and Fixtures | M29: Office Equipment | N29: Computers and Peripherals | O29: Vehicle | Q29: Plant and Machinery | R29: Vehicle
G30: ---------------------------------------- Rupees ----------------------------------------
B32: Cost | C32: Opening balance | E32: ='Depreciation-Working'!Q1 -> B.S.01 - 8 | T32: =SUM(G32:R32) -> 0
C33: Additions during the period | E33: ='Additions-Vouching'!AA1 -> B.S.01 - 6 | T33: =SUM(G33:R33) -> 0
C34: Disposals during the period | E34: ='Disposals-Vouching'!V1 -> B.S.01 - 7 | T34: =SUM(G34:R34) -> 0
C35: Closing balance | E35: =E32 -> B.S.01 - 8 | T35: =SUM(G35:R35) -> 0
B37: Depreciation | C37: Opening balance | E37: =E32 -> B.S.01 - 8 | T37: =SUM(G37:R37) -> 0
C38: Expense for the period | E38: =E37 -> B.S.01 - 8 | T38: =SUM(G38:R38) -> 0
C39: Disposals during the period | E39: ='Disposals-Vouching'!V1 -> B.S.01 - 7 | T39: =SUM(G39:R39) -> 0
C40: Closing balance | E40: =E37 -> B.S.01 - 8 | T40: =SUM(G40:R40) -> 0
B42: Opening Net Book Value | E42: ='Depreciation-Working'!Q1 -> B.S.01 - 8 | G42: =G32-G37 -> 0 | H42: =H32-H37 -> 0 | I42: =I32-I37 -> 0 | J42: =J32-J37 -> 0 | K42: =K32-K37 -> 0 | L42: =L32-L37 -> 0 | M42: =M32-M37 -> 0 | N42: =N32-N37 -> 0 | O42: =O32-O37 -> 0 | Q42: =Q32-Q37 -> 0 | R42: =R32-R37 -> 0 | T42: =SUM(G42:R42) -> 0
B44: Closing Net Book Value | E44: =E42 -> B.S.01 - 8 | G44: =G35-G40 -> 0 | H44: =H35-H40 -> 0 | I44: =I35-I40 -> 0 | J44: =J35-J40 -> 0 | K44: =K35-K40 -> 0 | L44: =L35-L40 -> 0 | M44: =M35-M40 -> 0 | N44: =N35-N40 -> 0 | O44: =O35-O40 -> 0 | Q44: =Q35-Q40 -> 0 | R44: =R35-R40 -> 0 | T44: =SUM(G44:R44) -> 0
T46: =Lead!M1 -> B.S.01 - 2

Sheet TOCs
B1: =Index!B1 -> ABC & Co. | W1: =Index!F18 -> B.S.01 - 4
B2: =Index!B2 -> (Chartered Accountants)
B4: Client: | C4: =Index!D4 -> ABC Limited | V4: =Index!$H$4 -> Prepared by: | W4: M. Basit
B5: Period: | C5: =Index!D5 -> Year ended June 30, 2023 | V5: =Index!$H$5 -> Date prepared: | W5: =IF(Index!$J$5="","",Index!$J$5)
B6: Head: | C6: =Index!D6 -> Property, plant and equipment | V6: =Index!$H$6 -> Reviewed by: | W6: A. Arif
V7: =Index!$H$7 -> Date reviewed: | W7: =IF(Index!$J$7="","",Index!$J$7)
B8: Evaluation of Controls
B10: Work Performed
B11: Assessed the reasonableness of design of system of internal control by enquiring relevant client personnel and documenting the same.
B12: To ensure that expenditure is properly authorised, we:
B13: Reviewed policies and procedures in place for addition & disposal.
B14: Examined a sample of additions & disposal to check for approval from at appropriate level of management.
B15: Checked whether quotations were obtained from approved list of suppliers.
B16: Checked for approval of quotations from senior management..
B17: Inspected whether invoices are approved by respected personnel.
B18: To ensure that all assets are correctly recorded, we:
B19: Ensured that enteries are made properly in Fixed asset register.
B20: Ensured that CWIP is valued properly.
... B29: To ensure that expenditure is correctly classified as capital expenditure, we:
B30: 1 | C30: Reviewed entries for recorded assets.
B31: =B30+1 -> 2 | C31: Reviewed authorization for acquisition.
B32: =B31+1 -> 3 | C32: Reviewed expenditure policy for self construction.
B33: =B32+1 -> 4 | C33: Reviewed policy for Identification of individual asset.
B34: =B33+1 -> 5 | C34: Reviewed safeguard from theft and misuse of assets.
B35: =B34+1 -> 6 | C35: Discussed capitalization or expenses policy.
B36: =B35+1 -> 7 | C36: Reviewed depreciation method and detailed record.
B37: =B36+1 -> 8 | C37: Reviewed adequacy of insurance for assets.
B38: =B37+1 -> 9 | C38: Reviewed authorization for retirement and sale of assset.
B39: =B38+1 -> 10 | C39: Reviewed controls over fully depreciated assets.
B40: =B39+1 -> 11 | C40: Checked the capital/revenue analysis of invoices.
B42: Observations
B43: None.
B45: Conclusion
B46: Satisfactory
J48: Purchase order | N48: Invoice | R48: GRN approved by
B49: Date | C49: Voucher # | D49: Description | E49: Quantity | F49: Amount Vertified | G49: Purchase Requisition # | H49: Approved supplier list maintained? | I49: Quotation Reference | J49: Prepared by | K49: Approved by Manger | L49: Approved by Accountant | M49: Authorised by Director | N49: Invoice # | O49: Invoices sequentially numbered? | P49: Quantity matched with PO & GRN | Q49: GRN # / GIN # | R49: Store Supervisor | S49: Store Manager | T49: Proper posting in GL (Yes / No) | U49: Reconciliation of Payments with A/P (Yes / No) | V49: Purchase reconciled with Inventory Change (Yes / No) | W49: Updated Agreement in Place (Yes / No)

Sheet Sampling-Physical-Inspection
B1: =Index!B1 -> ABC & Co. | J1: =Index!F20 -> B.S.01 - 5
B2: =Index!B2 -> (Chartered Accountants)
B4: Client: | C4: =Index!D4 -> ABC Limited | I4: =Index!$H$4 -> Prepared by: | J4: M. Basit
B5: Period: | C5: =Index!D5 -> Year ended June 30, 2023 | I5: =Index!$H$5 -> Date prepared: | J5: =IF(Index!$J$5="","",Index!$J$5)
B6: Head: | C6: =Index!D6 -> Property, plant and equipment | I6: =Index!$H$6 -> Reviewed by: | J6: A. Arif
B7: Sub Head: | C7: =Lead!B29 -> Operating fixed assets | I7: =Index!$H$7 -> Date reviewed: | J7: =IF(Index!$J$7="","",Index!$J$7)
B9: ASSET'S PHYSICAL VERIFICATION
B11: Performance of Physical Inspection
B13: To ensure existence and verification of ownership of fixed assets, following procedures were performed.
B15: Work Performed
B16: Made a selection of fixed assets held by client at year-end and physically inspected them using sheet to floor and floor to sheet to ensure that:
B18: Asset is owned and held by client.
B19: Remaining useful life appears to be correct
B20: No new/further impairment is needed
B22: Inspected evidence of ownership of the following: e.g. vehicle registration, property documents, machinery import documents etc.
B25: Attached Sampling Sheet
B27: Observations
B28: None.
... B31: Satisfactory

Sheet Additions-Vouching
B1: =SubLead!B1 -> ABC & Co. | AA1: =Index!F22 -> B.S.01 - 6
B2: =SubLead!B2 -> (Chartered Accountants)
B4: =SubLead!B4 -> Client: | C4: =Index!D4 -> ABC Limited
B5: =SubLead!B5 -> Period: | C5: =Index!D5 -> Year ended June 30, 2023 | Z5: =Index!$H$4 -> Prepared by: | AA5: M. Basit
B6: =SubLead!B6 -> Head: | C6: =Index!D6 -> Property, plant and equipment | Z6: =Index!$H$5 -> Date prepared: | AA6: =IF(Index!$J$5="","",Index!$J$5)
B7: =SubLead!B7 -> Sub Head: | C7: =Lead!B29 -> Operating fixed assets | Z7: =Index!$H$6 -> Reviewed by: | AA7: A. Arif
Z8: =Index!$H$7 -> Date reviewed: | AA8: =IF(Index!$J$7="","",Index!$J$7)
B9: VOUCHING FOR ADDITIONS
B11: Work Performed
B12: Checked supporting documents like vendors' invoices, contractor bills, and other evidences.
B13: Checked proper authorization and approval.
B14: Checked proper posting in general ledger.
B15: Ensured payments made and are reflected in the bank statements.
B16: For additions in leased assets during the year, checked from lease agreements that the lease is a finance lease in substance.
B18: Observations | E18: Total Verified | F18: =SUM(F25:F97) -> 0
B19: None. | E19: Total Population | G19: =Lead!M1 -> B.S.01 - 2
E20: Population Covered | F20: =IFERROR(F18/F19,"")
B21: Conclusion | E21: Sampling Method | F21: Random Table
B22: Satisfactory | E22: Sample size (Planned)
B24: Date | C24: Voucher # | D24: Description of Transaction | E24: Supplier Name | F24: Invoice Amount | G24: Purchase Requisition | H24: Quotations | I24: Qty | J24: Purchase Order # | K24: Goods Received Note # | L24: Supplier's Invoice # | M24: Mathematical Accuracy | N24: Proper Classification | O24: Payment Approval | P24: Posted in Fixed Assets Register | Q24: Sales Tax % | R24: Sales Tax Amount | S24: Sales Tax Withholding % | T24: Sales Tax Withholding Amount | U24: Income Tax Withholding % | V24: Income Tax Withholding Amount | W24: Net Payment | X24: Traced in Bank | Y24: Cheque Date | Z24: Cheque # | AA24: Cheque Amount

Sheet Disposals-Vouching
B1: =SubLead!B1 -> ABC & Co. | V1: =Index!F24 -> B.S.01 - 7
B2: =SubLead!B2 -> (Chartered Accountants)
B4: =SubLead!B4 -> Client: | C4: =SubLead!C4 -> ABC Limited | U4: =Index!$H$4 -> Prepared by: | V4: =IF(Index!$J$4="","",Index!$J$4)
B5: =SubLead!B5 -> Period: | C5: =SubLead!C5 -> Year ended June 30, 2023 | U5: =Index!$H$5 -> Date prepared: | V5: =IF(Index!$J$5="","",Index!$J$5)
B6: =SubLead!B6 -> Head: | C6: =SubLead!C6 -> Property, plant and equipment | U6: =Index!$H$6 -> Reviewed by: | V6: =IF(Index!$J$6="","",Index!$J$6)
B7: =SubLead!B7 -> Sub Head: | C7: =SubLead!C7 -> Operating fixed assets | U7: =Index!$H$7 -> Date reviewed: | V7: =IF(Index!$J$7="","",Index!$J$7)
B9: VOUCHING FOR DELETIONS
B11: Work Performed
B12: Checked supporting documents like transfer deeds and other evidences.
B13: Checked proper authorization and approval.
B14: Checked proper posting in general ledger.
B15: Ensured receipts are reflected in the bank statements.
B16: Performed the above mentioned procedures to ensure various assertions
B18: Observations
B19: None.
B21: Conclusion
B22: Satisfactory
B25: Date | C25: Voucher # | D25: Description of Transaction | E25: Name of Buyer | F25: Date of Acquisition | G25: Cost of Asset | H25: Opening Acc. Dep. | I25: Opening Written Down Value | J25: Disposal date | K25: No of Months in use | L25: Depreciation Rate | M25: Depreciation expense till disposal date | N25: Acc. Dep. till disposal as per our calculation | O25: Acc. Dep. till disposal as per General Ledger | P25: WDV as per our calculation | Q25: WDV as per client | R25: Difference | S25: Sales Proceeds | T25: Gain / (loss) on disposal as per our calculation | U25: Gain / (loss) on disposal as per General Ledger | V25: Difference
H46: =SUM(H25:H45) -> 0

Sheet Depreciation-Working
B1: =Index!B1 -> ABC & Co. | Q1: =Index!F26 -> B.S.01 - 8
B2: =Index!B2 -> (Chartered Accountants)
B4: Client: | C4: =Index!D4 -> ABC Limited | O4: =Index!$H$4 -> Prepared by: | Q4: =IF(Index!$J$4="","",Index!$J$4)
B5: Period: | C5: =Index!D5 -> Year ended June 30, 2023 | O5: =Index!$H$5 -> Date prepared: | Q5: =IF(Index!$J$5="","",Index!$J$5)
B6: Head: | C6: =Index!D6 -> Property, plant and equipment | O6: =Index!$H$6 -> Reviewed by: | Q6: =IF(Index!$J$6="","",Index!$J$6)
B7: Sub Head: | C7: =Lead!B29 -> Operating fixed assets | O7: =Index!$H$7 -> Date reviewed: | Q7: =IF(Index!$J$7="","",Index!$J$7)
B9: RECALCULATION OF DEPRECIATION WORKING
B11: Work Performed
B12: Analytical Procedures
B13: Assessed the appropriateness of depreciation method and rate in view of the flow of economic benefits and useful life of the assets
B14: Checked the reasonableness of depreciation expense by applying depreciation rate to closing cost/ carrying value as per the method adopted
B15: Compare current year expenses with last year expenses and ensure that any significant variation should be properly and logically reasoned
B17: Test of Details
B18: Determined the reasonableness of accounting policy and depreciation method, rates and their consistency with prior years.
B19: Checked calculation of depreciation of selected assets.
B20: Assessed the reasonableness of allocation to manufacturing costs, admin cost etc.
B21: Ensured that none of the assets has been impaired or the recoverable amount of an asset is not less than its carrying amount.
B22: Ensured that any subsequent addition has been depreciated over remaining useful life and not simply depreciated by applying the depreciation rate.
... B31: Satisfactory
D34: Owned Assets | N34: Leased Assets | Q34: Total Assets
D35: Land - freehold | E35: Building - freehold | F35: Plant and Machinery | G35: Electric Installation | H35: Tools and Equipment | I35: Furniture and Fixtures | J35: Office Equipment | K35: Computers and Peripherals | L35: Vehicle | N35: Plant and Machinery | O35: Vehicle
B37: Opening cost / revalued amount
B38: Opening accumulated depreciation
B39: Opening Written Down Value | D39: =SUM(D37:D38) -> 0 | E39: =SUM(E37:E38) -> 0 | F39: =SUM(F37:F38) -> 0 | G39: =SUM(G37:G38) -> 0 | H39: =SUM(H37:H38) -> 0 | I39: =SUM(I37:I38) -> 0 | J39: =SUM(J37:J38) -> 0 | K39: =SUM(K37:K38) -> 0 | L39: =SUM(L37:L38) -> 0 | N39: =SUM(N37:N38) -> 0 | O39: =SUM(O37:O38) -> 0 | Q39: =SUM(Q37:Q38) -> 0
B41: Depreciation rate
B43: Depreciation on opening balance for the whole year
B44: Depreciation on the additions of assets during the year
B45: Depreciation not charged on the assets disposed-off during the year
B46: Expected depreciation charge for the year
B47: Depreciation as per General Ledger
B48: Difference | D48: =D46-D47 -> 0 | E48: =E46-E47 -> 0 | F48: =F46-F47 -> 0 | G48: =G46-G47 -> 0 | H48: =H46-H47 -> 0 | I48: =I46-I47 -> 0 | J48: =J46-J47 -> 0 | K48: =K46-K47 -> 0 | L48: =L46-L47 -> 0 | N48: =N46-N47 -> 0 | O48: =O46-O47 -> 0 | Q48: =Q46-Q47 -> 0
B50: Closing cost / revalued amount
B51: Closing accumulated depreciation
B52: Closing Written Down Value | D52: =SUM(D50:D51) -> 0 | E52: =SUM(E50:E51) -> 0 | F52: =SUM(F50:F51) -> 0 | G52: =SUM(G50:G51) -> 0 | H52: =SUM(H50:H51) -> 0 | I52: =SUM(I50:I51) -> 0 | J52: =SUM(J50:J51) -> 0 | K52: =SUM(K50:K51) -> 0 | L52: =SUM(L50:L51) -> 0 | N52: =SUM(N50:N51) -> 0 | O52: =SUM(O50:O51) -> 0 | Q52: =SUM(Q50:Q51) -> 0

Sheet Vouching-CWIP.
B1: =SubLead!B1 -> ABC & Co. | Z1: =Index!F28 -> B.S.01 - 9
B2: =SubLead!B2 -> (Chartered Accountants)
B4: =SubLead!B4 -> Client: | C4: =SubLead!C4 -> ABC Limited | Y4: =Index!$H$4 -> Prepared by: | Z4: =IF(Index!$J$4="","",Index!$J$4)
B5: =SubLead!B5 -> Period: | C5: =SubLead!C5 -> Year ended June 30, 2023 | Y5: =Index!$H$5 -> Date prepared: | Z5: =IF(Index!$J$5="","",Index!$J$5)
B6: =SubLead!B6 -> Head: | C6: =SubLead!C6 -> Property, plant and equipment | Y6: =Index!$H$6 -> Reviewed by: | Z6: =IF(Index!$J$6="","",Index!$J$6)
B7: =SubLead!B7 -> Sub Head: | C7: =Lead!B30 -> Capital work in progress | Y7: =Index!$H$7 -> Date reviewed: | Z7: =IF(Index!$J$7="","",Index!$J$7)
B9: VOUCHING FOR ADDITIONS
B11: Work Performed
B12: Checked supporting documents like vendors' invoices, contractor bills, and other evidences.
B13: Checked proper authorization and approval.
B14: For selected transfers to fixed assets during the year, check contractor certificates of completion of project and proper approval thereof and examine the stage of completion.
B15: For items stuck-up for considerable period of time, inquire about its status from the management.
B16: Compute provisions if required and ask for management representations.
B18: Observations
B19: None.
B21: Conclusion
B22: Satisfactory
B24: Date | C24: Voucher # | D24: Description of Transaction | E24: Supplier Name | F24: Purchase Requisition | G24: Quotations | H24: Qty | I24: Purchase Order # | J24: Goods Received Note # | K24: Supplier's Invoice # | L24: Mathematical Accuracy | M24: Proper Classification | N24: Payment Approval | O24: Posted in Fixed Assets Register | P24: Sales Tax % | Q24: Sales Tax Amount | R24: Sales Tax Withholding % | S24: Sales Tax Withholding Amount | T24: Income Tax Withholding % | U24: Income Tax Withholding Amount | V24: Net Payment | W24: Traced in Bank | X24: Cheque Date | Y24: Cheque # | Z24: Cheque Amount
H45: =SUM(H24:H44) -> 0

Sheet Adjusting Entries
B1: =Index!B1 -> ABC & Co. | E1: =Index!F30 -> B.S.01 - 10
B2: =Index!B2 -> (Chartered Accountants)
B4: =Index!B4 -> Client: | C4: =Index!D4 -> ABC Limited | D4: =Index!$H$4 -> Prepared by: | E4: =IF(Index!$J$4="","",Index!$J$4)
B5: =Index!B5 -> Period: | C5: =Index!D5 -> Year ended June 30, 2023 | D5: =Index!$H$5 -> Date prepared: | E5: =IF(Index!$J$5="","",Index!$J$5)
B6: =Index!B6 -> Head: | C6: =Index!D6 -> Property, plant and equipment | D6: =Index!$H$6 -> Reviewed by: | E6: =IF(Index!$J$6="","",Index!$J$6)
D7: =Index!$H$7 -> Date reviewed: | E7: =IF(Index!$J$7="","",Index!$J$7)
B9: ADJUSTING ENTRIES
B11: Sr. # | C11: Entry Proposed | D11: Amount
D12: Debit | E12: Credit
