Workbook

Sheet Index
B1: ABC & Co. | J1: B.S.02
B2: (Chartered Accountants)
B4: Client: | D4: ABC Limited | H4: Prepared by:
B5: Period: | D5: Year ended June 30, 2023 | H5: Date prepared:
B6: Head: | D6: Intangible Assets | H6: Reviewed by:
H7: Date reviewed:
B9: INDEX
B11: Sr. # | D11: Description | F11: W.P. Ref. | H11: Whether Placed in File | J11: Initials of Reviewer
B13: 1 | D13: Audit Objectives and Conclusions | F13: =$J$1&" - "&B13 -> B.S.02 - 1
B15: =B13+1 -> 2 | D15: Lead Schedule | F15: =$J$1&" - "&B15 -> B.S.02 - 2
B17: =B15+1 -> 3 | D17: Sub-Lead Schedule | F17: =$J$1&" - "&B17 -> B.S.02 - 3
B19: =B17+1 -> 4 | D19: Related information | F19: =$J$1&" - "&B19 -> B.S.02 - 4
B21: =B19+1 -> 5 | D21: Vouching for Additions | F21: =$J$1&" - "&B21 -> B.S.02 - 5
B23: =B21+1 -> 6 | D23: Vouching for Disposals | F23: =$J$1&" - "&B23 -> B.S.02 - 6
B25: =B23+1 -> 7 | D25: Amortization - Analytical procedures | F25: =$J$1&" - "&B25 -> B.S.02 - 7
B27: =B25+1 -> 8 | D27: Adjusting Entries | F27: =$J$1&" - "&B27 -> B.S.02 - 8

Sheet AOC
B1: =Index!$B$1 -> ABC & Co. | G1: =Index!F13 -> B.S.02 - 1
B2: =Index!$B$2 -> (Chartered Accountants)
F3: =Index!$H$4 -> Prepared by: | G3: =IF(Index!$J$4="","",Index!$J$4)
B4: =Index!B4 -> Client: | D4: =Index!$D$4 -> ABC Limited | F4: =Index!$H$5 -> Date prepared: | G4: =IF(Index!$J$5="","",Index!$J$5)
B5: =Index!B5 -> Period: | D5: =Index!$D$5 -> Year ended June 30, 2023 | F5: =Index!$H$6 -> Reviewed by: | G5: =IF(Index!$J$6="","",Index!$J$6)
B6: =Index!B6 -> Head: | D6: =Index!$D$6 -> Intangible Assets | F6: =Index!$H$7 -> Date reviewed: | G6: =IF(Index!$J$7="","",Index!$J$7)
B8: =UPPER("Audit Objectives and Conclusions") -> AUDIT OBJECTIVES AND CONCLUSIONS
B10: Sr. # | D10: Audit Objectives | F10: Objective Met
F11: Yes/No | G11: Initials
B13: =B12+1 -> 1 | D13: Intangibles assets are completely and accurately recorded.
B14: =B13+1 -> 2 | D14: All recorded intangibles assets actually exist.
B15: =B14+1 -> 3 | D15: Intangibles assets are recorded at appropriate values.
B16: =B15+1 -> 4 | D16: Intangibles assets recorded are owned by the client and title is also in the name of client.
B17: =B16+1 -> 5 | D17: Amortization/impairment expense and gain/ loss on disposal has been accurately calculated and appropriately disclosed.
B18: =B17+1 -> 6 | D18: Intangibles assets are presented and all disclosures have been given in accordance with the Fifth Schedules of the Companies Act, 2017 and relevant IASs/IFRSs.
B21: Sr. # | D21: Conclusion | F21: Satisfactory
F22: Yes/No | G22: Initials
B24: =B23+1 -> 1 | D24: The audit has been completed in accordance with Audit program.
B25: =B24+1 -> 2 | D25: The working papers demonstrate that adequate work has been undertaken.
B26: =B25+1 -> 3 | D26: The working papers contain sufficient information, details of significant features and notes of unusual matters to enable us to form an opinion on financial statements.
B27: =B26+1 -> 4 | D27: In my opinion above amounts are fairly stated and on a consistent basis with the previous period.

Sheet Lead
B1: =Index!$B$1 -> ABC & Co. | M1: =Index!F15 -> B.S.02 - 2
B2: =Index!$B$2 -> (Chartered Accountants)
K3: =Index!$H$4 -> Prepared by: | M3: =IF(Index!$J$4="","",Index!$J$4)
B4: =Index!B4 -> Client: | C4: =Index!$D$4 -> ABC Limited | K4: =Index!$H$5 -> Date prepared: | M4: =IF(Index!$J$5="","",Index!$J$5)
B5: =Index!B5 -> Period: | C5: =Index!$D$5 -> Year ended June 30, 2023 | K5: =Index!$H$6 -> Reviewed by: | M5: =IF(Index!$J$6="","",Index!$J$6)
B6: =Index!B6 -> Head: | C6: =Index!$D$6 -> Intangible Assets | K6: =Index!$H$7 -> Date reviewed: | M6: =IF(Index!$J$7="","",Index!$J$7)
B8: LEAD SCHEDULE
B10: Work performed
B11: Analytical Procedures:
B12: Compared current year balances with last year balances and ensured that any significant variation has been properly and logically reasoned.
B13: Test of Details
B14: Traced opening balances from fixed assets register, general ledger and last year’s working papers.
B15: Ensure that closing balances as per our working paper file are in match with closing balance as per general ledger.
B16: Determined and ensured that disclosures have been made in accordance with the requirements of Fifth Schedule to the Companies Act, 2017 and the applicable IASs / IFRSs.
B18: Ascertain the nature of each significant intangible asset by inquiry or reviewing information contained in prior-year’s working papers.
B19: Ensured that all intangible assets fully comply with the definition (identifiable, control and flow of economic benefits) and recognition criteria of the IAS 38 i.e.
B21: (a) Flow of economic benefits to enterprise is expected in future, and
B22: (b) Cost of the asset may be determined.
... B28: Satisfactory
B30: Description | E30: W.P. Ref. | G30: 2023 | H30: 2022 | J30: Variance | K30: Variance | M30: Reason for Variance
G31: Rupees | H31: Rupees | J31: Rupees | K31: %
B33: Intangible
B34: Goodwill | E34: =SubLead!$M$1 -> B.S.02 - 3 | J34: =G34-H34 -> 0 | K34: =IFERROR(J34/H34,"")
B35: Patents | E35: =SubLead!$M$1 -> B.S.02 - 3 | J35: =G35-H35 -> 0 | K35: =IFERROR(J35/H35,"")
B36: Trademarks | E36: =SubLead!$M$1 -> B.S.02 - 3 | J36: =G36-H36 -> 0 | K36: =IFERROR(J36/H36,"")
B37: Copyrights | E37: =SubLead!$M$1 -> B.S.02 - 3 | J37: =G37-H37 -> 0 | K37: =IFERROR(J37/H37,"")
B38: Financial Software | E38: =SubLead!$M$1 -> B.S.02 - 3 | J38: =G38-H38 -> 0 | K38: =IFERROR(J38/H38,"")
B41: Total | G41: =SUM(G32:G40) -> 0 | H41: =SUM(H32:H39) -> 0 | J41: =SUM(J32:J39) -> 0
B47: 2. Ensure that all intangible assets fully comply with the definition (identifiable, control and flow of economic benefits) and recognition criteria of the IAS 38 i.e.
B48: (a) Flow of economic benefits to enterprise is expected in future, and
B49: (b) Cost of the asset may be determined.

Sheet SubLead
B1: =Index!$B$1 -> ABC & Co. | M1: =Index!F17 -> B.S.02 - 3
B2: =Index!$B$2 -> (Chartered Accountants)
K3: =Index!$H$4 -> Prepared by: | M3: =IF(Index!$J$4="","",Index!$J$4)
B4: =Index!B4 -> Client: | C4: =Index!$D$4 -> ABC Limited | K4: =Index!$H$5 -> Date prepared: | M4: =IF(Index!$J$5="","",Index!$J$5)
B5: =Index!B5 -> Period: | C5: =Index!$D$5 -> Year ended June 30, 2023 | K5: =Index!$H$6 -> Reviewed by: | M5: =IF(Index!$J$6="","",Index!$J$6)
B6: =Index!B6 -> Head: | C6: =Index!$D$6 -> Intangible Assets | K6: =Index!$H$7 -> Date reviewed: | M6: =IF(Index!$J$7="","",Index!$J$7)
B8: SUB-LEAD SCHEDULE
B10: Work Performed
B11: Test of Details
B12: Obtained movement schedule of Intangibles for cost, accumulated amortization and impairment.
B13: Performed casting and cross casting of the schedule.
B14: Document logical commercial reasons for major additions and disposal made during the year and check whether the additions are in accordance with the objects of the company.
B17: Observations
B18: None.
B20: Conclusion
B21: Satisfactory
E23: W.P. Ref. | G23: Goodwill | H23: Patents | I23: Copyrights | J23: Trademarks | K23: Financial Software | M23: Total
G24: ---------------------------------------- Rupees ----------------------------------------
B26: Cost | C26: Opening balance | E26: ='Ammortization-AP'!I1 -> B.S.02 - 7
C27: Additions during the period | E27: ='Additions-Vouching'!AA1 -> B.S.02 - 5
C28: Disposals during the period | E28: ='Disposals-Vouching'!V1 -> B.S.02 - 6
C29: Closing balance | E29: =E26 -> B.S.02 - 7
B31: Amortization | C31: Opening balance | E31: ='Ammortization-AP'!I1 -> B.S.02 - 7
C32: Charge for the period | E32: ='Ammortization-AP'!I1 -> B.S.02 - 7
C33: Disposals during the period | E33: =E28 -> B.S.02 - 6
C34: Closing balance | E34: =E31 -> B.S.02 - 7
B36: Opening Net Book Value | E36: ='Ammortization-AP'!I1 -> B.S.02 - 7
B38: Closing Net Book Value | E38: =E36 -> B.S.02 - 7
G40: =Lead!$M$1 -> B.S.02 - 2 | H40: =Lead!$M$1 -> B.S.02 - 2 | I40: =Lead!$M$1 -> B.S.02 - 2 | J40: =Lead!$M$1 -> B.S.02 - 2 | K40: =Lead!$M$1 -> B.S.02 - 2 | M40: =Lead!$M$1 -> B.S.02 - 2

Sheet Additions-Vouching
B1: =Index!$B$1 -> ABC & Co. | AA1: =Index!F21 -> B.S.02 - 5
B2: =Index!$B$2 -> (Chartered Accountants)
B4: =Index!B4 -> Client: | C4: =Index!$D$4 -> ABC Limited | Z4: =Index!$H$4 -> Prepared by: | AA4: =IF(Index!$J$4="","",Index!$J$4)
B5: =Index!B5 -> Period: | C5: =Index!$D$5 -> Year ended June 30, 2023 | Z5: =Index!$H$5 -> Date prepared: | AA5: =IF(Index!$J$5="","",Index!$J$5)
B6: =Index!B6 -> Head: | C6: =Index!$D$6 -> Intangible Assets | Z6: =Index!$H$6 -> Reviewed by: | AA6: =IF(Index!$J$6="","",Index!$J$6)
Z7: =Index!$H$7 -> Date reviewed: | AA7: =IF(Index!$J$7="","",Index!$J$7)
B8: VOUCHING FOR ADDITIONS
B10: Work Performed
B11: Checked supporting documents like vendors' invoices, contractor bills, and other evidences.
B12: Checked proper authorization and approval.
B13: Checked proper posting in general ledger.
B14: Ensured payments made and are reflected in the bank statements.
B15: For selected intangibles additions during the year: -
B16: (a) Approval in Board meeting
B17: (b) Trace the recorded value to supporting documents e.g. independent valuation for purchases in current year.
B18: (c) Obtain authorization or board minutes.
B20: Observations | E20: Total Verified | F20: =SUM(F27:F100) -> 0
B21: None. | E21: Total Population | G21: =SubLead!M1 -> B.S.02 - 3
E22: Population Covered | F22: =IFERROR(F20/F21,"")
B23: Conclusion | E23: Sampling Method | F23: Random Table
B24: Satisfactory | E24: Sample size (Planned)
B26: Date | C26: Voucher # | D26: Description of Transaction | E26: Supplier Name | F26: Invoice Amount | G26: Purchase Requisition # | H26: Quotation Reference | I26: Qty | J26: Purchase Order # | K26: Goods Received Note # | L26: Supplier's Invoice # | M26: Mathematical Accuracy (Yes/No) | N26: Proper Classification (Yes/No) | O26: Payment Approval by | P26: Posted in Intangible Register | Q26: Sales Tax % | R26: Sales Tax Amount | S26: Sales Tax Withholding % | T26: Sales Tax Withholding Amount | U26: Income Tax Withholding % | V26: Income Tax Withholding Amount | W26: Net Payment | X26: Traced in Bank | Y26: Cheque Date | Z26: Cheque # | AA26: Cheque Amount

Sheet Disposals-Vouching
B1: =Index!$B$1 -> ABC & Co. | V1: =Index!F23 -> B.S.02 - 6
B2: =Index!$B$2 -> (Chartered Accountants)
B4: =Index!B4 -> Client: | C4: =Index!$D$4 -> ABC Limited | U4: =Index!$H$4 -> Prepared by: | V4: =IF(Index!$J$4="","",Index!$J$4)
B5: =Index!B5 -> Period: | C5: =Index!$D$5 -> Year ended June 30, 2023 | U5: =Index!$H$5 -> Date prepared: | V5: =IF(Index!$J$5="","",Index!$J$5)
B6: =Index!B6 -> Head: | C6: =Index!$D$6 -> Intangible Assets | U6: =Index!$H$6 -> Reviewed by: | V6: =IF(Index!$J$6="","",Index!$J$6)
U7: =Index!$H$7 -> Date reviewed: | V7: =IF(Index!$J$7="","",Index!$J$7)
B8: VOUCHING FOR DELETIONS
B10: Work Performed
B11: Checked supporting documents like transfer deeds and other evidences.
B12: Checked proper authorization and approval.
B13: Checked proper posting in general ledger.
B14: Ensured receipts are reflected in the bank statements.
B15: Performed the above mentioned procedures to ensure various assertions
B16: For selected intangible assets disposed-off during the year: -
B17: (a) Examine supporting documents (e.g. cash receipts).
B18: (b) Calculate gain or loss on sale of assets
B20: Observations
B21: None.
... B24: Satisfactory
B26: Date | C26: Voucher # | D26: Description of Transaction | E26: Name of Buyer | F26: Date of Acquisition | G26: Cost of Asset | H26: Opening Acc. Dep. | I26: Opening Written Down Value | J26: Disposal date | K26: No of Months in use | L26: Amortization Rate | M26: Amortization expense till disposal date | N26: Acc. Amrt. till disposal as per our calculation | O26: Acc. Amrt. till disposal as per General Ledger | P26: WDV as per our calculation | Q26: WDV as per client | R26: Difference | S26: Sales Proceeds | T26: Gain / (loss) on disposal as per our calculation | U26: Gain / (loss) on disposal as per General Ledger | V26: Difference
G46: =SUM(G26:G45) -> 0 | H46: =SUM(H26:H45) -> 0 | I46: =SUM(I26:I45) -> 0 | M46: =SUM(M26:M45) -> 0 | N46: =SUM(N26:N45) -> 0 | O46: =SUM(O26:O45) -> 0 | P46: =SUM(P26:P45) -> 0 | Q46: =SUM(Q26:Q45) -> 0 | R46: =SUM(R26:R45) -> 0 | S46: =SUM(S26:S45) -> 0 | T46: =SUM(T26:T45) -> 0 | ... V46: =SUM(V26:V45) -> 0

Sheet Ammortization-AP
B1: =Index!$B$1 -> ABC & Co. | I1: =Index!F25 -> B.S.02 - 7
B2: =Index!$B$2 -> (Chartered Accountants)
B4: =Index!B4 -> Client: | C4: =Index!$D$4 -> ABC Limited | G4: =Index!$H$4 -> Prepared by: | I4: =IF(Index!$J$4="","",Index!$J$4)
B5: =Index!B5 -> Period: | C5: =Index!$D$5 -> Year ended June 30, 2023 | G5: =Index!$H$5 -> Date prepared: | I5: =IF(Index!$J$5="","",Index!$J$5)
B6: =Index!B6 -> Head: | C6: =Index!$D$6 -> Intangible Assets | G6: =Index!$H$6 -> Reviewed by: | I6: =IF(Index!$J$6="","",Index!$J$6)
B7: Sub Head: | C7: =Lead!B38 -> Financial Software | G7: =Index!$H$7 -> Date reviewed: | I7: =IF(Index!$J$7="","",Index!$J$7)
B9: AMORTIZATION - ANALYTICAL PROCEDURE
B11: Work Performed
B12: Analytical Procedures
B13: Assessed the appropriateness of amortization method and rate in view of the flow of economic benefits and useful life of the assets
B14: Checked the reasonableness of amortization expense by applying amortization rate to closing cost/ carrying value as per the method adopted
B15: Compare current year expenses with last year expenses and ensure that any significant variation should be properly and logically reasoned
B17: Test of Details
B18: Determined the reasonableness of accounting policy and amortization method, rates and their consistency with prior years.
B19: Checked calculation of amortization of selected assets.
B20: Ensured that none of the assets has been impaired or the recoverable amount of an asset is not less than its carrying amount.
B21: Ensured that any subsequent addition has been amortized over remaining useful life and not simply depreciated by applying the amortization rate.
B22: Determined that client's accounting policies for amortization are appropriate and applied consistently.
... B29: Satisfactory
D31: =SubLead!H23 -> Patents | E31: =SubLead!I23 -> Copyrights | F31: =SubLead!J23 -> Trademarks | G31: =SubLead!K23 -> Financial Software | I31: Total
B33: Opening cost | K33: =SubLead!E26 -> B.S.02 - 7
B34: Opening accumulated amortization | K34: =K33 -> B.S.02 - 7
B35: Opening Written Down Value | D35: =SUM(D33:D34) -> 0 | E35: =SUM(E33:E34) -> 0 | F35: =SUM(F33:F34) -> 0 | G35: =SUM(G33:G34) -> 0 | I35: =SUM(I33:I34) -> 0 | K35: =K34 -> B.S.02 - 7
B37: Amortization rate
B39: Amortization on opening balance for the whole year
B40: Amortization the additions of assets during the year
B41: Amortization not charged on the assets disposed-off during the year
B42: Expected amortization charge for the year
B43: Amortization as per General Ledger | K43: =SubLead!E32 -> B.S.02 - 7
B44: Difference | D44: =D42-D43 -> 0 | E44: =E42-E43 -> 0 | F44: =F42-F43 -> 0 | G44: =G42-G43 -> 0 | I44: =I42-I43 -> 0
B50: Closing cost | K50: =SubLead!E29 -> B.S.02 - 7
B51: Closing accumulated amortization | K51: =K50 -> B.S.02 - 7
B52: Closing Written Down Value | D52: =D50-D51 -> 0 | E52: =E50-E51 -> 0 | F52: =F50-F51 -> 0 | G52: =G50-G51 -> 0 | I52: =I50-I51 -> 0 | K52: =K51 -> B.S.02 - 7

Sheet Adjusting Entries
B1: =Index!$B$1 -> ABC & Co. | E1: =Index!F27 -> B.S.02 - 8
B2: =Index!$B$2 -> (Chartered Accountants)
D3: =Index!$H$4 -> Prepared by: | E3: =IF(Index!$J$4="","",Index!$J$4)
B4: =Index!B4 -> Client: | C4: =Index!$D$4 -> ABC Limited | D4: =Index!$H$5 -> Date prepared: | E4: =IF(Index!$J$5="","",Index!$J$5)
B5: =Index!B5 -> Period: | C5: =Index!$D$5 -> Year ended June 30, 2023 | D5: =Index!$H$6 -> Reviewed by: | E5: =IF(Index!$J$6="","",Index!$J$6)
B6: =Index!B6 -> Head: | C6: =Index!$D$6 -> Intangible Assets | D6: =Index!$H$7 -> Date reviewed: | E6: =IF(Index!$J$7="","",Index!$J$7)
B8: ADJUSTING ENTRIES
B10: Sr. # | C10: Entry Proposed | D10: Amount
D11: Debit | E11: Credit
