Workbook

Sheet Index
B1: ABC & Co. | F1: BS.10
B2: (Chartered Accountants)
B4: Client: | C4: ABC Limited | E4: Prepared by:
B5: Period: | C5: Year ended June 30, 2023 | E5: Date prepared:
B6: Head: | C6: Short term loans and advances | E6: Reviewed by:
E7: Date reviewed:
B8: INDEX
B10: Sr. # | C10: Description | D10: W.P. Ref. | E10: Whether Placed in File | F10: Initials of Reviewer
B12: 1 | C12: Audit Objectives and Conclusions | D12: =$F$1&" - "&B12 -> BS.10 - 1
B14: =B12+1 -> 2 | C14: Lead Schedule | D14: =$F$1&" - "&B14 -> BS.10 - 2
B16: =B14+1 -> 3 | C16: Sub-Lead Schedule | D16: =$F$1&" - "&B16 -> BS.10 - 3
B18: =B16+1 -> 4 | C18: Vouching - Additions | D18: =$F$1&" - "&B18 -> BS.10 - 4
B20: =B18+1 -> 5 | C20: Confirmation summary, reconciliation | D20: =$F$1&" - "&B20 -> BS.10 - 5
B22: =B20+1 -> 6 | C22: Copies of Documents/Summary | D22: =$F$1&" - "&B22 -> BS.10 - 6
B24: =B22+1 -> 7 | C24: Impairment Testing | D24: =$F$1&" - "&B24 -> BS.10 - 7
B26: =B24+1 -> 8 | C26: Adjusting Entries | D26: =$F$1&" - "&B26 -> BS.10 - 8

Sheet AOC
B1: =Index!$B$1 -> ABC & Co. | E1: =Index!D12 -> BS.10 - 1
B2: =Index!$B$2 -> (Chartered Accountants)
B4: =Index!$B$4 -> Client: | C4: =Index!$C$4 -> ABC Limited | D4: =Index!$E$4 -> Prepared by: | E4: =IF(Index!$F$4="","",Index!$F$4)
B5: =Index!$B$5 -> Period: | C5: =Index!$C$5 -> Year ended June 30, 2023 | D5: =Index!$E$5 -> Date prepared: | E5: =IF(Index!$F$5="","",Index!$F$5)
B6: =Index!$B$6 -> Head: | C6: =Index!$C$6 -> Short term loans and advances | D6: =Index!$E$6 -> Reviewed by: | E6: =IF(Index!$F$6="","",Index!$F$6)
D7: =Index!$E$7 -> Date reviewed: | E7: =IF(Index!$F$7="","",Index!$F$7)
B8: =UPPER("Audit Objectives and Conclusions") -> AUDIT OBJECTIVES AND CONCLUSIONS
B10: Sr. # | C10: Audit Objectives | D10: Objective Met
D11: Yes/No | E11: Initials
B13: 1 | C13: All short term loans and advances are completely and accurately recorded
B14: =B13+1 -> 2 | C14: All recorded short term loans and advances actually exist
B15: =B14+1 -> 3 | C15: Short term loans and advances are recorded at appropriate values and all bad and doubtful balances have been provided for/ written off
B16: =B15+1 -> 4 | C16: Short term loans and advances recorded are the right of the company
B17: =B16+1 -> 5 | C17: Short term loans and advances to associated undertaking were in accordance with legal requirements
B18: =B17+1 -> 6 | C18: Short term loans and advances are presented and all disclosures have been given in accordance with the Fifth Schedule of the Companies Act, 2017 and relevant IASs/IFRSs.
B21: Sr. # | C21: Conclusion | D21: Satisfactory
D22: Yes/No | E22: Initials
B24: 1 | C24: The audit has been completed in accordance with Audit program.
B25: =B24+1 -> 2 | C25: The working papers demonstrate that adequate work has been undertaken.
B26: =B25+1 -> 3 | C26: The working papers contain sufficient information, details of significant features and notes of unusual matters to enable us to form an opinion on financial statements.
B27: =B26+1 -> 4 | C27: In my opinion above amounts are fairly stated and on a consistent basis with the previous period.

Sheet Lead
B1: =Index!$B$1 -> ABC & Co. | I1: =Index!D14 -> BS.10 - 2
B2: =Index!$B$2 -> (Chartered Accountants)
B4: =Index!$B$4 -> Client: | C4: =Index!$C$4 -> ABC Limited | H4: =Index!$E$4 -> Prepared by: | I4: =IF(Index!$F$4="","",Index!$F$4)
B5: =Index!$B$5 -> Period: | C5: =Index!$C$5 -> Year ended June 30, 2023 | H5: =Index!$E$5 -> Date prepared: | I5: =IF(Index!$F$5="","",Index!$F$5)
B6: =Index!$B$6 -> Head: | C6: =Index!$C$6 -> Short term loans and advances | H6: =Index!$E$6 -> Reviewed by: | I6: =IF(Index!$F$6="","",Index!$F$6)
H7: =Index!$E$7 -> Date reviewed: | I7: =IF(Index!$F$7="","",Index!$F$7)
B8: LEAD SCHEDULE
B9: Work performed
B10: Analytical Procedures:
B11: Compared current year balances with last year balances and ensured that any significant variation has been properly and logically reasoned.
B13: Test of Details
B14: Ensured that all loans and advances to associated undertakings are granted after due compliance with legal requirements.
B15: Ensured that none of the loans and advances are impaired or the recoverable amount of a loan or advance is not less than its carrying amount.
B16: If the carrying amount of a loan/ advance is the reduction as impairment loss.
B17: Checked loan agreement and legal documents to verify the terms and conditions of the advances.
B18: For items stucked-up for considerable period of time, inquired about its status from the management.
B19: Ensured that loans and advances should be measured at amortized cost using the effective interest rate method
B20: Ensured that closing balances as per our working paper file are matched with general ledger.
... B27: Satisfactory
B30: Description | D30: W.P. Ref. | E30: 2021 | F30: =E30-1 -> 2020 | G30: Variance | H30: Variance | I30: Reason for Variance
E31: Rupees | F31: Rupees | G31: Rupees | H31: %
B33: =C6 -> Short term loans and advances
B34: Short term loans
B35: Loan to Employees | G35: =E35-F35 -> 0 | H35: =IFERROR(G35/F35,"")
B36: Loan to Executives | G36: =E36-F36 -> 0 | H36: =IFERROR(G36/F36,"")
B37: Loan to Associated undertakings | G37: =E37-F37 -> 0 | H37: =IFERROR(G37/F37,"")
B39: Advances
B40: Advances to employees against salary | G40: =E40-F40 -> 0 | H40: =IFERROR(G40/F40,"")
B41: Advances to employees against expenses | G41: =E41-F41 -> 0 | H41: =IFERROR(G41/F41,"")
B42: Advances to suppliers | G42: =E42-F42 -> 0 | H42: =IFERROR(G42/F42,"")
B43: Advances to statutory authorities | G43: =E43-F43 -> 0 | H43: =IFERROR(G43/F43,"")
B46: T O T A L | E46: =SUM(E32:E45) -> 0 | F46: =SUM(F32:F44) -> 0 | G46: =SUM(G32:G44) -> 0

Sheet SubLead-Loans
B1: =Index!$B$1 -> ABC & Co. | I1: =Index!D16 -> BS.10 - 3
B2: =Index!$B$2 -> (Chartered Accountants)
B4: =Index!$B$4 -> Client: | C4: =Index!$C$4 -> ABC Limited | H4: =Index!$E$4 -> Prepared by: | I4: =IF(Index!$F$4="","",Index!$F$4)
B5: =Index!$B$5 -> Period: | C5: =Index!$C$5 -> Year ended June 30, 2023 | H5: =Index!$E$5 -> Date prepared: | I5: =IF(Index!$F$5="","",Index!$F$5)
B6: =Index!$B$6 -> Head: | C6: =Index!$C$6 -> Short term loans and advances | H6: =Index!$E$6 -> Reviewed by: | I6: =IF(Index!$F$6="","",Index!$F$6)
B7: Subhead: | C7: =Lead!B34 -> Short term loans | H7: =Index!$E$7 -> Date reviewed: | I7: =IF(Index!$F$7="","",Index!$F$7)
B8: SUB-LEAD SCHEDULE
B9: Work performed
B10: Test of Details
B11: For disbursements made during the year checked disbursements of funds with disbursement register and bank statement.
B12: For a sample of repayments made during the year:
B13: (a) Ensured that amount and date of repayment was accordance with repayment schedule or agreement.
B14: (b) Checked receipt of funds with receipt records and bank statement.
B15: (c) Checked the recovery of interest is in accordance with the policy (i.e. along with principal or after recovery of full principal, as the case may be).
B16: Circularized confirmations to selected parties. Matched replies with the amounts outstanding against each party.
B17: Obtained age-analysis of short-term loans and advances and perform the following:
B18: (a) Verified that loans have been classified in correct categories.
B19: (b) Current maturity has been appropriately calculated and separately disclosed.
... B30: Satisfactory
B32: Description | D32: W.P. Ref. | E32: =Lead!E30 -> 2021 | F32: =Lead!F30 -> 2020 | G32: Variance | H32: Variance | I32: Reason for Variance
E33: Rupees | F33: Rupees | G33: Rupees | H33: %
B35: =Lead!B35 -> Loan to Employees
B36: Opening balance | G36: =E36-F36 -> 0 | H36: =IFERROR(G36/F36,"")
B37: Add: Loans advanced during the year | G37: =E37-F37 -> 0 | H37: =IFERROR(G37/F37,"")
B38: Less: Loan returned during the year | G38: =E38-F38 -> 0 | H38: =IFERROR(G38/F38,"")
B40: =Lead!B36 -> Loan to Executives
B41: Opening balance | G41: =E41-F41 -> 0 | H41: =IFERROR(G41/F41,"")
B42: Add: Loans advanced during the year | G42: =E42-F42 -> 0 | H42: =IFERROR(G42/F42,"")
B43: Less: Loan returned during the year | G43: =E43-F43 -> 0 | H43: =IFERROR(G43/F43,"")
B45: =Lead!B37 -> Loan to Associated undertakings
B46: Opening balance | G46: =E46-F46 -> 0 | H46: =IFERROR(G46/F46,"")
B47: Add: Loans advanced during the year | G47: =E47-F47 -> 0 | H47: =IFERROR(G47/F47,"")
B48: Less: Loan returned during the year | G48: =E48-F48 -> 0 | H48: =IFERROR(G48/F48,"")
B54: Total closing balance | E54: =E52+E39 -> 0 | F54: =F52+F39 -> 0 | G54: =G52+G39 -> 0

Sheet SubLead-Advances
B1: =Index!$B$1 -> ABC & Co. | I1: =Index!D16 -> BS.10 - 3
B2: =Index!$B$2 -> (Chartered Accountants)
B4: =Index!$B$4 -> Client: | C4: =Index!$C$4 -> ABC Limited | H4: =Index!$E$4 -> Prepared by: | I4: =IF(Index!$F$4="","",Index!$F$4)
B5: =Index!$B$5 -> Period: | C5: =Index!$C$5 -> Year ended June 30, 2023 | H5: =Index!$E$5 -> Date prepared: | I5: =IF(Index!$F$5="","",Index!$F$5)
B6: =Index!$B$6 -> Head: | C6: =Index!$C$6 -> Short term loans and advances | H6: =Index!$E$6 -> Reviewed by: | I6: =IF(Index!$F$6="","",Index!$F$6)
B7: Subhead: | C7: =Lead!B39 -> Advances | H7: =Index!$E$7 -> Date reviewed: | I7: =IF(Index!$F$7="","",Index!$F$7)
B9: SUB-LEAD SCHEDULE
B10: Work performed
B11: Test of Details
B12: For disbursements made during the year checked disbursements of funds with advances register and bank statement.
B13: For a sample of repayments made during the year:
B14: (a) Ensured that amount and date of repayment was accordance with repayment schedule or agreement.
B15: (b) Checked receipt of funds with receipt records and bank statement.
B16: (c) Checked the recovery of interest is in accordance with the policy (i.e. along with principal or after recovery of full principal, as the case may be).
B17: Circularized confirmations to selected parties. Matched replies with the amounts outstanding against each party.
B18: Obtained age-analysis of advances and performed the following:
B19: (a) Verified that advances have been classified in correct categories.
B20: (b) Current maturity has been appropriately calculated and separately disclosed.
... B30: Satisfactory
B32: Description | D32: W.P. Ref. | E32: =Lead!E30 -> 2021 | F32: =Lead!F30 -> 2020 | G32: Variance | H32: Variance | I32: Reason for Variance
E33: Rupees | F33: Rupees | G33: Rupees | H33: %
B35: =Lead!B40 -> Advances to employees against salary
B36: Opening balance | G36: =E36-F36 -> 0 | H36: =IFERROR(G36/F36,"")
B37: Add: Advances made during the year | G37: =E37-F37 -> 0 | H37: =IFERROR(G37/F37,"")
B38: Less: Advances returned during the year | G38: =E38-F38 -> 0 | H38: =IFERROR(G38/F38,"")
B40: =Lead!B41 -> Advances to employees against expenses
B41: Opening balance | G41: =E41-F41 -> 0 | H41: =IFERROR(G41/F41,"")
B42: Add: Advances made during the year | G42: =E42-F42 -> 0 | H42: =IFERROR(G42/F42,"")
B43: Less: Expenses made during the year | G43: =E43-F43 -> 0 | H43: =IFERROR(G43/F43,"")
B45: =Lead!B42 -> Advances to suppliers
B46: Opening balance | G46: =E46-F46 -> 0 | H46: =IFERROR(G46/F46,"")
B47: Add: Advances made during the year | G47: =E47-F47 -> 0 | H47: =IFERROR(G47/F47,"")
B48: Less: Advances returned during the year | G48: =E48-F48 -> 0 | H48: =IFERROR(G48/F48,"")
B50: =Lead!B43 -> Advances to statutory authorities
B51: Opening balance | G51: =E51-F51 -> 0 | H51: =IFERROR(G51/F51,"")
B52: Add: Advances made during the year | G52: =E52-F52 -> 0 | H52: =IFERROR(G52/F52,"")
B53: Less: Advances returned during the year | G53: =E53-F53 -> 0 | H53: =IFERROR(G53/F53,"")
B56: Total closing balance | E56: =E54+E39 -> 0 | F56: =F54+F39 -> 0 | G56: =G54+G39 -> 0

Sheet Vouching-Additions
B1: =Index!$B$1 -> ABC & Co. | I1: =Index!D18 -> BS.10 - 4
B2: =Index!$B$2 -> (Chartered Accountants)
B4: =Index!$B$4 -> Client: | C4: =Index!$C$4 -> ABC Limited | H4: =Index!$E$4 -> Prepared by: | I4: =IF(Index!$F$4="","",Index!$F$4)
B5: =Index!$B$5 -> Period: | C5: =Index!$C$5 -> Year ended June 30, 2023 | H5: =Index!$E$5 -> Date prepared: | I5: =IF(Index!$F$5="","",Index!$F$5)
B6: =Index!$B$6 -> Head: | C6: =Index!$C$6 -> Short term loans and advances | H6: =Index!$E$6 -> Reviewed by: | I6: =IF(Index!$F$6="","",Index!$F$6)
B7: Subhead: | H7: =Index!$E$7 -> Date reviewed: | I7: =IF(Index!$F$7="","",Index!$F$7)
B8: VOUCHING - ADDITIONS
B9: Work performed
B11: Date | C11: Voucher # | D11: Description | E11: Approved By | F11: Cheque # | G11: Amount | H11: Traced into Bank Statement | I11: Proper Classification

Sheet Impairnment
B1: =Index!$B$1 -> ABC & Co. | I1: =Index!D24 -> BS.10 - 7
B2: =Index!$B$2 -> (Chartered Accountants)
B4: =Index!$B$4 -> Client: | C4: =Index!$C$4 -> ABC Limited | H4: =Index!$E$4 -> Prepared by: | I4: =IF(Index!$F$4="","",Index!$F$4)
B5: =Index!$B$5 -> Period: | C5: =Index!$C$5 -> Year ended June 30, 2023 | H5: =Index!$E$5 -> Date prepared: | I5: =IF(Index!$F$5="","",Index!$F$5)
B6: =Index!$B$6 -> Head: | C6: =Index!$C$6 -> Short term loans and advances | H6: =Index!$E$6 -> Reviewed by: | I6: =IF(Index!$F$6="","",Index!$F$6)
H7: =Index!$E$7 -> Date reviewed: | I7: =IF(Index!$F$7="","",Index!$F$7)
B8: IMPAIRNMENT TESTING
B9: Work performed
B10: Obtained age-analysis of long-term loans and advances and performed the following:
B11: (a) Verified that loans and advances had been classified in correct categories.
B12: (b) Current maturity had been appropriately identified and separately disclosed
B13: Ensured that none of the loans and advances are impaired or the recoverable amount of same is not less than its carrying amount.
B14: If the carrying amount of loans and advances is more than its recoverable amount, then same should be reduced to recoverable amount.
B15: The reduction is recogised as impairment loss.
B17: Observations
B18: None.
B20: Conclusion
B21: Satisfactory
B23: Description | D23: Amount | E23: Ageing | I23: Subsequent Position
E24: 0 - 1 year | F24: 1 - 2 year | G24: 2 - 3 years | H24: More than 3 years

Sheet Adjusting Entries
B1: =Index!$B$1 -> ABC & Co. | E1: =Index!D26 -> BS.10 - 8
B2: =Index!$B$2 -> (Chartered Accountants)
B4: =Index!$B$4 -> Client: | C4: =Index!$C$4 -> ABC Limited | D4: =Index!$E$4 -> Prepared by: | E4: =IF(Index!$F$4="","",Index!$F$4)
B5: =Index!$B$5 -> Period: | C5: =Index!$C$5 -> Year ended June 30, 2023 | D5: =Index!$E$5 -> Date prepared: | E5: =IF(Index!$F$5="","",Index!$F$5)
B6: =Index!$B$6 -> Head: | C6: =Index!$C$6 -> Short term loans and advances | D6: =Index!$E$6 -> Reviewed by: | E6: =IF(Index!$F$6="","",Index!$F$6)
D7: =Index!$E$7 -> Date reviewed: | E7: =IF(Index!$F$7="","",Index!$F$7)
B8: ADJUSTING ENTRIES
B10: Sr. # | C10: Entry Proposed | D10: Amount
D11: Debit | E11: Credit
