Workbook

Sheet Index
B1: ABC & Co. | H1: BS.15
B2: (Chartered Accountants)
B4: Client: | C4: ABC Limited | G4: Prepared by:
B5: Period: | C5: Year ended June 30, 2023 | G5: Date prepared:
B6: Head: | C6: Cash and bank balance | G6: Reviewed by:
G7: Date reviewed:
B8: INDEX
B10: Sr. # | C10: Description | E10: W.P. Ref. | G10: Whether Placed in File | H10: Initials of Reviewer
B12: 1 | C12: =PROPER(AOC!B8) -> Audit Objectives And Conclusions | E12: =$H$1&" - "&B12 -> BS.15 - 1
B14: =B12+1 -> 2 | C14: =PROPER(Lead!B8) -> Lead Schedule | E14: =$H$1&" - "&B14 -> BS.15 - 2
B16: =B14+1 -> 3 | C16: =PROPER(SubLead!B8) -> Sub-Lead Schedule | E16: =$H$1&" - "&B16 -> BS.15 - 3
B18: =B16+1 -> 4 | C18: =PROPER('BankConfirmation-CS'!B8) -> Bank Confirmation - Control Sheet | E18: =$H$1&" - "&B18 -> BS.15 - 4
B20: =B18+1 -> 5 | C20: Bank Statements and Reconciliations | E20: =$H$1&" - "&B20 -> BS.15 - 5
B22: =B20+1 -> 6 | C22: Adjusting Entries | E22: =$H$1&" - "&B22 -> BS.15 - 6

Sheet AOC
B1: =Index!$B$1 -> ABC & Co. | E1: =Index!E12 -> BS.15 - 1
B2: =Index!$B$2 -> (Chartered Accountants)
B4: =Index!$B$4 -> Client: | C4: =Index!$C$4 -> ABC Limited | D4: =Index!$G$4 -> Prepared by: | E4: =IF(Index!$H$4="","",Index!$H$4)
B5: =Index!$B$5 -> Period: | C5: =Index!$C$5 -> Year ended June 30, 2023 | D5: =Index!$G$5 -> Date prepared: | E5: =IF(Index!$H$5="","",Index!$H$5)
B6: =Index!$B$6 -> Head: | C6: =Index!$C$6 -> Cash and bank balance | D6: =Index!$G$6 -> Reviewed by: | E6: =IF(Index!$H$6="","",Index!$H$6)
D7: =Index!$G$7 -> Date reviewed: | E7: =IF(Index!$H$7="","",Index!$H$7)
B8: =UPPER("Audit Objectives and Conclusions") -> AUDIT OBJECTIVES AND CONCLUSIONS
B10: Sr. # | C10: Audit Objectives | D10: Objective Met
D11: Yes/No | E11: Initials
B13: 1 | C13: All cash and bank balances are completely and accurately recorded
B14: =B13+1 -> 2 | C14: All recorded cash and bank balances actually exist
B15: =B14+1 -> 3 | C15: All cash and bank balances are recorded at appropriate values
B16: =B15+1 -> 4 | C16: All cash and bank balances recorded are owned by the client and title is also in the name of client
B17: =B16+1 -> 5 | C17: All cash and bank balances are presented and all disclosures have been given in accordance with the Fourth / Fifth Schedule of the Companies Act, 2017 and relevant IASs
B20: Sr. # | C20: Conclusion | D20: Satisfactory
D21: Yes/No | E21: Initials
B23: 1 | C23: The audit has been completed in accordance with Audit program.
B24: =B23+1 -> 2 | C24: The working papers demonstrate that adequate work has been undertaken.
B25: =B24+1 -> 3 | C25: The working papers contain sufficient information, details of significant features and notes of unusual matters to enable us to form an opinion on financial statements.
B26: =B25+1 -> 4 | C26: In my opinion above amounts are fairly stated and on a consistent basis with the previous period.

Sheet Lead
B1: =Index!$B$1 -> ABC & Co. | I1: =Index!E14 -> BS.15 - 2
B2: =Index!$B$2 -> (Chartered Accountants)
B4: =Index!$B$4 -> Client: | C4: =Index!$C$4 -> ABC Limited | H4: =Index!$G$4 -> Prepared by: | I4: =IF(Index!$H$4="","",Index!$H$4)
B5: =Index!$B$5 -> Period: | C5: =Index!$C$5 -> Year ended June 30, 2023 | H5: =Index!$G$5 -> Date prepared: | I5: =IF(Index!$H$5="","",Index!$H$5)
B6: =Index!$B$6 -> Head: | C6: =Index!$C$6 -> Cash and bank balance | H6: =Index!$G$6 -> Reviewed by: | I6: =IF(Index!$H$6="","",Index!$H$6)
H7: =Index!$G$7 -> Date reviewed: | I7: =IF(Index!$H$7="","",Index!$H$7)
B8: LEAD SCHEDULE
B9: Work performed
B10: Analytical Procedures:
B11: Compared current year balances with last year balances and ensured that any significant variation has been properly and logically reasoned.
B12: Obtained list of banks from client and documented logical commercial reasons for new bank accounts opened and closed during the year.
B14: Test of Details
B15: Attended year-end cash count and deposit verification.
B16: Performed cut-off procedures to ensure transactions are recorded in correct accounting period.
B17: Traced opening balance in general ledger from last year working papers
B18: Ensured that no balances are subject any encumbrance, if so then disclosure is made
B19: Obtained certificates of cash in hand and matched them to the accounting records and cash count report.
B20: Ensured that closing balances as per our working paper file are matched with general ledger.
... B27: Satisfactory
B29: Description | D29: W.P. Ref. | E29: 2021 | F29: =E29-1 -> 2020 | G29: Variance | H29: Variance | I29: Reason for Variance
E30: Rupees | F30: Rupees | G30: Rupees | H30: %
B32: Cash and bank balance
B33: Cash in hand
B34: - Cash in Hand - Imperest | G34: =E34-F34 -> 0 | H34: =IFERROR(G34/F34,"")
B35: - Cash in Hand - Petty Cash | G35: =E35-F35 -> 0 | H35: =IFERROR(G35/F35,"")
B36: - Cash in Transit | G36: =E36-F36 -> 0 | H36: =IFERROR(G36/F36,"")
B38: Cash at Bank
B39: on deposit account | G39: =E39-F39 -> 0 | H39: =IFERROR(G39/F39,"")
B40: on current account | G40: =E40-F40 -> 0 | H40: =IFERROR(G40/F40,"")
B41: other accounts | G41: =E41-F41 -> 0 | H41: =IFERROR(G41/F41,"")
B43: a) In Current Accounts
B44: Local Currency | G44: =E44-F44 -> 0 | H44: =IFERROR(G44/F44,"")
B45: Foreign Currency | G45: =E45-F45 -> 0 | H45: =IFERROR(G45/F45,"")
B47: b) In Deposit Accounts
B48: Local Currency | G48: =E48-F48 -> 0 | H48: =IFERROR(G48/F48,"")
B49: Foreign Currency | G49: =E49-F49 -> 0 | H49: =IFERROR(G49/F49,"")
B52: T O T A L | E52: =SUM(E31:E51) -> 0 | F52: =SUM(F31:F51) -> 0 | G52: =SUM(G31:G51) -> 0

Sheet SubLead
B1: =Index!$B$1 -> ABC & Co. | I1: =Index!E16 -> BS.15 - 3
B2: =Index!$B$2 -> (Chartered Accountants)
B4: =Index!$B$4 -> Client: | C4: =Index!$C$4 -> ABC Limited | H4: =Index!$G$4 -> Prepared by: | I4: =IF(Index!$H$4="","",Index!$H$4)
B5: =Index!$B$5 -> Period: | C5: =Index!$C$5 -> Year ended June 30, 2023 | H5: =Index!$G$5 -> Date prepared: | I5: =IF(Index!$H$5="","",Index!$H$5)
B6: =Index!$B$6 -> Head: | C6: =Index!$C$6 -> Cash and bank balance | H6: =Index!$G$6 -> Reviewed by: | I6: =IF(Index!$H$6="","",Index!$H$6)
B7: Subhead: | C7: =Lead!B38 -> Cash at Bank | H7: =Index!$G$7 -> Date reviewed: | I7: =IF(Index!$H$7="","",Index!$H$7)
B8: SUB-LEAD SCHEDULE
B9: Work performed
B10: Circularized banks balances confirmation and matched them to accounting records and bank statements.
B11: For significant variation between bank balances as per ledger and as per bank record, obtained bank reconciliation from management.
B12: Ensure that all balances and bank details reported by bank in replies to bank confirmation request are included in records of the client.
B13: Converted Foreign current accounts into functional currency of the company at the year-end rate.
B14: Ensured that all bank accounts are in company's name.
B15: Ensured that all bank accounts have been appropriately classified.
B16: Obtained and examined bank reconciliations to ensure the following:
B17: No long outstanding item should remain un-followed,
B18: No revenue nature item should be appearing
B19: No revenue nature item should be appearing
... B28: Satisfactory
B30: Description | D30: W.P. Ref. | E30: =Lead!E29 -> 2021 | F30: =Lead!F29 -> 2020 | G30: Variance | H30: Variance | I30: Reason for Variance
E31: Rupees | F31: Rupees | G31: Rupees | H31: %
B33: =Lead!B38 -> Cash at Bank
B34: In Current Accounts
B35: - Local Currency | G35: =E35-F35 -> 0 | H35: =IFERROR(G35/F35,"")
B36: - Foreign Currency | G36: =E36-F36 -> 0 | H36: =IFERROR(G36/F36,"")
B38: In Deposit Accounts
B39: - Local Currency | G39: =E39-F39 -> 0 | H39: =IFERROR(G39/F39,"")
B40: - Foreign Currency | G40: =E40-F40 -> 0 | H40: =IFERROR(G40/F40,"")
B42: Balances in transit | G42: =E42-F42 -> 0 | H42: =IFERROR(G42/F42,"")
B44: Total closing balance | E44: =SUM(E32:E43) -> 0 | F44: =SUM(F32:F43) -> 0 | G44: =SUM(G32:G43) -> 0

Sheet BankConfirmation-CS
B1: =Index!$B$1 -> ABC & Co. | I1: =Index!E18 -> BS.15 - 4
B2: =Index!$B$2 -> (Chartered Accountants)
B4: =Index!$B$4 -> Client: | C4: =Index!$C$4 -> ABC Limited | H4: =Index!$G$4 -> Prepared by: | I4: =IF(Index!$H$4="","",Index!$H$4)
B5: =Index!$B$5 -> Period: | C5: =Index!$C$5 -> Year ended June 30, 2023 | H5: =Index!$G$5 -> Date prepared: | I5: =IF(Index!$H$5="","",Index!$H$5)
B6: =Index!$B$6 -> Head: | C6: =Index!$C$6 -> Cash and bank balance | H6: =Index!$G$6 -> Reviewed by: | I6: =IF(Index!$H$6="","",Index!$H$6)
B7: Subhead: | C7: =SubLead!C7 -> Cash at Bank | H7: =Index!$G$7 -> Date reviewed: | I7: =IF(Index!$H$7="","",Index!$H$7)
B8: BANK CONFIRMATION - CONTROL SHEET
B9: Work performed
B11: Sr. # | C11: Bank Name | D11: Account Number | E11: Balance Amount | F11: Date - Confirmation Sent | G11: Balance Confirmed | H11: Difference | I11: Reason for Variance

Sheet Adjusting Entries
B1: =Index!$B$1 -> ABC & Co. | E1: =Index!E22 -> BS.15 - 6
B2: =Index!$B$2 -> (Chartered Accountants)
B4: =Index!$B$4 -> Client: | C4: =Index!$C$4 -> ABC Limited | D4: =Index!$G$4 -> Prepared by: | E4: =IF(Index!$H$4="","",Index!$H$4)
B5: =Index!$B$5 -> Period: | C5: =Index!$C$5 -> Year ended June 30, 2023 | D5: =Index!$G$5 -> Date prepared: | E5: =IF(Index!$H$5="","",Index!$H$5)
B6: =Index!$B$6 -> Head: | C6: =Index!$C$6 -> Cash and bank balance | D6: =Index!$G$6 -> Reviewed by: | E6: =IF(Index!$H$6="","",Index!$H$6)
D7: =Index!$G$7 -> Date reviewed: | E7: =IF(Index!$H$7="","",Index!$H$7)
B8: ADJUSTING ENTRIES
B10: Sr. # | C10: Entry Proposed | D10: Amount
D11: Debit | E11: Credit
