Workbook

Sheet Index
B1: ABC & Co. | F1: B.S.18
B2: (Chartered Accountants)
B4: Client: | C4: ABC Limited | E4: Prepared by:
B5: Period: | C5: Year ended June 30, 2023 | E5: Date prepared:
B6: Head: | C6: Long term financing - Related parties | E6: Reviewed by:
E7: Date reviewed:
B8: INDEX
B10: Sr. # | C10: Description | D10: W.P. Ref. | E10: Whether Placed in File | F10: Initials of Reviewer
B12: 1 | C12: Audit Objectives and Conclusions | D12: =$F$1&" - "&B12 -> B.S.18 - 1
B14: =B12+1 -> 2 | C14: Lead Schedule | D14: =$F$1&" - "&B14 -> B.S.18 - 2
B16: =B14+1 -> 3 | C16: Sub-Lead Schedule | D16: =$F$1&" - "&B16 -> B.S.18 - 3
B18: =B16+1 -> 4 | C18: Related information | D18: =$F$1&" - "&B18 -> B.S.18 - 4
B20: =B18+1 -> 5 | C20: Vouching for Loan obtained | D20: =$F$1&" - "&B20 -> B.S.18 - 5
B22: =B20+1 -> 6 | C22: Vouching for Loan repaid | D22: =$F$1&" - "&B22 -> B.S.18 - 6
B24: =B22+1 -> 7 | C24: Interest cost - Analytical procedures | D24: =$F$1&" - "&B24 -> B.S.18 - 7
B26: =B24+1 -> 8 | C26: Board minutes for major additions/deletions | D26: =$F$1&" - "&B26 -> B.S.18 - 8
B28: =B26+1 -> 9 | C28: Adjusting Entries | D28: =$F$1&" - "&B28 -> B.S.18 - 9

Sheet AOC
B1: =Index!$B$1 -> ABC & Co. | E1: =Index!D12 -> B.S.18 - 1
B2: =Index!$B$2 -> (Chartered Accountants)
B4: =Index!$B$4 -> Client: | C4: =Index!$C$4 -> ABC Limited | D4: =Index!$E$4 -> Prepared by: | E4: =IF(Index!$F$4="","",Index!$F$4)
B5: =Index!$B$5 -> Period: | C5: =Index!$C$5 -> Year ended June 30, 2023 | D5: =Index!$E$5 -> Date prepared: | E5: =IF(Index!$F$5="","",Index!$F$5)
B6: =Index!$B$6 -> Head: | C6: =Index!$C$6 -> Long term financing - Related parties | D6: =Index!$E$6 -> Reviewed by: | E6: =IF(Index!$F$6="","",Index!$F$6)
D7: =Index!$E$7 -> Date reviewed: | E7: =IF(Index!$F$7="","",Index!$F$7)
B8: =UPPER("Audit Objectives and Conclusions") -> AUDIT OBJECTIVES AND CONCLUSIONS
B10: Sr. # | C10: Audit Objectives | D10: Objective Met
D11: Yes/No | E11: Initials
B13: 1 | C13: All long term financing on the balance sheet represent valid claims by related parties.
B14: =B13+1 -> 2 | C14: To ensure that all goods and services received by the entity have been accounted for in the books of the company on a timely basis.
B15: =B14+1 -> 3 | C15: To ensure that liability is recorded at the correct amount.
B16: =B15+1 -> 4 | C16: Interest and finance cost has been accurately calculated and appropriately disclosed.
B17: =B16+1 -> 5 | C17: Long term financing is presented and all disclosures have been given in accordance with the Fifth Schedules of the Companies Act, 2017 and relevant IASs/IFRSs.
B20: Sr. # | C20: Conclusion | D20: Satisfactory
D21: Yes/No | E21: Initials
B23: 1 | C23: The audit has been completed in accordance with Audit program.
B24: =B23+1 -> 2 | C24: The working papers demonstrate that adequate work has been undertaken.
B25: =B24+1 -> 3 | C25: The working papers contain sufficient information, details of significant features and notes of unusual matters to enable us to form an opinion on financial statements.
B26: =B25+1 -> 4 | C26: In my opinion above amounts are fairly stated and on a consistent basis with the previous period.

Sheet Lead
B1: =Index!$B$1 -> ABC & Co. | I1: =Index!D14 -> B.S.18 - 2
B2: =Index!$B$2 -> (Chartered Accountants)
B4: =Index!$B$4 -> Client: | C4: =Index!$C$4 -> ABC Limited | H4: =Index!$E$4 -> Prepared by: | I4: =IF(Index!$F$4="","",Index!$F$4)
B5: =Index!$B$5 -> Period: | C5: =Index!$C$5 -> Year ended June 30, 2023 | H5: =Index!$E$5 -> Date prepared: | I5: =IF(Index!$F$5="","",Index!$F$5)
B6: =Index!$B$6 -> Head: | C6: =Index!$C$6 -> Long term financing - Related parties | H6: =Index!$E$6 -> Reviewed by: | I6: =IF(Index!$F$6="","",Index!$F$6)
H7: =Index!$E$7 -> Date reviewed: | I7: =IF(Index!$F$7="","",Index!$F$7)
B8: LEAD SCHEDULE
B9: Work performed
B10: Analytical Procedures:
B11: Compared current year balances with last year balances and ensured that any significant variation has been properly and logically reasoned.
B12: Test of Details
B13: Traced opening balances from loan register, general ledger and last year’s working papers.
B14: Obtained a schedule of long term financing (including debt outstanding at the end of the prior year, as well as any new debt) showing beginning and ending balances and borrowings and repayments during the year, and performed the following:
B16: Obtained assurance about the completeness of the schedule:
B17: (a) Made inquiries of knowledgeable management.
B18: (b) Considered any evidence of additional debt obtained through examination of minutes of the board, (when testing payables), and other documents.
B19: Tested the summarization and traced the ending balances to the general ledger.
B20: Tested the summarization and traced the ending balances to the general ledger.
... B35: Determined and ensured that disclosures have been made in accordance with the requirements of Fifth Schedule to the Companies Act, 2017 and the applicable IASs / IFRSs.
B43: Description | D43: W.P. Ref. | E43: 2021 | F43: =E43-1 -> 2020 | G43: Variance | H43: Variance | I43: Reason for Variance
E44: Rupees | F44: Rupees | G44: Rupees | H44: %
B46: Financing from Related Parties
B48: Party A | G48: =E48-F48 -> 0 | H48: =IFERROR(G48/F48,"")
B50: Party B | G50: =E50-F50 -> 0 | H50: =IFERROR(G50/F50,"")
B53: T O T A L | E53: =SUM(E45:E52) -> 0 | F53: =SUM(F45:F51) -> 0 | G53: =SUM(G45:G51) -> 0

Sheet SubLead
B1: =Index!$B$1 -> ABC & Co. | H1: =Index!D16 -> B.S.18 - 3
B2: =Index!$B$2 -> (Chartered Accountants)
B4: =Index!$B$4 -> Client: | C4: =Index!$C$4 -> ABC Limited | E4: =Index!$E$4 -> Prepared by: | F4: =IF(Index!$F$4="","",Index!$F$4)
B5: =Index!$B$5 -> Period: | C5: =Index!$C$5 -> Year ended June 30, 2023 | E5: =Index!$E$5 -> Date prepared: | F5: =IF(Index!$F$5="","",Index!$F$5)
B6: =Index!$B$6 -> Head: | C6: =Index!$C$6 -> Long term financing - Related parties | E6: =Index!$E$6 -> Reviewed by: | F6: =IF(Index!$F$6="","",Index!$F$6)
E7: =Index!$E$7 -> Date reviewed: | F7: =IF(Index!$F$7="","",Index!$F$7)
B8: SUB-LEAD SCHEDULE
B9: Work Performed
B10: Test of Details
B11: Obtained a schedule of accrued interest expense (which may be prepared in connection with the schedule of debt in Procedure 1 above).
B12: Tested the summarization and trace the total or the individual amounts, as applicable, to the general ledger.
B13: Made a selection of debt instruments tested in Procedure 1 and, for each item selected, performed the following:
B14: Based on the information in the confirmation concerning the date through which interest was paid and the applicable interest rate.
B15: Recomputed the amount of accrued interest.
B16: If the information needed to re-compute the amount was not confirmed:
B17: Examined the debt agreement evidencing the interest rate.
B18: Obtained and examined cash disbursement records (usually the paid check) evidencing the most recent payment of interest.
B19: Re-computed the amount of accrued interest.
... B46: Determined that the accounting policies and methods of recording debt are appropriate and applied consistently.
E48: W.P. Ref | F48: =Lead!E43 -> 2021 | H48: =F48-1 -> 2020
F49: ----------- Rupees -----------
B50: =Lead!B48 -> Party A | C50: Opening balance
C51: Obtained during the period
C52: Less: Repaid during the period
C53: Interest accrued
C54: Closing balance
B56: =Lead!B50 -> Party B | C56: Opening balance
C57: Obtained during the period
C58: Less: Repaid during the period
C59: Interest accrued
C60: Closing balance
B62: Closing Total

Sheet Loan Obtained-Vouching
B1: =Index!$B$1 -> ABC & Co. | O1: =Index!D20 -> B.S.18 - 5
B2: =Index!$B$2 -> (Chartered Accountants)
B4: =Index!$B$4 -> Client: | C4: =Index!$C$4 -> ABC Limited
B5: =Index!$B$5 -> Period: | C5: =Index!$C$5 -> Year ended June 30, 2023 | M5: =Index!$E$4 -> Prepared by: | N5: =IF(Index!$F$4="","",Index!$F$4)
B6: =Index!$B$6 -> Head: | C6: =Index!$C$6 -> Long term financing - Related parties | M6: =Index!$E$5 -> Date prepared: | N6: =IF(Index!$F$5="","",Index!$F$5)
M7: =Index!$E$6 -> Reviewed by: | N7: =IF(Index!$F$6="","",Index!$F$6)
M8: =Index!$E$7 -> Date reviewed: | N8: =IF(Index!$F$7="","",Index!$F$7)
B9: VOUCHING FOR LOAN OBTAINED
B10: Work Performed
B11: Checked supporting documents like loan agreements, minutes of the meetings and other evidences.
B12: Checked proper authorization and approval.
B13: Checked proper posting in general ledger.
B14: Ensured receipts are reflected in the bank statements.
B16: Date | C16: Voucher # | D16: Description of Transaction | E16: Bank Name | F16: Board Approval | G16: Minutes of Meetings | H16: Loan Agreement | I16: Loan Amount as per Agreement | J16: Loan amount as per ledger | K16: Proper Classification | L16: Traced in Bank | M16: Date of Receipt | N16: Interest charged? | O16: Interest amount

Sheet Repayment-Vouching
B1: =Index!$B$1 -> ABC & Co. | L1: =Index!D22 -> B.S.18 - 6
B2: =Index!$B$2 -> (Chartered Accountants)
B4: =Index!$B$4 -> Client: | C4: =Index!$C$4 -> ABC Limited
B5: =Index!$B$5 -> Period: | C5: =Index!$C$5 -> Year ended June 30, 2023 | K5: =Index!$E$4 -> Prepared by: | L5: =IF(Index!$F$4="","",Index!$F$4)
B6: =Index!$B$6 -> Head: | C6: =Index!$C$6 -> Long term financing - Related parties | K6: =Index!$E$5 -> Date prepared: | L6: =IF(Index!$F$5="","",Index!$F$5)
K7: =Index!$E$6 -> Reviewed by: | L7: =IF(Index!$F$6="","",Index!$F$6)
K8: =Index!$E$7 -> Date reviewed: | L8: =IF(Index!$F$7="","",Index!$F$7)
B9: VOUCHING FOR LOAN REPAID
B10: Work Performed
B11: Checked proper authorization and approval.
B12: Checked proper posting in general ledger.
B13: Ensured payments are reflected in the bank statements.
B14: Performed the above mentioned procedures to ensure various assertions
B16: Date | C16: Voucher # | D16: Description of Transaction | E16: Bank Name | F16: Date of Payment | G16: Repayment Amount (A) | H16: Approved by | I16: Traced in Bank | J16: Cheque # | K16: Cheque Amount (B) | L16: Difference in A and B
H37: =SUM(H16:H36) -> 0

Sheet Interest-AP
B1: =Index!$B$1 -> ABC & Co. | I1: =Index!D24 -> B.S.18 - 7
B2: =Index!$B$2 -> (Chartered Accountants)
B4: =Index!$B$4 -> Client: | C4: =Index!$C$4 -> ABC Limited | F4: =Index!$E$4 -> Prepared by: | G4: =IF(Index!$F$4="","",Index!$F$4)
B5: =Index!$B$5 -> Period: | C5: =Index!$C$5 -> Year ended June 30, 2023 | F5: =Index!$E$5 -> Date prepared: | G5: =IF(Index!$F$5="","",Index!$F$5)
B6: =Index!$B$6 -> Head: | C6: =Index!$C$6 -> Long term financing - Related parties | F6: =Index!$E$6 -> Reviewed by: | G6: =IF(Index!$F$6="","",Index!$F$6)
B7: Sub Head: | C7: =Lead!B46 -> Financing from Related Parties | F7: =Index!$E$7 -> Date reviewed: | G7: =IF(Index!$F$7="","",Index!$F$7)
B9: INTEREST EXPENSE - ANALYTICAL PROCEDURE
B10: Work Performed
B11: Analytical Procedures
B12: Calculated overall interest expense on loans for the year, and compared with recorded interest expense.
B13: Compare current year expenses with last year expenses and ensure that any significant variation should be properly and logically reasoned
B15: Test of Details
B16: Determined the reasonableness of accounting policy and amortization method, rates and their consistency with prior years.
B17: Checked calculation of amortization of selected assets.
B18: Ensured that none of the assets has been impaired or the recoverable amount of an asset is not less than its carrying amount.
B19: Ensured that any subsequent addition has been amortized over remaining useful life and not simply depreciated by applying the amortization rate.
B20: Determine that client's accounting policies for amortization are appropriate and applied consistently. See that intangible assets with indefinite life are subject to impairment review.
D22: =SubLead!B50 -> Party A | E22: =SubLead!B56 -> Party B | I22: Total
B24: Opening principal loan amount
B25: Opening accumulated interest cost
B26: Opening loan amount
B27: Rate of interest
B29: Interest on opening balance for the whole year
B30: Interest on loan obtained during the year
B31: Interest not charged on the loan repaid during the year
B32: Expected interest cost for the year
B33: Interest as per General Ledger
B34: Difference

Sheet Adjusting Entries
B1: =Index!$B$1 -> ABC & Co. | E1: =Index!D28 -> B.S.18 - 9
B2: =Index!$B$2 -> (Chartered Accountants)
B4: =Index!$B$4 -> Client: | C4: =Index!$C$4 -> ABC Limited | D4: =Index!$E$4 -> Prepared by: | E4: =IF(Index!$F$4="","",Index!$F$4)
B5: =Index!$B$5 -> Period: | C5: =Index!$C$5 -> Year ended June 30, 2023 | D5: =Index!$E$5 -> Date prepared: | E5: =IF(Index!$F$5="","",Index!$F$5)
B6: =Index!$B$6 -> Head: | C6: =Index!$C$6 -> Long term financing - Related parties | D6: =Index!$E$6 -> Reviewed by: | E6: =IF(Index!$F$6="","",Index!$F$6)
D7: =Index!$E$7 -> Date reviewed: | E7: =IF(Index!$F$7="","",Index!$F$7)
B8: ADJUSTING ENTRIES
B10: Sr. # | C10: Entry Proposed | D10: Amount
D11: Debit | E11: Credit
