Workbook

Sheet Index
B1: ABC & Co. | F1: B.S.23
B2: (Chartered Accountants)
B4: Client: | C4: ABC Limited | E4: Prepared by:
B5: Period: | C5: Year ended June 30, 2023 | E5: Date prepared:
B6: Head: | C6: Staff Retirement Benefits | E6: Reviewed by:
E7: Date reviewed:
B8: INDEX
B10: Sr. # | C10: Description | D10: W.P. Ref. | E10: Whether Placed in File | F10: Initials of Reviewer
B12: 1 | C12: Audit Objectives and Conclusions | D12: =$F$1&" - "&B12 -> B.S.23 - 1
B14: =B12+1 -> 2 | C14: Lead Schedule | D14: =$F$1&" - "&B14 -> B.S.23 - 2
B16: =B14+1 -> 3 | C16: Related information | D16: =$F$1&" - "&B16 -> B.S.23 - 3
B18: =B16+1 -> 4 | C18: Adjusting Entries | D18: =$F$1&" - "&B18 -> B.S.23 - 4

Sheet AOC
B1: =Index!B1 -> ABC & Co. | E1: =Index!D12 -> B.S.23 - 1
B2: =Index!B2 -> (Chartered Accountants)
B4: =Index!B4 -> Client: | C4: =Index!C4 -> ABC Limited | D4: =Index!$E$4 -> Prepared by: | E4: =IF(Index!$F$4="","",Index!$F$4)
B5: =Index!B5 -> Period: | C5: =Index!C5 -> Year ended June 30, 2023 | D5: =Index!$E$5 -> Date prepared: | E5: =IF(Index!$F$5="","",Index!$F$5)
B6: =Index!B6 -> Head: | C6: =Index!C6 -> Staff Retirement Benefits | D6: =Index!$E$6 -> Reviewed by: | E6: =IF(Index!$F$6="","",Index!$F$6)
D7: =Index!$E$7 -> Date reviewed: | E7: =IF(Index!$F$7="","",Index!$F$7)
B8: =UPPER("Audit Objectives and Conclusions") -> AUDIT OBJECTIVES AND CONCLUSIONS
B10: Sr. # | C10: Audit Objectives | D10: Objective Met
D11: Yes/No | E11: Initials
B13: 1 | C13: To ensure that staff retirement benefits represents amount owed to staff.
B14: =B13+1 -> 2 | C14: To ensure that staff retirement benefits represent obligations of the entity at the period end date.
B15: =B14+1 -> 3 | C15: To ensure that staff retirement benefits are recorded at the correct amount.
B16: =B15+1 -> 4 | C16: To ensure that staff retirement benefits have been presented, classified and disclosed in the financial statements in accordance with the requirements of applicable financial reporting framework i.e. Companies Act, 2017 and applicable International Financial Reporting Standards.
B19: Sr. # | C19: Conclusion | D19: Satisfactory
D20: Yes/No | E20: Initials
B22: 1 | C22: The audit has been completed in accordance with Audit program.
B23: =B22+1 -> 2 | C23: The working papers demonstrate that adequate work has been undertaken.
B24: =B23+1 -> 3 | C24: The working papers contain sufficient information, details of significant features and notes of unusual matters to enable us to form an opinion on financial statements.
B25: =B24+1 -> 4 | C25: In my opinion above amounts are fairly stated and on a consistent basis with the previous period.

Sheet Lead
B1: =Index!B1 -> ABC & Co. | I1: =Index!D14 -> B.S.23 - 2
B2: =Index!B2 -> (Chartered Accountants)
B4: =Index!B4 -> Client: | C4: =Index!C4 -> ABC Limited | H4: =Index!$E$4 -> Prepared by: | I4: =IF(Index!$F$4="","",Index!$F$4)
B5: =Index!B5 -> Period: | C5: =Index!C5 -> Year ended June 30, 2023 | H5: =Index!$E$5 -> Date prepared: | I5: =IF(Index!$F$5="","",Index!$F$5)
B6: =Index!B6 -> Head: | C6: =Index!C6 -> Staff Retirement Benefits | H6: =Index!$E$6 -> Reviewed by: | I6: =IF(Index!$F$6="","",Index!$F$6)
H7: =Index!$E$7 -> Date reviewed: | I7: =IF(Index!$F$7="","",Index!$F$7)
B8: LEAD SCHEDULE
B9: Work performed
B10: Analytical Procedures:
B11: Compared current year balances with last year balances and ensured that any significant variation has been properly and logically reasoned.
B12: Reviewed movement during the year in deferred taxation and ensured reasonableness of changes during the year.
B13: Test of Details
B14: Traced opening balances from last year's audited financial statements, general ledger and last year’s working papers.
B15: Ascertained the nature of change by inquiry or by reviewing prior year’s working papers
B16: Obtained copy of company’s rules and policies regarding staff gratuity.
B17: Verified the last salaries drawn by selected employees from payroll or salary sheet.
B18: For a sample of employees, checked the calculation of number of years completed from date of appointment to date of the balance sheet.
B19: Checked the calculation of charge of the gratuity for the year.
... B29: Satisfactory
B32: Description | D32: W.P. Ref. | E32: 2021 | F32: =E32-1 -> 2020 | G32: Variance | H32: Variance | I32: Reason for Variance
E33: Rupees | F33: Rupees | G33: Rupees | H33: %
B35: =Index!C6 -> Staff Retirement Benefits
B36: Opening balance | G36: =E36-F36 -> 0 | H36: =IFERROR(G36/F36,"")
B37: Charged / (Credited) to profit or loss | G37: =E37-F37 -> 0 | H37: =IFERROR(G37/F37,"")
B38: Charged / (Credited) to other comprehensive income | G38: =E38-F38 -> 0 | H38: =IFERROR(G38/F38,"")
B39: Payments made during the year
B42: T O T A L | E42: =SUM(E34:E41) -> 0 | F42: =SUM(F34:F38) -> 0 | G42: =SUM(G34:G38) -> 0

Sheet Adjusting Entries
B1: =Index!B1 -> ABC & Co. | E1: =Index!D18 -> B.S.23 - 4
B2: =Index!B2 -> (Chartered Accountants)
B4: =Index!B4 -> Client: | C4: =Index!C4 -> ABC Limited | D4: =Index!$E$4 -> Prepared by: | E4: =IF(Index!$F$4="","",Index!$F$4)
B5: =Index!B5 -> Period: | C5: =Index!C5 -> Year ended June 30, 2023 | D5: =Index!$E$5 -> Date prepared: | E5: =IF(Index!$F$5="","",Index!$F$5)
B6: =Index!B6 -> Head: | C6: =Index!C6 -> Staff Retirement Benefits | D6: =Index!$E$6 -> Reviewed by: | E6: =IF(Index!$F$6="","",Index!$F$6)
D7: =Index!$E$7 -> Date reviewed: | E7: =IF(Index!$F$7="","",Index!$F$7)
B8: ADJUSTING ENTRIES
B10: Sr. # | C10: Entry Proposed | D10: Amount
D11: Debit | E11: Credit
