Workbook

Sheet Index
B1: ABC & Co. | F1: B.S.27
B2: (Chartered Accountants)
B4: Client: | C4: ABC Limited | E4: Prepared by:
B5: Period: | C5: Year ended June 30, 2023 | E5: Date prepared:
B6: Head: | C6: Short term borrowings | E6: Reviewed by:
E7: Date reviewed:
B8: INDEX
B10: Sr. # | C10: Description | D10: W.P. Ref. | E10: Whether Placed in File | F10: Initials of Reviewer
B12: 1 | C12: Audit Objectives and Conclusions | D12: =$F$1&" - "&B12 -> B.S.27 - 1
B14: =B12+1 -> 2 | C14: Lead Schedule | D14: =$F$1&" - "&B14 -> B.S.27 - 2
B16: =B14+1 -> 3 | C16: Sub-Lead Schedule | D16: =$F$1&" - "&B16 -> B.S.27 - 3
B18: =B16+1 -> 4 | C18: Related information | D18: =$F$1&" - "&B18 -> B.S.27 - 4
B20: =B18+1 -> 5 | C20: Calculation of Markup on Short Term Borrowings | D20: =$F$1&" - "&B20 -> B.S.27 - 5
B22: =B20+1 -> 6 | C22: Interest cost - Analytical procedures | D22: =$F$1&" - "&B22 -> B.S.27 - 6
B24: =B22+1 -> 7 | C24: Board minutes for major additions/deletions | D24: =$F$1&" - "&B24 -> B.S.27 - 7
B26: =B24+1 -> 8 | C26: Adjusting Entries | D26: =$F$1&" - "&B26 -> B.S.27 - 8

Sheet AOC
B1: =Index!$B$1 -> ABC & Co. | E1: =Index!D12 -> B.S.27 - 1
B2: =Index!$B$2 -> (Chartered Accountants)
B4: =Index!$B$4 -> Client: | C4: =Index!$C$4 -> ABC Limited | D4: =Index!$E$4 -> Prepared by: | E4: =IF(Index!$F$4="","",Index!$F$4)
B5: =Index!$B$5 -> Period: | C5: =Index!$C$5 -> Year ended June 30, 2023 | D5: =Index!$E$5 -> Date prepared: | E5: =IF(Index!$F$5="","",Index!$F$5)
B6: =Index!$B$6 -> Head: | C6: =Index!$C$6 -> Short term borrowings | D6: =Index!$E$6 -> Reviewed by: | E6: =IF(Index!$F$6="","",Index!$F$6)
D7: =Index!$E$7 -> Date reviewed: | E7: =IF(Index!$F$7="","",Index!$F$7)
B8: =UPPER("Audit Objectives and Conclusions") -> AUDIT OBJECTIVES AND CONCLUSIONS
B10: Sr. # | C10: Audit Objectives | D10: Objective Met
D11: Yes/No | E11: Initials
B13: 1 | C13: To ensure that liability represents valid claims by lessor against assets leased to the entity under finance lease arrangements.
B14: =B13+1 -> 2 | C14: To ensure that the entire liability against finance lease arrangements has been accounted for in the books of the company on a timely basis.
B15: =B14+1 -> 3 | C15: To ensure that liability is recorded at the correct amount.
B16: =B15+1 -> 4 | C16: To ensure that the liability has been presented, classified and disclosed in the financial statements in accordance with the requirements of applicable financial reporting framework i.e. Companies Act, 2017 and applicable International Financial Reporting Standards.
B19: Sr. # | C19: Conclusion | D19: Satisfactory
D20: Yes/No | E20: Initials
B22: 1 | C22: The audit has been completed in accordance with Audit program.
B23: =B22+1 -> 2 | C23: The working papers demonstrate that adequate work has been undertaken.
B24: =B23+1 -> 3 | C24: The working papers contain sufficient information, details of significant features and notes of unusual matters to enable us to form an opinion on financial statements.
B25: =B24+1 -> 4 | C25: In my opinion above amounts are fairly stated and on a consistent basis with the previous period.

Sheet Lead
B1: =Index!$B$1 -> ABC & Co. | I1: =Index!D14 -> B.S.27 - 2
B2: =Index!$B$2 -> (Chartered Accountants)
B4: =Index!$B$4 -> Client: | C4: =Index!$C$4 -> ABC Limited | H4: =Index!$E$4 -> Prepared by: | I4: =IF(Index!$F$4="","",Index!$F$4)
B5: =Index!$B$5 -> Period: | C5: =Index!$C$5 -> Year ended June 30, 2023 | H5: =Index!$E$5 -> Date prepared: | I5: =IF(Index!$F$5="","",Index!$F$5)
B6: =Index!$B$6 -> Head: | C6: =Index!$C$6 -> Short term borrowings | H6: =Index!$E$6 -> Reviewed by: | I6: =IF(Index!$F$6="","",Index!$F$6)
H7: =Index!$E$7 -> Date reviewed: | I7: =IF(Index!$F$7="","",Index!$F$7)
B8: LEAD SCHEDULE
B9: Work performed
B10: Analytical Procedures:
B11: Compared current year balances with last year balances and ensured that any significant variation has been properly and logically reasoned.
B12: Review movement during the year in long term deposits and ensure reasonableness of changes during the year.
B13: Test of Details
B14: Obtained schedule(s) of Finance and operating leases (including any that existed at the end of the prior year, as well as any new leases).
B15: For finance leases, the schedule present beginning and ending balances and borrowings and repayments during the year.
B16: For operating leases, ensured that the schedule matches with current-year rent expense.
B17: To obtain assurance about the completeness of the schedule:
B18: Made inquiries of knowledgeable management.
B19: Considered any evidence of additional leases obtained through ;
... B33: Satisfactory
B35: Description | D35: W.P. Ref. | E35: 2023 | F35: =E35-1 -> 2022 | G35: Variance | H35: Variance | I35: Reason for Variance
E36: Rupees | F36: Rupees | G36: Rupees | H36: %
B38: Short term borrowings
B39: Running finance
B40: FIM | G40: =E40-F40 -> 0 | H40: =IFERROR(G40/F40,"")
B41: FATR
B42: Bank Overdraft | G42: =E42-F42 -> 0 | H42: =IFERROR(G42/F42,"")
B44: T O T A L | E44: =SUM(E37:E43) -> 0 | F44: =SUM(F37:F43) -> 0 | G44: =SUM(G37:G43) -> 0

Sheet SubLead
B1: =Index!$B$1 -> ABC & Co. | O1: =Index!D16 -> B.S.27 - 3
B2: =Index!$B$2 -> (Chartered Accountants)
B4: =Index!$B$4 -> Client: | C4: =Index!$C$4 -> ABC Limited | M4: =Index!$E$4 -> Prepared by:
B5: =Index!$B$5 -> Period: | C5: =Index!$C$5 -> Year ended June 30, 2023 | M5: =Index!$E$5 -> Date prepared:
B6: =Index!$B$6 -> Head: | C6: =Index!$C$6 -> Short term borrowings | M6: =Index!$E$6 -> Reviewed by:
B7: Sub Head: | C7: =Lead!B39 -> Running finance | M7: =Index!$E$7 -> Date reviewed:
B9: SUB-LEAD SCHEDULE
B10: Work Performed
B11: Test of Details
B12: Made a selection of finance leases. Prepared, or have the client prepared, confirmation requests, and perform the following:
B13: Ascertained that the confirmations request all information likely to be relevant to our tests of the leases and related interest balances
B14: For Example applicable interest rates, due dates, the date to which interest has been paid, and the nature and original value of the property leased).
B15: Mailed the request under our control to the lessor.
B16: Sent second requests for non-replies.
B17: Compared replies to requests. Prepared, or have the client prepared, reconciliations of exceptions. Traced reconciling items to supporting documents.
B19: Observations
B20: None.
B22: Conclusion
B23: Satisfactory
E25: W.P. Ref | G25: =Lead!E35 -> 2023 | I25: =G25-1 -> 2022 | K25: Balance Confirmed | M25: Difference | O25: Reconciliation Ref
G26: ----------- Rupees -----------
B28: Bank 1
B29: Bank 2
B30: Bank 3
B31: Bank 4
B32: Bank 5
B33: Bank 6
B34: Bank 7
B35: Bank 8
B36: Bank 9

Sheet Markup Detailed
B1: =Index!$B$1 -> ABC & Co. | S1: =Index!D20 -> B.S.27 - 5
B2: =Index!$B$2 -> (Chartered Accountants)
B4: =Index!$B$4 -> Client: | C4: =Index!$C$4 -> ABC Limited
B5: =Index!$B$5 -> Period: | C5: =Index!$C$5 -> Year ended June 30, 2023 | R5: =Index!$E$4 -> Prepared by: | S5: =IF(Index!$F$4="","",Index!$F$4)
B6: =Index!$B$6 -> Head: | C6: =Index!$C$6 -> Short term borrowings | R6: =Index!$E$5 -> Date prepared: | S6: =IF(Index!$F$5="","",Index!$F$5)
B7: Sub Head: | R7: =Index!$E$6 -> Reviewed by: | S7: =IF(Index!$F$6="","",Index!$F$6)
R8: =Index!$E$7 -> Date reviewed: | S8: =IF(Index!$F$7="","",Index!$F$7)
B9: Calculation of Markup on Short Term Borrowings
B11: Work Performed
B12: Verified the receipts of short term borrowings from bank statements.
B13: Ensured proper bifurcation of principal paid and finance charges paid.
B14: Verified payment from bank statements.
B15: Reviewed calculation of financial charges.
B16: Reviewed bank facility letters for Interest rates working.
B17: Obtained Kibor rates from www.sbp.org.pk
B18: Agreed with general ledger and final accounts.
B19: Checked the Declaration date, Maturity date and transaction amount from the bank debit advice.
B20: Recalculated the interest expense and Proposed the adjusting entry for the difference in expense as per ledger and as per our calculation.
B22: Observations
... B26: Satisfactory
B28: Declaration Date | C28: Maturity Date | D28: Year Ended (30 June 20XX)? | E28: Days Outstanding till Maturity | F28: Days Outstanding till Year end date | G28: Transaction Amount | H28: KIBOR | I28: Factor | J28: Rate | K28: Floor | L28: Amount till Maturity | M28: Amount till year end date | N28: As per Ledger | O28: Difference | P28: Difference as per our calculation | Q28: Traced interest payment in bank statement | R28: Traced disbursement of funds in bank statement | S28: Traced repayment in bank statements
L49: =SUM(L28:L48) -> 0
B52: C. Evaluate results of the tests.
E55: Opening Payable
E56: Profit Payable on Utilization during the year
E57: Payment During the year
E58: Closing Payable

Sheet Interest-AP
B1: =Index!$B$1 -> ABC & Co. | I1: =Index!D22 -> B.S.27 - 6
B2: =Index!$B$2 -> (Chartered Accountants)
B4: =Index!$B$4 -> Client: | C4: =Index!$C$4 -> ABC Limited | F4: =Index!$E$4 -> Prepared by: | G4: =IF(Index!$F$4="","",Index!$F$4)
B5: =Index!$B$5 -> Period: | C5: =Index!$C$5 -> Year ended June 30, 2023 | F5: =Index!$E$5 -> Date prepared: | G5: =IF(Index!$F$5="","",Index!$F$5)
B6: =Index!$B$6 -> Head: | C6: =Index!$C$6 -> Short term borrowings | F6: =Index!$E$6 -> Reviewed by: | G6: =IF(Index!$F$6="","",Index!$F$6)
B7: Sub Head: | C7: =Lead!B38 -> Short term borrowings | F7: =Index!$E$7 -> Date reviewed: | G7: =IF(Index!$F$7="","",Index!$F$7)
B9: INTEREST EXPENSE - ANALYTICAL PROCEDURE
B10: Work Performed
B11: Analytical Procedures
B12: Calculated overall interest expense on loans for the year, and compared with recorded interest expense.
B13: Compare current year expenses with last year expenses and ensure that any significant variation should be properly and logically reasoned
B15: Test of Details
B16: Determined the reasonableness of accounting policy and its consistency with prior years.
B17: Ensured that any subsequent addition has been appropriately incorporated in the schedule.
B19: Observations
B20: None.
B22: Conclusion
B23: Satisfactory
D26: =SubLead!B27 -> 0 | E26: =SubLead!B33 -> Bank 6 | I26: Total
B28: Opening principal loan amount
B29: Opening accumulated interest cost
B30: Opening loan amount
B31: Rate of interest
B33: Interest on opening balance for the whole year
B34: Interest on loan obtained during the year
B35: Interest not charged on the loan repaid during the year
B36: Expected interest cost for the year
B37: Interest as per General Ledger
B38: Difference

Sheet Adjusting Entries
B1: =Index!$B$1 -> ABC & Co. | E1: =Index!D26 -> B.S.27 - 8
B2: =Index!$B$2 -> (Chartered Accountants)
B4: =Index!$B$4 -> Client: | C4: =Index!$C$4 -> ABC Limited | D4: =Index!$E$4 -> Prepared by: | E4: =IF(Index!$F$4="","",Index!$F$4)
B5: =Index!$B$5 -> Period: | C5: =Index!$C$5 -> Year ended June 30, 2023 | D5: =Index!$E$5 -> Date prepared: | E5: =IF(Index!$F$5="","",Index!$F$5)
B6: =Index!$B$6 -> Head: | C6: =Index!$C$6 -> Short term borrowings | D6: =Index!$E$6 -> Reviewed by: | E6: =IF(Index!$F$6="","",Index!$F$6)
D7: =Index!$E$7 -> Date reviewed: | E7: =IF(Index!$F$7="","",Index!$F$7)
B8: ADJUSTING ENTRIES
B10: Sr. # | C10: Entry Proposed | D10: Amount
D11: Debit | E11: Credit
